Workbook

Sheet BancoAjustado
A1: Seção | B1: Divisão | C1: Grupo | D1: Classe | E1: Subclasse | F1: Seção | G1: Divisão | H1: Grupo | I1: Classe | J1: Subclasse | K1: Subclasse | L1: e_obj4 | M1: com_agr | N1: com_min
A2: A | B2: 01 | C2: 011 | D2: 01113 | E2: 0111301 | F2: =VLOOKUP(A2,Base!$A:$F,6,FALSE) -> AGRICULTURA, PECUÁRIA, PRODUÇÃO FLORESTAL, PESCA E AQUICULTURA | G2: =VLOOKUP(B2,Base!$B:$F,5,FALSE) -> AGRICULTURA, PECUÁRIA E SERVIÇOS RELACIONADOS | H2: =VLOOKUP(C2,Base!$C:$F,4,FALSE) -> Produção de lavouras temporárias | I2: =VLOOKUP(D2,Base!$D:$F,3,FALSE) -> Cultivo de cereais | J2: =VLOOKUP(E2,Base!$E:$F,2,FALSE) -> Cultivo de arroz | K2: 0111301 | L2: =IFERROR(VLOOKUP($K2,Base_Atividades!$E$1:$N$2398,MATCH(BancoAjustado!L$1,Base_Atividades!$E$1:$N$1,0),FALSE),0) -> 1 | M2: =IFERROR(VLOOKUP($K2,Base_Atividades!$E$1:$N$2398,MATCH(BancoAjustado!M$1,Base_Atividades!$E$1:$N$1,0),FALSE),0) -> 0 | N2: =IFERROR(VLOOKUP($K2,Base_Atividades!$E$1:$N$2398,MATCH(BancoAjustado!N$1,Base_Atividades!$E$1:$N$1,0),FALSE),0) -> 0
A3: A | B3: 01 | C3: 011 | D3: 01113 | E3: 0111302 | F3: =VLOOKUP(A3,Base!$A:$F,6,FALSE) -> AGRICULTURA, PECUÁRIA, PRODUÇÃO FLORESTAL, PESCA E AQUICULTURA | G3: =VLOOKUP(B3,Base!$B:$F,5,FALSE) -> AGRICULTURA, PECUÁRIA E SERVIÇOS RELACIONADOS | H3: =VLOOKUP(C3,Base!$C:$F,4,FALSE) -> Produção de lavouras temporárias | I3: =VLOOKUP(D3,Base!$D:$F,3,FALSE) -> Cultivo de cereais | J3: =VLOOKUP(E3,Base!$E:$F,2,FALSE) -> Cultivo de milho | K3: 0111302 | L3: =IFERROR(VLOOKUP($K3,Base_Atividades!$E$1:$N$2398,MATCH(BancoAjustado!L$1,Base_Atividades!$E$1:$N$1,0),FALSE),0) -> 0 | M3: =IFERROR(VLOOKUP($K3,Base_Atividades!$E$1:$N$2398,MATCH(BancoAjustado!M$1,Base_Atividades!$E$1:$N$1,0),FALSE),0) -> 1 | N3: =IFERROR(VLOOKUP($K3,Base_Atividades!$E$1:$N$2398,MATCH(BancoAjustado!N$1,Base_Atividades!$E$1:$N$1,0),FALSE),0) -> 0
A4: A | B4: 01 | C4: 011 | D4: 01113 | E4: 0111303 | F4: =VLOOKUP(A4,Base!$A:$F,6,FALSE) -> AGRICULTURA, PECUÁRIA, PRODUÇÃO FLORESTAL, PESCA E AQUICULTURA | G4: =VLOOKUP(B4,Base!$B:$F,5,FALSE) -> AGRICULTURA, PECUÁRIA E SERVIÇOS RELACIONADOS | H4: =VLOOKUP(C4,Base!$C:$F,4,FALSE) -> Produção de lavouras temporárias | I4: =VLOOKUP(D4,Base!$D:$F,3,FALSE) -> Cultivo de cereais | J4: =VLOOKUP(E4,Base!$E:$F,2,FALSE) -> Cultivo de trigo | K4: 0111303 | L4: =IFERROR(VLOOKUP($K4,Base_Atividades!$E$1:$N$2398,MATCH(BancoAjustado!L$1,Base_Atividades!$E$1:$N$1,0),FALSE),0) -> 0 | M4: =IFERROR(VLOOKUP($K4,Base_Atividades!$E$1:$N$2398,MATCH(BancoAjustado!M$1,Base_Atividades!$E$1:$N$1,0),FALSE),0) -> 1 | N4: =IFERROR(VLOOKUP($K4,Base_Atividades!$E$1:$N$2398,MATCH(BancoAjustado!N$1,Base_Atividades!$E$1:$N$1,0),FALSE),0) -> 0
A5: A | B5: 01 | C5: 011 | D5: 01113 | E5: 0111399 | F5: =VLOOKUP(A5,Base!$A:$F,6,FALSE) -> AGRICULTURA, PECUÁRIA, PRODUÇÃO FLORESTAL, PESCA E AQUICULTURA | G5: =VLOOKUP(B5,Base!$B:$F,5,FALSE) -> AGRICULTURA, PECUÁRIA E SERVIÇOS RELACIONADOS | H5: =VLOOKUP(C5,Base!$C:$F,4,FALSE) -> Produção de lavouras temporárias | I5: =VLOOKUP(D5,Base!$D:$F,3,FALSE) -> Cultivo de cereais | J5: =VLOOKUP(E5,Base!$E:$F,2,FALSE) -> Cultivo de outros cereais não especificados anteriormente | K5: 0111399 | L5: =IFERROR(VLOOKUP($K5,Base_Atividades!$E$1:$N$2398,MATCH(BancoAjustado!L$1,Base_Atividades!$E$1:$N$1,0),FALSE),0) -> 1 | M5: =IFERROR(VLOOKUP($K5,Base_Atividades!$E$1:$N$2398,MATCH(BancoAjustado!M$1,Base_Atividades!$E$1:$N$1,0),FALSE),0) -> 0 | N5: =IFERROR(VLOOKUP($K5,Base_Atividades!$E$1:$N$2398,MATCH(BancoAjustado!N$1,Base_Atividades!$E$1:$N$1,0),FALSE),0) -> 0
A6: A | B6: 01 | C6: 011 | D6: 01121 | E6: 0112101 | F6: =VLOOKUP(A6,Base!$A:$F,6,FALSE) -> AGRICULTURA, PECUÁRIA, PRODUÇÃO FLORESTAL, PESCA E AQUICULTURA | G6: =VLOOKUP(B6,Base!$B:$F,5,FALSE) -> AGRICULTURA, PECUÁRIA E SERVIÇOS RELACIONADOS | H6: =VLOOKUP(C6,Base!$C:$F,4,FALSE) -> Produção de lavouras temporárias | I6: =VLOOKUP(D6,Base!$D:$F,3,FALSE) -> Cultivo de algodão herbáceo e de outras fibras de lavoura temporária | J6: =VLOOKUP(E6,Base!$E:$F,2,FALSE) -> Cultivo de algodão herbáceo | K6: 0112101 | L6: =IFERROR(VLOOKUP($K6,Base_Atividades!$E$1:$N$2398,MATCH(BancoAjustado!L$1,Base_Atividades!$E$1:$N$1,0),FALSE),0) -> 0 | M6: =IFERROR(VLOOKUP($K6,Base_Atividades!$E$1:$N$2398,MATCH(BancoAjustado!M$1,Base_Atividades!$E$1:$N$1,0),FALSE),0) -> 1 | N6: =IFERROR(VLOOKUP($K6,Base_Atividades!$E$1:$N$2398,MATCH(BancoAjustado!N$1,Base_Atividades!$E$1:$N$1,0),FALSE),0) -> 0
A7: A | B7: 01 | C7: 011 | D7: 01121 | E7: 0112102 | F7: =VLOOKUP(A7,Base!$A:$F,6,FALSE) -> AGRICULTURA, PECUÁRIA, PRODUÇÃO FLORESTAL, PESCA E AQUICULTURA | G7: =VLOOKUP(B7,Base!$B:$F,5,FALSE) -> AGRICULTURA, PECUÁRIA E SERVIÇOS RELACIONADOS | H7: =VLOOKUP(C7,Base!$C:$F,4,FALSE) -> Produção de lavouras temporárias | I7: =VLOOKUP(D7,Base!$D:$F,3,FALSE) -> Cultivo de algodão herbáceo e de outras fibras de lavoura temporária | J7: =VLOOKUP(E7,Base!$E:$F,2,FALSE) -> Cultivo de juta | K7: 0112102 | L7: =IFERROR(VLOOKUP($K7,Base_Atividades!$E$1:$N$2398,MATCH(BancoAjustado!L$1,Base_Atividades!$E$1:$N$1,0),FALSE),0) -> 1 | M7: =IFERROR(VLOOKUP($K7,Base_Atividades!$E$1:$N$2398,MATCH(BancoAjustado!M$1,Base_Atividades!$E$1:$N$1,0),FALSE),0) -> 0 | N7: =IFERROR(VLOOKUP($K7,Base_Atividades!$E$1:$N$2398,MATCH(BancoAjustado!N$1,Base_Atividades!$E$1:$N$1,0),FALSE),0) -> 0
A8: A | B8: 01 | C8: 011 | D8: 01121 | E8: 0112199 | F8: =VLOOKUP(A8,Base!$A:$F,6,FALSE) -> AGRICULTURA, PECUÁRIA, PRODUÇÃO FLORESTAL, PESCA E AQUICULTURA | G8: =VLOOKUP(B8,Base!$B:$F,5,FALSE) -> AGRICULTURA, PECUÁRIA E SERVIÇOS RELACIONADOS | H8: =VLOOKUP(C8,Base!$C:$F,4,FALSE) -> Produção de lavouras temporárias | I8: =VLOOKUP(D8,Base!$D:$F,3,FALSE) -> Cultivo de algodão herbáceo e de outras fibras de lavoura temporária | J8: =VLOOKUP(E8,Base!$E:$F,2,FALSE) -> Cultivo de outras fibras de lavoura temporária não especificadas anteriormente | K8: 0112199 | L8: =IFERROR(VLOOKUP($K8,Base_Atividades!$E$1:$N$2398,MATCH(BancoAjustado!L$1,Base_Atividades!$E$1:$N$1,0),FALSE),0) -> 1 | M8: =IFERROR(VLOOKUP($K8,Base_Atividades!$E$1:$N$2398,MATCH(BancoAjustado!M$1,Base_Atividades!$E$1:$N$1,0),FALSE),0) -> 0 | N8: =IFERROR(VLOOKUP($K8,Base_Atividades!$E$1:$N$2398,MATCH(BancoAjustado!N$1,Base_Atividades!$E$1:$N$1,0),FALSE),0) -> 0
A9: A | B9: 01 | C9: 011 | D9: 01130 | E9: 0113000 | F9: =VLOOKUP(A9,Base!$A:$F,6,FALSE) -> AGRICULTURA, PECUÁRIA, PRODUÇÃO FLORESTAL, PESCA E AQUICULTURA | G9: =VLOOKUP(B9,Base!$B:$F,5,FALSE) -> AGRICULTURA, PECUÁRIA E SERVIÇOS RELACIONADOS | H9: =VLOOKUP(C9,Base!$C:$F,4,FALSE) -> Produção de lavouras temporárias | I9: =VLOOKUP(D9,Base!$D:$F,3,FALSE) -> Cultivo de cana-de-açúcar | J9: =VLOOKUP(E9,Base!$E:$F,2,FALSE) -> Cultivo de cana-de-açúcar | K9: 0113000 | L9: =IFERROR(VLOOKUP($K9,Base_Atividades!$E$1:$N$2398,MATCH(BancoAjustado!L$1,Base_Atividades!$E$1:$N$1,0),FALSE),0) -> 0 | M9: =IFERROR(VLOOKUP($K9,Base_Atividades!$E$1:$N$2398,MATCH(BancoAjustado!M$1,Base_Atividades!$E$1:$N$1,0),FALSE),0) -> 1 | N9: =IFERROR(VLOOKUP($K9,Base_Atividades!$E$1:$N$2398,MATCH(BancoAjustado!N$1,Base_Atividades!$E$1:$N$1,0),FALSE),0) -> 0
A10: A | B10: 01 | C10: 011 | D10: 01148 | E10: 0114800 | F10: =VLOOKUP(A10,Base!$A:$F,6,FALSE) -> AGRICULTURA, PECUÁRIA, PRODUÇÃO FLORESTAL, PESCA E AQUICULTURA | G10: =VLOOKUP(B10,Base!$B:$F,5,FALSE) -> AGRICULTURA, PECUÁRIA E SERVIÇOS RELACIONADOS | H10: =VLOOKUP(C10,Base!$C:$F,4,FALSE) -> Produção de lavouras temporárias | I10: =VLOOKUP(D10,Base!$D:$F,3,FALSE) -> Cultivo de fumo | J10: =VLOOKUP(E10,Base!$E:$F,2,FALSE) -> Cultivo de fumo | K10: 0114800 | L10: =IFERROR(VLOOKUP($K10,Base_Atividades!$E$1:$N$2398,MATCH(BancoAjustado!L$1,Base_Atividades!$E$1:$N$1,0),FALSE),0) -> 0 | M10: =IFERROR(VLOOKUP($K10,Base_Atividades!$E$1:$N$2398,MATCH(BancoAjustado!M$1,Base_Atividades!$E$1:$N$1,0),FALSE),0) -> 0 | N10: =IFERROR(VLOOKUP($K10,Base_Atividades!$E$1:$N$2398,MATCH(BancoAjustado!N$1,Base_Atividades!$E$1:$N$1,0),FALSE),0) -> 0
A11: A | B11: 01 | C11: 011 | D11: 01156 | E11: 0115600 | F11: =VLOOKUP(A11,Base!$A:$F,6,FALSE) -> AGRICULTURA, PECUÁRIA, PRODUÇÃO FLORESTAL, PESCA E AQUICULTURA | G11: =VLOOKUP(B11,Base!$B:$F,5,FALSE) -> AGRICULTURA, PECUÁRIA E SERVIÇOS RELACIONADOS | H11: =VLOOKUP(C11,Base!$C:$F,4,FALSE) -> Produção de lavouras temporárias | I11: =VLOOKUP(D11,Base!$D:$F,3,FALSE) -> Cultivo de soja | J11: =VLOOKUP(E11,Base!$E:$F,2,FALSE) -> Cultivo de soja | K11: 0115600 | L11: =IFERROR(VLOOKUP($K11,Base_Atividades!$E$1:$N$2398,MATCH(BancoAjustado!L$1,Base_Atividades!$E$1:$N$1,0),FALSE),0) -> 0 | M11: =IFERROR(VLOOKUP($K11,Base_Atividades!$E$1:$N$2398,MATCH(BancoAjustado!M$1,Base_Atividades!$E$1:$N$1,0),FALSE),0) -> 1 | N11: =IFERROR(VLOOKUP($K11,Base_Atividades!$E$1:$N$2398,MATCH(BancoAjustado!N$1,Base_Atividades!$E$1:$N$1,0),FALSE),0) -> 0
A12: A | B12: 01 | C12: 011 | D12: 01164 | E12: 0116401 | F12: =VLOOKUP(A12,Base!$A:$F,6,FALSE) -> AGRICULTURA, PECUÁRIA, PRODUÇÃO FLORESTAL, PESCA E AQUICULTURA | G12: =VLOOKUP(B12,Base!$B:$F,5,FALSE) -> AGRICULTURA, PECUÁRIA E SERVIÇOS RELACIONADOS | H12: =VLOOKUP(C12,Base!$C:$F,4,FALSE) -> Produção de lavouras temporárias | I12: =VLOOKUP(D12,Base!$D:$F,3,FALSE) -> Cultivo de oleaginosas de lavoura temporária, exceto soja | J12: =VLOOKUP(E12,Base!$E:$F,2,FALSE) -> Cultivo de amendoim | K12: 0116401 | L12: =IFERROR(VLOOKUP($K12,Base_Atividades!$E$1:$N$2398,MATCH(BancoAjustado!L$1,Base_Atividades!$E$1:$N$1,0),FALSE),0) -> 1 | M12: =IFERROR(VLOOKUP($K12,Base_Atividades!$E$1:$N$2398,MATCH(BancoAjustado!M$1,Base_Atividades!$E$1:$N$1,0),FALSE),0) -> 0 | N12: =IFERROR(VLOOKUP($K12,Base_Atividades!$E$1:$N$2398,MATCH(BancoAjustado!N$1,Base_Atividades!$E$1:$N$1,0),FALSE),0) -> 0
A13: A | B13: 01 | C13: 011 | D13: 01164 | E13: 0116402 | F13: =VLOOKUP(A13,Base!$A:$F,6,FALSE) -> AGRICULTURA, PECUÁRIA, PRODUÇÃO FLORESTAL, PESCA E AQUICULTURA | G13: =VLOOKUP(B13,Base!$B:$F,5,FALSE) -> AGRICULTURA, PECUÁRIA E SERVIÇOS RELACIONADOS | H13: =VLOOKUP(C13,Base!$C:$F,4,FALSE) -> Produção de lavouras temporárias | I13: =VLOOKUP(D13,Base!$D:$F,3,FALSE) -> Cultivo de oleaginosas de lavoura temporária, exceto soja | J13: =VLOOKUP(E13,Base!$E:$F,2,FALSE) -> Cultivo de girassol | K13: 0116402 | L13: =IFERROR(VLOOKUP($K13,Base_Atividades!$E$1:$N$2398,MATCH(BancoAjustado!L$1,Base_Atividades!$E$1:$N$1,0),FALSE),0) -> 1 | M13: =IFERROR(VLOOKUP($K13,Base_Atividades!$E$1:$N$2398,MATCH(BancoAjustado!M$1,Base_Atividades!$E$1:$N$1,0),FALSE),0) -> 0 | N13: =IFERROR(VLOOKUP($K13,Base_Atividades!$E$1:$N$2398,MATCH(BancoAjustado!N$1,Base_Atividades!$E$1:$N$1,0),FALSE),0) -> 0
... A346: C | B346: 20 | C346: 209 | D346: 20991 | E346: 2099199 | F346: =VLOOKUP(A346,Base!$A:$F,6,FALSE) -> INDÚSTRIAS DE TRANSFORMAÇÃO | G346: =VLOOKUP(B346,Base!$B:$F,5,FALSE) -> FABRICAÇÃO DE PRODUTOS QUÍMICOS | H346: =VLOOKUP(C346,Base!$C:$F,4,FALSE) -> Fabricação de produtos e preparados químicos diversos | I346: =VLOOKUP(D346,Base!$D:$F,3,FALSE) -> Fabricação de produtos químicos não especificados anteriormente | J346: =VLOOKUP(E346,Base!$E:$F,2,FALSE) -> Fabricação de outros produtos químicos não especificados anteriormente | K346: 2099199 | L346: =IFERROR(VLOOKUP($K346,Base_Atividades!$E$1:$N$2398,MATCH(BancoAjustado!L$1,Base_Atividades!$E$1:$N$1,0),FALSE),0) -> 1 | M346: =IFERROR(VLOOKUP($K346,Base_Atividades!$E$1:$N$2398,MATCH(BancoAjustado!M$1,Base_Atividades!$E$1:$N$1,0),FALSE),0) -> 0 | N346: =IFERROR(VLOOKUP($K346,Base_Atividades!$E$1:$N$2398,MATCH(BancoAjustado!N$1,Base_Atividades!$E$1:$N$1,0),FALSE),0) -> 0
A347: C | B347: 21 | C347: 211 | D347: 21106 | E347: 2110600 | F347: =VLOOKUP(A347,Base!$A:$F,6,FALSE) -> INDÚSTRIAS DE TRANSFORMAÇÃO | G347: =VLOOKUP(B347,Base!$B:$F,5,FALSE) -> FABRICAÇÃO DE PRODUTOS FARMOQUÍMICOS E FARMACÊUTICOS | H347: =VLOOKUP(C347,Base!$C:$F,4,FALSE) -> Fabricação de produtos farmoquímicos | I347: =VLOOKUP(D347,Base!$D:$F,3,FALSE) -> Fabricação de produtos farmoquímicos | J347: =VLOOKUP(E347,Base!$E:$F,2,FALSE) -> Fabricação de produtos farmoquímicos | K347: 2110600 | L347: =IFERROR(VLOOKUP($K347,Base_Atividades!$E$1:$N$2398,MATCH(BancoAjustado!L$1,Base_Atividades!$E$1:$N$1,0),FALSE),0) -> 1 | M347: =IFERROR(VLOOKUP($K347,Base_Atividades!$E$1:$N$2398,MATCH(BancoAjustado!M$1,Base_Atividades!$E$1:$N$1,0),FALSE),0) -> 0 | N347: =IFERROR(VLOOKUP($K347,Base_Atividades!$E$1:$N$2398,MATCH(BancoAjustado!N$1,Base_Atividades!$E$1:$N$1,0),FALSE),0) -> 0
A348: C | B348: 21 | C348: 212 | D348: 21211 | E348: 2121101 | F348: =VLOOKUP(A348,Base!$A:$F,6,FALSE) -> INDÚSTRIAS DE TRANSFORMAÇÃO | G348: =VLOOKUP(B348,Base!$B:$F,5,FALSE) -> FABRICAÇÃO DE PRODUTOS FARMOQUÍMICOS E FARMACÊUTICOS | H348: =VLOOKUP(C348,Base!$C:$F,4,FALSE) -> Fabricação de produtos farmacêuticos | I348: =VLOOKUP(D348,Base!$D:$F,3,FALSE) -> Fabricação de medicamentos para uso humano | J348: =VLOOKUP(E348,Base!$E:$F,2,FALSE) -> Fabricação de medicamentos alopáticos para uso humano | K348: 2121101 | L348: =IFERROR(VLOOKUP($K348,Base_Atividades!$E$1:$N$2398,MATCH(BancoAjustado!L$1,Base_Atividades!$E$1:$N$1,0),FALSE),0) -> 1 | M348: =IFERROR(VLOOKUP($K348,Base_Atividades!$E$1:$N$2398,MATCH(BancoAjustado!M$1,Base_Atividades!$E$1:$N$1,0),FALSE),0) -> 0 | N348: =IFERROR(VLOOKUP($K348,Base_Atividades!$E$1:$N$2398,MATCH(BancoAjustado!N$1,Base_Atividades!$E$1:$N$1,0),FALSE),0) -> 0
A349: C | B349: 21 | C349: 212 | D349: 21211 | E349: 2121102 | F349: =VLOOKUP(A349,Base!$A:$F,6,FALSE) -> INDÚSTRIAS DE TRANSFORMAÇÃO | G349: =VLOOKUP(B349,Base!$B:$F,5,FALSE) -> FABRICAÇÃO DE PRODUTOS FARMOQUÍMICOS E FARMACÊUTICOS | H349: =VLOOKUP(C349,Base!$C:$F,4,FALSE) -> Fabricação de produtos farmacêuticos | I349: =VLOOKUP(D349,Base!$D:$F,3,FALSE) -> Fabricação de medicamentos para uso humano | J349: =VLOOKUP(E349,Base!$E:$F,2,FALSE) -> Fabricação de medicamentos homeopáticos para uso humano | K349: 2121102 | L349: =IFERROR(VLOOKUP($K349,Base_Atividades!$E$1:$N$2398,MATCH(BancoAjustado!L$1,Base_Atividades!$E$1:$N$1,0),FALSE),0) -> 1 | M349: =IFERROR(VLOOKUP($K349,Base_Atividades!$E$1:$N$2398,MATCH(BancoAjustado!M$1,Base_Atividades!$E$1:$N$1,0),FALSE),0) -> 0 | N349: =IFERROR(VLOOKUP($K349,Base_Atividades!$E$1:$N$2398,MATCH(BancoAjustado!N$1,Base_Atividades!$E$1:$N$1,0),FALSE),0) -> 0
A350: C | B350: 21 | C350: 212 | D350: 21211 | E350: 2121103 | F350: =VLOOKUP(A350,Base!$A:$F,6,FALSE) -> INDÚSTRIAS DE TRANSFORMAÇÃO | G350: =VLOOKUP(B350,Base!$B:$F,5,FALSE) -> FABRICAÇÃO DE PRODUTOS FARMOQUÍMICOS E FARMACÊUTICOS | H350: =VLOOKUP(C350,Base!$C:$F,4,FALSE) -> Fabricação de produtos farmacêuticos | I350: =VLOOKUP(D350,Base!$D:$F,3,FALSE) -> Fabricação de medicamentos para uso humano | J350: =VLOOKUP(E350,Base!$E:$F,2,FALSE) -> Fabricação de medicamentos fitoterápicos para uso humano | K350: 2121103 | L350: =IFERROR(VLOOKUP($K350,Base_Atividades!$E$1:$N$2398,MATCH(BancoAjustado!L$1,Base_Atividades!$E$1:$N$1,0),FALSE),0) -> 1 | M350: =IFERROR(VLOOKUP($K350,Base_Atividades!$E$1:$N$2398,MATCH(BancoAjustado!M$1,Base_Atividades!$E$1:$N$1,0),FALSE),0) -> 0 | N350: =IFERROR(VLOOKUP($K350,Base_Atividades!$E$1:$N$2398,MATCH(BancoAjustado!N$1,Base_Atividades!$E$1:$N$1,0),FALSE),0) -> 0
A351: C | B351: 21 | C351: 212 | D351: 21220 | E351: 2122000 | F351: =VLOOKUP(A351,Base!$A:$F,6,FALSE) -> INDÚSTRIAS DE TRANSFORMAÇÃO | G351: =VLOOKUP(B351,Base!$B:$F,5,FALSE) -> FABRICAÇÃO DE PRODUTOS FARMOQUÍMICOS E FARMACÊUTICOS | H351: =VLOOKUP(C351,Base!$C:$F,4,FALSE) -> Fabricação de produtos farmacêuticos | I351: =VLOOKUP(D351,Base!$D:$F,3,FALSE) -> Fabricação de medicamentos para uso veterinário | J351: =VLOOKUP(E351,Base!$E:$F,2,FALSE) -> Fabricação de medicamentos para uso veterinário | K351: 2122000 | L351: =IFERROR(VLOOKUP($K351,Base_Atividades!$E$1:$N$2398,MATCH(BancoAjustado!L$1,Base_Atividades!$E$1:$N$1,0),FALSE),0) -> 1 | M351: =IFERROR(VLOOKUP($K351,Base_Atividades!$E$1:$N$2398,MATCH(BancoAjustado!M$1,Base_Atividades!$E$1:$N$1,0),FALSE),0) -> 0 | N351: =IFERROR(VLOOKUP($K351,Base_Atividades!$E$1:$N$2398,MATCH(BancoAjustado!N$1,Base_Atividades!$E$1:$N$1,0),FALSE),0) -> 0
A352: C | B352: 21 | C352: 212 | D352: 21238 | E352: 2123800 | F352: =VLOOKUP(A352,Base!$A:$F,6,FALSE) -> INDÚSTRIAS DE TRANSFORMAÇÃO | G352: =VLOOKUP(B352,Base!$B:$F,5,FALSE) -> FABRICAÇÃO DE PRODUTOS FARMOQUÍMICOS E FARMACÊUTICOS | H352: =VLOOKUP(C352,Base!$C:$F,4,FALSE) -> Fabricação de produtos farmacêuticos | I352: =VLOOKUP(D352,Base!$D:$F,3,FALSE) -> Fabricação de preparações farmacêuticas | J352: =VLOOKUP(E352,Base!$E:$F,2,FALSE) -> Fabricação de preparações farmacêuticas | K352: 2123800 | L352: =IFERROR(VLOOKUP($K352,Base_Atividades!$E$1:$N$2398,MATCH(BancoAjustado!L$1,Base_Atividades!$E$1:$N$1,0),FALSE),0) -> 1 | M352: =IFERROR(VLOOKUP($K352,Base_Atividades!$E$1:$N$2398,MATCH(BancoAjustado!M$1,Base_Atividades!$E$1:$N$1,0),FALSE),0) -> 0 | N352: =IFERROR(VLOOKUP($K352,Base_Atividades!$E$1:$N$2398,MATCH(BancoAjustado!N$1,Base_Atividades!$E$1:$N$1,0),FALSE),0) -> 0
A353: C | B353: 22 | C353: 221 | D353: 22111 | E353: 2211100 | F353: =VLOOKUP(A353,Base!$A:$F,6,FALSE) -> INDÚSTRIAS DE TRANSFORMAÇÃO | G353: =VLOOKUP(B353,Base!$B:$F,5,FALSE) -> FABRICAÇÃO DE PRODUTOS DE BORRACHA E DE MATERIAL PLÁSTICO | H353: =VLOOKUP(C353,Base!$C:$F,4,FALSE) -> Fabricação de produtos de borracha | I353: =VLOOKUP(D353,Base!$D:$F,3,FALSE) -> Fabricação de pneumáticos e de câmaras-de-ar | J353: =VLOOKUP(E353,Base!$E:$F,2,FALSE) -> Fabricação de pneumáticos e de câmaras-de-ar | K353: 2211100 | L353: =IFERROR(VLOOKUP($K353,Base_Atividades!$E$1:$N$2398,MATCH(BancoAjustado!L$1,Base_Atividades!$E$1:$N$1,0),FALSE),0) -> 1 | M353: =IFERROR(VLOOKUP($K353,Base_Atividades!$E$1:$N$2398,MATCH(BancoAjustado!M$1,Base_Atividades!$E$1:$N$1,0),FALSE),0) -> 0 | N353: =IFERROR(VLOOKUP($K353,Base_Atividades!$E$1:$N$2398,MATCH(BancoAjustado!N$1,Base_Atividades!$E$1:$N$1,0),FALSE),0) -> 0
A354: C | B354: 22 | C354: 221 | D354: 22129 | E354: 2212900 | F354: =VLOOKUP(A354,Base!$A:$F,6,FALSE) -> INDÚSTRIAS DE TRANSFORMAÇÃO | G354: =VLOOKUP(B354,Base!$B:$F,5,FALSE) -> FABRICAÇÃO DE PRODUTOS DE BORRACHA E DE MATERIAL PLÁSTICO | H354: =VLOOKUP(C354,Base!$C:$F,4,FALSE) -> Fabricação de produtos de borracha | I354: =VLOOKUP(D354,Base!$D:$F,3,FALSE) -> Reforma de pneumáticos usados | J354: =VLOOKUP(E354,Base!$E:$F,2,FALSE) -> Reforma de pneumáticos usados | K354: 2212900 | L354: =IFERROR(VLOOKUP($K354,Base_Atividades!$E$1:$N$2398,MATCH(BancoAjustado!L$1,Base_Atividades!$E$1:$N$1,0),FALSE),0) -> 1 | M354: =IFERROR(VLOOKUP($K354,Base_Atividades!$E$1:$N$2398,MATCH(BancoAjustado!M$1,Base_Atividades!$E$1:$N$1,0),FALSE),0) -> 0 | N354: =IFERROR(VLOOKUP($K354,Base_Atividades!$E$1:$N$2398,MATCH(BancoAjustado!N$1,Base_Atividades!$E$1:$N$1,0),FALSE),0) -> 0
A355: C | B355: 22 | C355: 221 | D355: 22196 | E355: 2219600 | F355: =VLOOKUP(A355,Base!$A:$F,6,FALSE) -> INDÚSTRIAS DE TRANSFORMAÇÃO | G355: =VLOOKUP(B355,Base!$B:$F,5,FALSE) -> FABRICAÇÃO DE PRODUTOS DE BORRACHA E DE MATERIAL PLÁSTICO | H355: =VLOOKUP(C355,Base!$C:$F,4,FALSE) -> Fabricação de produtos de borracha | I355: =VLOOKUP(D355,Base!$D:$F,3,FALSE) -> Fabricação de artefatos de borracha não especificados anteriormente | J355: =VLOOKUP(E355,Base!$E:$F,2,FALSE) -> Fabricação de artefatos de borracha não especificados anteriormente | K355: 2219600 | L355: =IFERROR(VLOOKUP($K355,Base_Atividades!$E$1:$N$2398,MATCH(BancoAjustado!L$1,Base_Atividades!$E$1:$N$1,0),FALSE),0) -> 1 | M355: =IFERROR(VLOOKUP($K355,Base_Atividades!$E$1:$N$2398,MATCH(BancoAjustado!M$1,Base_Atividades!$E$1:$N$1,0),FALSE),0) -> 0 | N355: =IFERROR(VLOOKUP($K355,Base_Atividades!$E$1:$N$2398,MATCH(BancoAjustado!N$1,Base_Atividades!$E$1:$N$1,0),FALSE),0) -> 0
A356: C | B356: 22 | C356: 222 | D356: 22218 | E356: 2221800 | F356: =VLOOKUP(A356,Base!$A:$F,6,FALSE) -> INDÚSTRIAS DE TRANSFORMAÇÃO | G356: =VLOOKUP(B356,Base!$B:$F,5,FALSE) -> FABRICAÇÃO DE PRODUTOS DE BORRACHA E DE MATERIAL PLÁSTICO | H356: =VLOOKUP(C356,Base!$C:$F,4,FALSE) -> Fabricação de produtos de material plástico | I356: =VLOOKUP(D356,Base!$D:$F,3,FALSE) -> Fabricação de laminados planos e tubulares de material plástico | J356: =VLOOKUP(E356,Base!$E:$F,2,FALSE) -> Fabricação de laminados planos e tubulares de material plástico | K356: 2221800 | L356: =IFERROR(VLOOKUP($K356,Base_Atividades!$E$1:$N$2398,MATCH(BancoAjustado!L$1,Base_Atividades!$E$1:$N$1,0),FALSE),0) -> 1 | M356: =IFERROR(VLOOKUP($K356,Base_Atividades!$E$1:$N$2398,MATCH(BancoAjustado!M$1,Base_Atividades!$E$1:$N$1,0),FALSE),0) -> 0 | N356: =IFERROR(VLOOKUP($K356,Base_Atividades!$E$1:$N$2398,MATCH(BancoAjustado!N$1,Base_Atividades!$E$1:$N$1,0),FALSE),0) -> 0
A357: C | B357: 22 | C357: 222 | D357: 22226 | E357: 2222600 | F357: =VLOOKUP(A357,Base!$A:$F,6,FALSE) -> INDÚSTRIAS DE TRANSFORMAÇÃO | G357: =VLOOKUP(B357,Base!$B:$F,5,FALSE) -> FABRICAÇÃO DE PRODUTOS DE BORRACHA E DE MATERIAL PLÁSTICO | H357: =VLOOKUP(C357,Base!$C:$F,4,FALSE) -> Fabricação de produtos de material plástico | I357: =VLOOKUP(D357,Base!$D:$F,3,FALSE) -> Fabricação de embalagens de material plástico | J357: =VLOOKUP(E357,Base!$E:$F,2,FALSE) -> Fabricação de embalagens de material plástico | K357: 2222600 | L357: =IFERROR(VLOOKUP($K357,Base_Atividades!$E$1:$N$2398,MATCH(BancoAjustado!L$1,Base_Atividades!$E$1:$N$1,0),FALSE),0) -> 1 | M357: =IFERROR(VLOOKUP($K357,Base_Atividades!$E$1:$N$2398,MATCH(BancoAjustado!M$1,Base_Atividades!$E$1:$N$1,0),FALSE),0) -> 0 | N357: =IFERROR(VLOOKUP($K357,Base_Atividades!$E$1:$N$2398,MATCH(BancoAjustado!N$1,Base_Atividades!$E$1:$N$1,0),FALSE),0) -> 0
A358: C | B358: 22 | C358: 222 | D358: 22234 | E358: 2223400 | F358: =VLOOKUP(A358,Base!$A:$F,6,FALSE) -> INDÚSTRIAS DE TRANSFORMAÇÃO | G358: =VLOOKUP(B358,Base!$B:$F,5,FALSE) -> FABRICAÇÃO DE PRODUTOS DE BORRACHA E DE MATERIAL PLÁSTICO | H358: =VLOOKUP(C358,Base!$C:$F,4,FALSE) -> Fabricação de produtos de material plástico | I358: =VLOOKUP(D358,Base!$D:$F,3,FALSE) -> Fabricação de tubos e acessórios de material plástico para uso na construção | J358: =VLOOKUP(E358,Base!$E:$F,2,FALSE) -> Fabricação de tubos e acessórios de material plástico para uso na construção | K358: 2223400 | L358: =IFERROR(VLOOKUP($K358,Base_Atividades!$E$1:$N$2398,MATCH(BancoAjustado!L$1,Base_Atividades!$E$1:$N$1,0),FALSE),0) -> 1 | M358: =IFERROR(VLOOKUP($K358,Base_Atividades!$E$1:$N$2398,MATCH(BancoAjustado!M$1,Base_Atividades!$E$1:$N$1,0),FALSE),0) -> 0 | N358: =IFERROR(VLOOKUP($K358,Base_Atividades!$E$1:$N$2398,MATCH(BancoAjustado!N$1,Base_Atividades!$E$1:$N$1,0),FALSE),0) -> 0
A359: C | B359: 22 | C359: 222 | D359: 22293 | E359: 2229301 | F359: =VLOOKUP(A359,Base!$A:$F,6,FALSE) -> INDÚSTRIAS DE TRANSFORMAÇÃO | G359: =VLOOKUP(B359,Base!$B:$F,5,FALSE) -> FABRICAÇÃO DE PRODUTOS DE BORRACHA E DE MATERIAL PLÁSTICO | H359: =VLOOKUP(C359,Base!$C:$F,4,FALSE) -> Fabricação de produtos de material plástico | I359: =VLOOKUP(D359,Base!$D:$F,3,FALSE) -> Fabricação de artefatos de material plástico não especificados anteriormente | J359: =VLOOKUP(E359,Base!$E:$F,2,FALSE) -> Fabricação de artefatos de material plástico para uso pessoal e doméstico | K359: 2229301 | L359: =IFERROR(VLOOKUP($K359,Base_Atividades!$E$1:$N$2398,MATCH(BancoAjustado!L$1,Base_Atividades!$E$1:$N$1,0),FALSE),0) -> 1 | M359: =IFERROR(VLOOKUP($K359,Base_Atividades!$E$1:$N$2398,MATCH(BancoAjustado!M$1,Base_Atividades!$E$1:$N$1,0),FALSE),0) -> 0 | N359: =IFERROR(VLOOKUP($K359,Base_Atividades!$E$1:$N$2398,MATCH(BancoAjustado!N$1,Base_Atividades!$E$1:$N$1,0),FALSE),0) -> 0
A360: C | B360: 22 | C360: 222 | D360: 22293 | E360: 2229302 | F360: =VLOOKUP(A360,Base!$A:$F,6,FALSE) -> INDÚSTRIAS DE TRANSFORMAÇÃO | G360: =VLOOKUP(B360,Base!$B:$F,5,FALSE) -> FABRICAÇÃO DE PRODUTOS DE BORRACHA E DE MATERIAL PLÁSTICO | H360: =VLOOKUP(C360,Base!$C:$F,4,FALSE) -> Fabricação de produtos de material plástico | I360: =VLOOKUP(D360,Base!$D:$F,3,FALSE) -> Fabricação de artefatos de material plástico não especificados anteriormente | J360: =VLOOKUP(E360,Base!$E:$F,2,FALSE) -> Fabricação de artefatos de material plástico para usos industriais | K360: 2229302 | L360: =IFERROR(VLOOKUP($K360,Base_Atividades!$E$1:$N$2398,MATCH(BancoAjustado!L$1,Base_Atividades!$E$1:$N$1,0),FALSE),0) -> 1 | M360: =IFERROR(VLOOKUP($K360,Base_Atividades!$E$1:$N$2398,MATCH(BancoAjustado!M$1,Base_Atividades!$E$1:$N$1,0),FALSE),0) -> 0 | N360: =IFERROR(VLOOKUP($K360,Base_Atividades!$E$1:$N$2398,MATCH(BancoAjustado!N$1,Base_Atividades!$E$1:$N$1,0),FALSE),0) -> 0
A361: C | B361: 22 | C361: 222 | D361: 22293 | E361: 2229303 | F361: =VLOOKUP(A361,Base!$A:$F,6,FALSE) -> INDÚSTRIAS DE TRANSFORMAÇÃO | G361: =VLOOKUP(B361,Base!$B:$F,5,FALSE) -> FABRICAÇÃO DE PRODUTOS DE BORRACHA E DE MATERIAL PLÁSTICO | H361: =VLOOKUP(C361,Base!$C:$F,4,FALSE) -> Fabricação de produtos de material plástico | I361: =VLOOKUP(D361,Base!$D:$F,3,FALSE) -> Fabricação de artefatos de material plástico não especificados anteriormente | J361: =VLOOKUP(E361,Base!$E:$F,2,FALSE) -> Fabricação de artefatos de material plástico para uso na construção, exceto tubos e acessórios | K361: 2229303 | L361: =IFERROR(VLOOKUP($K361,Base_Atividades!$E$1:$N$2398,MATCH(BancoAjustado!L$1,Base_Atividades!$E$1:$N$1,0),FALSE),0) -> 1 | M361: =IFERROR(VLOOKUP($K361,Base_Atividades!$E$1:$N$2398,MATCH(BancoAjustado!M$1,Base_Atividades!$E$1:$N$1,0),FALSE),0) -> 0 | N361: =IFERROR(VLOOKUP($K361,Base_Atividades!$E$1:$N$2398,MATCH(BancoAjustado!N$1,Base_Atividades!$E$1:$N$1,0),FALSE),0) -> 0
A362: C | B362: 22 | C362: 222 | D362: 22293 | E362: 2229399 | F362: =VLOOKUP(A362,Base!$A:$F,6,FALSE) -> INDÚSTRIAS DE TRANSFORMAÇÃO | G362: =VLOOKUP(B362,Base!$B:$F,5,FALSE) -> FABRICAÇÃO DE PRODUTOS DE BORRACHA E DE MATERIAL PLÁSTICO | H362: =VLOOKUP(C362,Base!$C:$F,4,FALSE) -> Fabricação de produtos de material plástico | I362: =VLOOKUP(D362,Base!$D:$F,3,FALSE) -> Fabricação de artefatos de material plástico não especificados anteriormente | J362: =VLOOKUP(E362,Base!$E:$F,2,FALSE) -> Fabricação de artefatos de material plástico para outros usos não especificados anteriormente | K362: 2229399 | L362: =IFERROR(VLOOKUP($K362,Base_Atividades!$E$1:$N$2398,MATCH(BancoAjustado!L$1,Base_Atividades!$E$1:$N$1,0),FALSE),0) -> 1 | M362: =IFERROR(VLOOKUP($K362,Base_Atividades!$E$1:$N$2398,MATCH(BancoAjustado!M$1,Base_Atividades!$E$1:$N$1,0),FALSE),0) -> 0 | N362: =IFERROR(VLOOKUP($K362,Base_Atividades!$E$1:$N$2398,MATCH(BancoAjustado!N$1,Base_Atividades!$E$1:$N$1,0),FALSE),0) -> 0
A363: C | B363: 23 | C363: 231 | D363: 23117 | E363: 2311700 | F363: =VLOOKUP(A363,Base!$A:$F,6,FALSE) -> INDÚSTRIAS DE TRANSFORMAÇÃO | G363: =VLOOKUP(B363,Base!$B:$F,5,FALSE) -> FABRICAÇÃO DE PRODUTOS DE MINERAIS NÃO METÁLICOS | H363: =VLOOKUP(C363,Base!$C:$F,4,FALSE) -> Fabricação de vidro e de produtos do vidro | I363: =VLOOKUP(D363,Base!$D:$F,3,FALSE) -> Fabricação de vidro plano e de segurança | J363: =VLOOKUP(E363,Base!$E:$F,2,FALSE) -> Fabricação de vidro plano e de segurança | K363: 2311700 | L363: =IFERROR(VLOOKUP($K363,Base_Atividades!$E$1:$N$2398,MATCH(BancoAjustado!L$1,Base_Atividades!$E$1:$N$1,0),FALSE),0) -> 0 | M363: =IFERROR(VLOOKUP($K363,Base_Atividades!$E$1:$N$2398,MATCH(BancoAjustado!M$1,Base_Atividades!$E$1:$N$1,0),FALSE),0) -> 0 | N363: =IFERROR(VLOOKUP($K363,Base_Atividades!$E$1:$N$2398,MATCH(BancoAjustado!N$1,Base_Atividades!$E$1:$N$1,0),FALSE),0) -> 0
A364: C | B364: 23 | C364: 231 | D364: 23125 | E364: 2312500 | F364: =VLOOKUP(A364,Base!$A:$F,6,FALSE) -> INDÚSTRIAS DE TRANSFORMAÇÃO | G364: =VLOOKUP(B364,Base!$B:$F,5,FALSE) -> FABRICAÇÃO DE PRODUTOS DE MINERAIS NÃO METÁLICOS | H364: =VLOOKUP(C364,Base!$C:$F,4,FALSE) -> Fabricação de vidro e de produtos do vidro | I364: =VLOOKUP(D364,Base!$D:$F,3,FALSE) -> Fabricação de embalagens de vidro | J364: =VLOOKUP(E364,Base!$E:$F,2,FALSE) -> Fabricação de embalagens de vidro | K364: 2312500 | L364: =IFERROR(VLOOKUP($K364,Base_Atividades!$E$1:$N$2398,MATCH(BancoAjustado!L$1,Base_Atividades!$E$1:$N$1,0),FALSE),0) -> 0 | M364: =IFERROR(VLOOKUP($K364,Base_Atividades!$E$1:$N$2398,MATCH(BancoAjustado!M$1,Base_Atividades!$E$1:$N$1,0),FALSE),0) -> 0 | N364: =IFERROR(VLOOKUP($K364,Base_Atividades!$E$1:$N$2398,MATCH(BancoAjustado!N$1,Base_Atividades!$E$1:$N$1,0),FALSE),0) -> 0
A365: C | B365: 23 | C365: 231 | D365: 23192 | E365: 2319200 | F365: =VLOOKUP(A365,Base!$A:$F,6,FALSE) -> INDÚSTRIAS DE TRANSFORMAÇÃO | G365: =VLOOKUP(B365,Base!$B:$F,5,FALSE) -> FABRICAÇÃO DE PRODUTOS DE MINERAIS NÃO METÁLICOS | H365: =VLOOKUP(C365,Base!$C:$F,4,FALSE) -> Fabricação de vidro e de produtos do vidro | I365: =VLOOKUP(D365,Base!$D:$F,3,FALSE) -> Fabricação de artigos de vidro | J365: =VLOOKUP(E365,Base!$E:$F,2,FALSE) -> Fabricação de artigos de vidro | K365: 2319200 | L365: =IFERROR(VLOOKUP($K365,Base_Atividades!$E$1:$N$2398,MATCH(BancoAjustado!L$1,Base_Atividades!$E$1:$N$1,0),FALSE),0) -> 0 | M365: =IFERROR(VLOOKUP($K365,Base_Atividades!$E$1:$N$2398,MATCH(BancoAjustado!M$1,Base_Atividades!$E$1:$N$1,0),FALSE),0) -> 0 | N365: =IFERROR(VLOOKUP($K365,Base_Atividades!$E$1:$N$2398,MATCH(BancoAjustado!N$1,Base_Atividades!$E$1:$N$1,0),FALSE),0) -> 0
A366: C | B366: 23 | C366: 232 | D366: 23206 | E366: 2320600 | F366: =VLOOKUP(A366,Base!$A:$F,6,FALSE) -> INDÚSTRIAS DE TRANSFORMAÇÃO | G366: =VLOOKUP(B366,Base!$B:$F,5,FALSE) -> FABRICAÇÃO DE PRODUTOS DE MINERAIS NÃO METÁLICOS | H366: =VLOOKUP(C366,Base!$C:$F,4,FALSE) -> Fabricação de cimento | I366: =VLOOKUP(D366,Base!$D:$F,3,FALSE) -> Fabricação de cimento | J366: =VLOOKUP(E366,Base!$E:$F,2,FALSE) -> Fabricação de cimento | K366: 2320600 | L366: =IFERROR(VLOOKUP($K366,Base_Atividades!$E$1:$N$2398,MATCH(BancoAjustado!L$1,Base_Atividades!$E$1:$N$1,0),FALSE),0) -> 0 | M366: =IFERROR(VLOOKUP($K366,Base_Atividades!$E$1:$N$2398,MATCH(BancoAjustado!M$1,Base_Atividades!$E$1:$N$1,0),FALSE),0) -> 0 | N366: =IFERROR(VLOOKUP($K366,Base_Atividades!$E$1:$N$2398,MATCH(BancoAjustado!N$1,Base_Atividades!$E$1:$N$1,0),FALSE),0) -> 0
A367: C | B367: 23 | C367: 233 | D367: 23303 | E367: 2330301 | F367: =VLOOKUP(A367,Base!$A:$F,6,FALSE) -> INDÚSTRIAS DE TRANSFORMAÇÃO | G367: =VLOOKUP(B367,Base!$B:$F,5,FALSE) -> FABRICAÇÃO DE PRODUTOS DE MINERAIS NÃO METÁLICOS | H367: =VLOOKUP(C367,Base!$C:$F,4,FALSE) -> Fabricação de artefatos de concreto, cimento, fibrocimento, gesso e materiais semelhantes | I367: =VLOOKUP(D367,Base!$D:$F,3,FALSE) -> Fabricação de artefatos de concreto, cimento, fibrocimento, gesso e materiais semelhantes | J367: =VLOOKUP(E367,Base!$E:$F,2,FALSE) -> Fabricação de estruturas pré-moldadas de concreto armado, em série e sob encomenda | K367: 2330301 | L367: =IFERROR(VLOOKUP($K367,Base_Atividades!$E$1:$N$2398,MATCH(BancoAjustado!L$1,Base_Atividades!$E$1:$N$1,0),FALSE),0) -> 0 | M367: =IFERROR(VLOOKUP($K367,Base_Atividades!$E$1:$N$2398,MATCH(BancoAjustado!M$1,Base_Atividades!$E$1:$N$1,0),FALSE),0) -> 0 | N367: =IFERROR(VLOOKUP($K367,Base_Atividades!$E$1:$N$2398,MATCH(BancoAjustado!N$1,Base_Atividades!$E$1:$N$1,0),FALSE),0) -> 0
A368: C | B368: 23 | C368: 233 | D368: 23303 | E368: 2330302 | F368: =VLOOKUP(A368,Base!$A:$F,6,FALSE) -> INDÚSTRIAS DE TRANSFORMAÇÃO | G368: =VLOOKUP(B368,Base!$B:$F,5,FALSE) -> FABRICAÇÃO DE PRODUTOS DE MINERAIS NÃO METÁLICOS | H368: =VLOOKUP(C368,Base!$C:$F,4,FALSE) -> Fabricação de artefatos de concreto, cimento, fibrocimento, gesso e materiais semelhantes | I368: =VLOOKUP(D368,Base!$D:$F,3,FALSE) -> Fabricação de artefatos de concreto, cimento, fibrocimento, gesso e materiais semelhantes | J368: =VLOOKUP(E368,Base!$E:$F,2,FALSE) -> Fabricação de artefatos de cimento para uso na construção | K368: 2330302 | L368: =IFERROR(VLOOKUP($K368,Base_Atividades!$E$1:$N$2398,MATCH(BancoAjustado!L$1,Base_Atividades!$E$1:$N$1,0),FALSE),0) -> 0 | M368: =IFERROR(VLOOKUP($K368,Base_Atividades!$E$1:$N$2398,MATCH(BancoAjustado!M$1,Base_Atividades!$E$1:$N$1,0),FALSE),0) -> 0 | N368: =IFERROR(VLOOKUP($K368,Base_Atividades!$E$1:$N$2398,MATCH(BancoAjustado!N$1,Base_Atividades!$E$1:$N$1,0),FALSE),0) -> 0
A369: C | B369: 23 | C369: 233 | D369: 23303 | E369: 2330303 | F369: =VLOOKUP(A369,Base!$A:$F,6,FALSE) -> INDÚSTRIAS DE TRANSFORMAÇÃO | G369: =VLOOKUP(B369,Base!$B:$F,5,FALSE) -> FABRICAÇÃO DE PRODUTOS DE MINERAIS NÃO METÁLICOS | H369: =VLOOKUP(C369,Base!$C:$F,4,FALSE) -> Fabricação de artefatos de concreto, cimento, fibrocimento, gesso e materiais semelhantes | I369: =VLOOKUP(D369,Base!$D:$F,3,FALSE) -> Fabricação de artefatos de concreto, cimento, fibrocimento, gesso e materiais semelhantes | J369: =VLOOKUP(E369,Base!$E:$F,2,FALSE) -> Fabricação de artefatos de fibrocimento para uso na construção | K369: 2330303 | L369: =IFERROR(VLOOKUP($K369,Base_Atividades!$E$1:$N$2398,MATCH(BancoAjustado!L$1,Base_Atividades!$E$1:$N$1,0),FALSE),0) -> 0 | M369: =IFERROR(VLOOKUP($K369,Base_Atividades!$E$1:$N$2398,MATCH(BancoAjustado!M$1,Base_Atividades!$E$1:$N$1,0),FALSE),0) -> 0 | N369: =IFERROR(VLOOKUP($K369,Base_Atividades!$E$1:$N$2398,MATCH(BancoAjustado!N$1,Base_Atividades!$E$1:$N$1,0),FALSE),0) -> 0
A370: C | B370: 23 | C370: 233 | D370: 23303 | E370: 2330304 | F370: =VLOOKUP(A370,Base!$A:$F,6,FALSE) -> INDÚSTRIAS DE TRANSFORMAÇÃO | G370: =VLOOKUP(B370,Base!$B:$F,5,FALSE) -> FABRICAÇÃO DE PRODUTOS DE MINERAIS NÃO METÁLICOS | H370: =VLOOKUP(C370,Base!$C:$F,4,FALSE) -> Fabricação de artefatos de concreto, cimento, fibrocimento, gesso e materiais semelhantes | I370: =VLOOKUP(D370,Base!$D:$F,3,FALSE) -> Fabricação de artefatos de concreto, cimento, fibrocimento, gesso e materiais semelhantes | J370: =VLOOKUP(E370,Base!$E:$F,2,FALSE) -> Fabricação de casas pré-moldadas de concreto | K370: 2330304 | L370: =IFERROR(VLOOKUP($K370,Base_Atividades!$E$1:$N$2398,MATCH(BancoAjustado!L$1,Base_Atividades!$E$1:$N$1,0),FALSE),0) -> 0 | M370: =IFERROR(VLOOKUP($K370,Base_Atividades!$E$1:$N$2398,MATCH(BancoAjustado!M$1,Base_Atividades!$E$1:$N$1,0),FALSE),0) -> 0 | N370: =IFERROR(VLOOKUP($K370,Base_Atividades!$E$1:$N$2398,MATCH(BancoAjustado!N$1,Base_Atividades!$E$1:$N$1,0),FALSE),0) -> 0
A371: C | B371: 23 | C371: 233 | D371: 23303 | E371: 2330305 | F371: =VLOOKUP(A371,Base!$A:$F,6,FALSE) -> INDÚSTRIAS DE TRANSFORMAÇÃO | G371: =VLOOKUP(B371,Base!$B:$F,5,FALSE) -> FABRICAÇÃO DE PRODUTOS DE MINERAIS NÃO METÁLICOS | H371: =VLOOKUP(C371,Base!$C:$F,4,FALSE) -> Fabricação de artefatos de concreto, cimento, fibrocimento, gesso e materiais semelhantes | I371: =VLOOKUP(D371,Base!$D:$F,3,FALSE) -> Fabricação de artefatos de concreto, cimento, fibrocimento, gesso e materiais semelhantes | J371: =VLOOKUP(E371,Base!$E:$F,2,FALSE) -> Preparação de massa de concreto e argamassa para construção | K371: 2330305 | L371: =IFERROR(VLOOKUP($K371,Base_Atividades!$E$1:$N$2398,MATCH(BancoAjustado!L$1,Base_Atividades!$E$1:$N$1,0),FALSE),0) -> 0 | M371: =IFERROR(VLOOKUP($K371,Base_Atividades!$E$1:$N$2398,MATCH(BancoAjustado!M$1,Base_Atividades!$E$1:$N$1,0),FALSE),0) -> 0 | N371: =IFERROR(VLOOKUP($K371,Base_Atividades!$E$1:$N$2398,MATCH(BancoAjustado!N$1,Base_Atividades!$E$1:$N$1,0),FALSE),0) -> 0
A372: C | B372: 23 | C372: 233 | D372: 23303 | E372: 2330399 | F372: =VLOOKUP(A372,Base!$A:$F,6,FALSE) -> INDÚSTRIAS DE TRANSFORMAÇÃO | G372: =VLOOKUP(B372,Base!$B:$F,5,FALSE) -> FABRICAÇÃO DE PRODUTOS DE MINERAIS NÃO METÁLICOS | H372: =VLOOKUP(C372,Base!$C:$F,4,FALSE) -> Fabricação de artefatos de concreto, cimento, fibrocimento, gesso e materiais semelhantes | I372: =VLOOKUP(D372,Base!$D:$F,3,FALSE) -> Fabricação de artefatos de concreto, cimento, fibrocimento, gesso e materiais semelhantes | J372: =VLOOKUP(E372,Base!$E:$F,2,FALSE) -> Fabricação de outros artefatos e produtos de concreto, cimento, fibrocimento, gesso e materiais semelhantes | K372: 2330399 | L372: =IFERROR(VLOOKUP($K372,Base_Atividades!$E$1:$N$2398,MATCH(BancoAjustado!L$1,Base_Atividades!$E$1:$N$1,0),FALSE),0) -> 0 | M372: =IFERROR(VLOOKUP($K372,Base_Atividades!$E$1:$N$2398,MATCH(BancoAjustado!M$1,Base_Atividades!$E$1:$N$1,0),FALSE),0) -> 0 | N372: =IFERROR(VLOOKUP($K372,Base_Atividades!$E$1:$N$2398,MATCH(BancoAjustado!N$1,Base_Atividades!$E$1:$N$1,0),FALSE),0) -> 0
A373: C | B373: 23 | C373: 234 | D373: 23419 | E373: 2341900 | F373: =VLOOKUP(A373,Base!$A:$F,6,FALSE) -> INDÚSTRIAS DE TRANSFORMAÇÃO | G373: =VLOOKUP(B373,Base!$B:$F,5,FALSE) -> FABRICAÇÃO DE PRODUTOS DE MINERAIS NÃO METÁLICOS | H373: =VLOOKUP(C373,Base!$C:$F,4,FALSE) -> Fabricação de produtos cerâmicos | I373: =VLOOKUP(D373,Base!$D:$F,3,FALSE) -> Fabricação de produtos cerâmicos refratários | J373: =VLOOKUP(E373,Base!$E:$F,2,FALSE) -> Fabricação de produtos cerâmicos refratários | K373: 2341900 | L373: =IFERROR(VLOOKUP($K373,Base_Atividades!$E$1:$N$2398,MATCH(BancoAjustado!L$1,Base_Atividades!$E$1:$N$1,0),FALSE),0) -> 0 | M373: =IFERROR(VLOOKUP($K373,Base_Atividades!$E$1:$N$2398,MATCH(BancoAjustado!M$1,Base_Atividades!$E$1:$N$1,0),FALSE),0) -> 0 | N373: =IFERROR(VLOOKUP($K373,Base_Atividades!$E$1:$N$2398,MATCH(BancoAjustado!N$1,Base_Atividades!$E$1:$N$1,0),FALSE),0) -> 0
A374: C | B374: 23 | C374: 234 | D374: 23427 | E374: 2342701 | F374: =VLOOKUP(A374,Base!$A:$F,6,FALSE) -> INDÚSTRIAS DE TRANSFORMAÇÃO | G374: =VLOOKUP(B374,Base!$B:$F,5,FALSE) -> FABRICAÇÃO DE PRODUTOS DE MINERAIS NÃO METÁLICOS | H374: =VLOOKUP(C374,Base!$C:$F,4,FALSE) -> Fabricação de produtos cerâmicos | I374: =VLOOKUP(D374,Base!$D:$F,3,FALSE) -> Fabricação de produtos cerâmicos não refratários para uso estrutural na construção | J374: =VLOOKUP(E374,Base!$E:$F,2,FALSE) -> Fabricação de azulejos e pisos | K374: 2342701 | L374: =IFERROR(VLOOKUP($K374,Base_Atividades!$E$1:$N$2398,MATCH(BancoAjustado!L$1,Base_Atividades!$E$1:$N$1,0),FALSE),0) -> 0 | M374: =IFERROR(VLOOKUP($K374,Base_Atividades!$E$1:$N$2398,MATCH(BancoAjustado!M$1,Base_Atividades!$E$1:$N$1,0),FALSE),0) -> 0 | N374: =IFERROR(VLOOKUP($K374,Base_Atividades!$E$1:$N$2398,MATCH(BancoAjustado!N$1,Base_Atividades!$E$1:$N$1,0),FALSE),0) -> 0
... A384: C | B384: 23 | C384: 239 | D384: 23991 | E384: 2399199 | F384: =VLOOKUP(A384,Base!$A:$F,6,FALSE) -> INDÚSTRIAS DE TRANSFORMAÇÃO | G384: =VLOOKUP(B384,Base!$B:$F,5,FALSE) -> FABRICAÇÃO DE PRODUTOS DE MINERAIS NÃO METÁLICOS | H384: =VLOOKUP(C384,Base!$C:$F,4,FALSE) -> Aparelhamento de pedras e fabricação de outros produtos de minerais não metálicos | I384: =VLOOKUP(D384,Base!$D:$F,3,FALSE) -> Fabricação de produtos de minerais não metálicos não especificados anteriormente | J384: =VLOOKUP(E384,Base!$E:$F,2,FALSE) -> Fabricação de outros produtos de minerais não metálicos não especificados anteriormente | K384: 2399199 | L384: =IFERROR(VLOOKUP($K384,Base_Atividades!$E$1:$N$2398,MATCH(BancoAjustado!L$1,Base_Atividades!$E$1:$N$1,0),FALSE),0) -> 0 | M384: =IFERROR(VLOOKUP($K384,Base_Atividades!$E$1:$N$2398,MATCH(BancoAjustado!M$1,Base_Atividades!$E$1:$N$1,0),FALSE),0) -> 0 | N384: =IFERROR(VLOOKUP($K384,Base_Atividades!$E$1:$N$2398,MATCH(BancoAjustado!N$1,Base_Atividades!$E$1:$N$1,0),FALSE),0) -> 0
A385: C | B385: 24 | C385: 241 | D385: 24113 | E385: 2411300 | F385: =VLOOKUP(A385,Base!$A:$F,6,FALSE) -> INDÚSTRIAS DE TRANSFORMAÇÃO | G385: =VLOOKUP(B385,Base!$B:$F,5,FALSE) -> METALURGIA | H385: =VLOOKUP(C385,Base!$C:$F,4,FALSE) -> Produção de ferro-gusa e de ferroligas | I385: =VLOOKUP(D385,Base!$D:$F,3,FALSE) -> Produção de ferro-gusa | J385: =VLOOKUP(E385,Base!$E:$F,2,FALSE) -> Produção de ferro-gusa | K385: 2411300 | L385: =IFERROR(VLOOKUP($K385,Base_Atividades!$E$1:$N$2398,MATCH(BancoAjustado!L$1,Base_Atividades!$E$1:$N$1,0),FALSE),0) -> 0 | M385: =IFERROR(VLOOKUP($K385,Base_Atividades!$E$1:$N$2398,MATCH(BancoAjustado!M$1,Base_Atividades!$E$1:$N$1,0),FALSE),0) -> 0 | N385: =IFERROR(VLOOKUP($K385,Base_Atividades!$E$1:$N$2398,MATCH(BancoAjustado!N$1,Base_Atividades!$E$1:$N$1,0),FALSE),0) -> 0
A386: C | B386: 24 | C386: 241 | D386: 24121 | E386: 2412100 | F386: =VLOOKUP(A386,Base!$A:$F,6,FALSE) -> INDÚSTRIAS DE TRANSFORMAÇÃO | G386: =VLOOKUP(B386,Base!$B:$F,5,FALSE) -> METALURGIA | H386: =VLOOKUP(C386,Base!$C:$F,4,FALSE) -> Produção de ferro-gusa e de ferroligas | I386: =VLOOKUP(D386,Base!$D:$F,3,FALSE) -> Produção de ferroligas | J386: =VLOOKUP(E386,Base!$E:$F,2,FALSE) -> Produção de ferroligas | K386: 2412100 | L386: =IFERROR(VLOOKUP($K386,Base_Atividades!$E$1:$N$2398,MATCH(BancoAjustado!L$1,Base_Atividades!$E$1:$N$1,0),FALSE),0) -> 0 | M386: =IFERROR(VLOOKUP($K386,Base_Atividades!$E$1:$N$2398,MATCH(BancoAjustado!M$1,Base_Atividades!$E$1:$N$1,0),FALSE),0) -> 0 | N386: =IFERROR(VLOOKUP($K386,Base_Atividades!$E$1:$N$2398,MATCH(BancoAjustado!N$1,Base_Atividades!$E$1:$N$1,0),FALSE),0) -> 0
A387: C | B387: 24 | C387: 242 | D387: 24211 | E387: 2421100 | F387: =VLOOKUP(A387,Base!$A:$F,6,FALSE) -> INDÚSTRIAS DE TRANSFORMAÇÃO | G387: =VLOOKUP(B387,Base!$B:$F,5,FALSE) -> METALURGIA | H387: =VLOOKUP(C387,Base!$C:$F,4,FALSE) -> Siderurgia | I387: =VLOOKUP(D387,Base!$D:$F,3,FALSE) -> Produção de semiacabados de aço | J387: =VLOOKUP(E387,Base!$E:$F,2,FALSE) -> Produção de semiacabados de aço | K387: 2421100 | L387: =IFERROR(VLOOKUP($K387,Base_Atividades!$E$1:$N$2398,MATCH(BancoAjustado!L$1,Base_Atividades!$E$1:$N$1,0),FALSE),0) -> 0 | M387: =IFERROR(VLOOKUP($K387,Base_Atividades!$E$1:$N$2398,MATCH(BancoAjustado!M$1,Base_Atividades!$E$1:$N$1,0),FALSE),0) -> 0 | N387: =IFERROR(VLOOKUP($K387,Base_Atividades!$E$1:$N$2398,MATCH(BancoAjustado!N$1,Base_Atividades!$E$1:$N$1,0),FALSE),0) -> 0
A388: C | B388: 24 | C388: 242 | D388: 24229 | E388: 2422901 | F388: =VLOOKUP(A388,Base!$A:$F,6,FALSE) -> INDÚSTRIAS DE TRANSFORMAÇÃO | G388: =VLOOKUP(B388,Base!$B:$F,5,FALSE) -> METALURGIA | H388: =VLOOKUP(C388,Base!$C:$F,4,FALSE) -> Siderurgia | I388: =VLOOKUP(D388,Base!$D:$F,3,FALSE) -> Produção de laminados planos de aço | J388: =VLOOKUP(E388,Base!$E:$F,2,FALSE) -> Produção de laminados planos de aço ao carbono, revestidos ou não | K388: 2422901 | L388: =IFERROR(VLOOKUP($K388,Base_Atividades!$E$1:$N$2398,MATCH(BancoAjustado!L$1,Base_Atividades!$E$1:$N$1,0),FALSE),0) -> 0 | M388: =IFERROR(VLOOKUP($K388,Base_Atividades!$E$1:$N$2398,MATCH(BancoAjustado!M$1,Base_Atividades!$E$1:$N$1,0),FALSE),0) -> 0 | N388: =IFERROR(VLOOKUP($K388,Base_Atividades!$E$1:$N$2398,MATCH(BancoAjustado!N$1,Base_Atividades!$E$1:$N$1,0),FALSE),0) -> 0
A389: C | B389: 24 | C389: 242 | D389: 24229 | E389: 2422902 | F389: =VLOOKUP(A389,Base!$A:$F,6,FALSE) -> INDÚSTRIAS DE TRANSFORMAÇÃO | G389: =VLOOKUP(B389,Base!$B:$F,5,FALSE) -> METALURGIA | H389: =VLOOKUP(C389,Base!$C:$F,4,FALSE) -> Siderurgia | I389: =VLOOKUP(D389,Base!$D:$F,3,FALSE) -> Produção de laminados planos de aço | J389: =VLOOKUP(E389,Base!$E:$F,2,FALSE) -> Produção de laminados planos de aços especiais | K389: 2422902 | L389: =IFERROR(VLOOKUP($K389,Base_Atividades!$E$1:$N$2398,MATCH(BancoAjustado!L$1,Base_Atividades!$E$1:$N$1,0),FALSE),0) -> 0 | M389: =IFERROR(VLOOKUP($K389,Base_Atividades!$E$1:$N$2398,MATCH(BancoAjustado!M$1,Base_Atividades!$E$1:$N$1,0),FALSE),0) -> 0 | N389: =IFERROR(VLOOKUP($K389,Base_Atividades!$E$1:$N$2398,MATCH(BancoAjustado!N$1,Base_Atividades!$E$1:$N$1,0),FALSE),0) -> 0
A390: C | B390: 24 | C390: 242 | D390: 24237 | E390: 2423701 | F390: =VLOOKUP(A390,Base!$A:$F,6,FALSE) -> INDÚSTRIAS DE TRANSFORMAÇÃO | G390: =VLOOKUP(B390,Base!$B:$F,5,FALSE) -> METALURGIA | H390: =VLOOKUP(C390,Base!$C:$F,4,FALSE) -> Siderurgia | I390: =VLOOKUP(D390,Base!$D:$F,3,FALSE) -> Produção de laminados longos de aço | J390: =VLOOKUP(E390,Base!$E:$F,2,FALSE) -> Produção de tubos de aço sem costura | K390: 2423701 | L390: =IFERROR(VLOOKUP($K390,Base_Atividades!$E$1:$N$2398,MATCH(BancoAjustado!L$1,Base_Atividades!$E$1:$N$1,0),FALSE),0) -> 0 | M390: =IFERROR(VLOOKUP($K390,Base_Atividades!$E$1:$N$2398,MATCH(BancoAjustado!M$1,Base_Atividades!$E$1:$N$1,0),FALSE),0) -> 0 | N390: =IFERROR(VLOOKUP($K390,Base_Atividades!$E$1:$N$2398,MATCH(BancoAjustado!N$1,Base_Atividades!$E$1:$N$1,0),FALSE),0) -> 0
A391: C | B391: 24 | C391: 242 | D391: 24237 | E391: 2423702 | F391: =VLOOKUP(A391,Base!$A:$F,6,FALSE) -> INDÚSTRIAS DE TRANSFORMAÇÃO | G391: =VLOOKUP(B391,Base!$B:$F,5,FALSE) -> METALURGIA | H391: =VLOOKUP(C391,Base!$C:$F,4,FALSE) -> Siderurgia | I391: =VLOOKUP(D391,Base!$D:$F,3,FALSE) -> Produção de laminados longos de aço | J391: =VLOOKUP(E391,Base!$E:$F,2,FALSE) -> Produção de laminados longos de aço, exceto tubos | K391: 2423702 | L391: =IFERROR(VLOOKUP($K391,Base_Atividades!$E$1:$N$2398,MATCH(BancoAjustado!L$1,Base_Atividades!$E$1:$N$1,0),FALSE),0) -> 0 | M391: =IFERROR(VLOOKUP($K391,Base_Atividades!$E$1:$N$2398,MATCH(BancoAjustado!M$1,Base_Atividades!$E$1:$N$1,0),FALSE),0) -> 0 | N391: =IFERROR(VLOOKUP($K391,Base_Atividades!$E$1:$N$2398,MATCH(BancoAjustado!N$1,Base_Atividades!$E$1:$N$1,0),FALSE),0) -> 0
A392: C | B392: 24 | C392: 242 | D392: 24245 | E392: 2424501 | F392: =VLOOKUP(A392,Base!$A:$F,6,FALSE) -> INDÚSTRIAS DE TRANSFORMAÇÃO | G392: =VLOOKUP(B392,Base!$B:$F,5,FALSE) -> METALURGIA | H392: =VLOOKUP(C392,Base!$C:$F,4,FALSE) -> Siderurgia | I392: =VLOOKUP(D392,Base!$D:$F,3,FALSE) -> Produção de relaminados, trefilados e perfilados de aço | J392: =VLOOKUP(E392,Base!$E:$F,2,FALSE) -> Produção de arames de aço | K392: 2424501 | L392: =IFERROR(VLOOKUP($K392,Base_Atividades!$E$1:$N$2398,MATCH(BancoAjustado!L$1,Base_Atividades!$E$1:$N$1,0),FALSE),0) -> 0 | M392: =IFERROR(VLOOKUP($K392,Base_Atividades!$E$1:$N$2398,MATCH(BancoAjustado!M$1,Base_Atividades!$E$1:$N$1,0),FALSE),0) -> 0 | N392: =IFERROR(VLOOKUP($K392,Base_Atividades!$E$1:$N$2398,MATCH(BancoAjustado!N$1,Base_Atividades!$E$1:$N$1,0),FALSE),0) -> 0
A393: C | B393: 24 | C393: 242 | D393: 24245 | E393: 2424502 | F393: =VLOOKUP(A393,Base!$A:$F,6,FALSE) -> INDÚSTRIAS DE TRANSFORMAÇÃO | G393: =VLOOKUP(B393,Base!$B:$F,5,FALSE) -> METALURGIA | H393: =VLOOKUP(C393,Base!$C:$F,4,FALSE) -> Siderurgia | I393: =VLOOKUP(D393,Base!$D:$F,3,FALSE) -> Produção de relaminados, trefilados e perfilados de aço | J393: =VLOOKUP(E393,Base!$E:$F,2,FALSE) -> Produção de relaminados, trefilados e perfilados de aço, exceto arames | K393: 2424502 | L393: =IFERROR(VLOOKUP($K393,Base_Atividades!$E$1:$N$2398,MATCH(BancoAjustado!L$1,Base_Atividades!$E$1:$N$1,0),FALSE),0) -> 0 | M393: =IFERROR(VLOOKUP($K393,Base_Atividades!$E$1:$N$2398,MATCH(BancoAjustado!M$1,Base_Atividades!$E$1:$N$1,0),FALSE),0) -> 0 | N393: =IFERROR(VLOOKUP($K393,Base_Atividades!$E$1:$N$2398,MATCH(BancoAjustado!N$1,Base_Atividades!$E$1:$N$1,0),FALSE),0) -> 0
A394: C | B394: 24 | C394: 243 | D394: 24318 | E394: 2431800 | F394: =VLOOKUP(A394,Base!$A:$F,6,FALSE) -> INDÚSTRIAS DE TRANSFORMAÇÃO | G394: =VLOOKUP(B394,Base!$B:$F,5,FALSE) -> METALURGIA | H394: =VLOOKUP(C394,Base!$C:$F,4,FALSE) -> Produção de tubos de aço, exceto tubos sem costura | I394: =VLOOKUP(D394,Base!$D:$F,3,FALSE) -> Produção de tubos de aço com costura | J394: =VLOOKUP(E394,Base!$E:$F,2,FALSE) -> Produção de tubos de aço com costura | K394: 2431800 | L394: =IFERROR(VLOOKUP($K394,Base_Atividades!$E$1:$N$2398,MATCH(BancoAjustado!L$1,Base_Atividades!$E$1:$N$1,0),FALSE),0) -> 0 | M394: =IFERROR(VLOOKUP($K394,Base_Atividades!$E$1:$N$2398,MATCH(BancoAjustado!M$1,Base_Atividades!$E$1:$N$1,0),FALSE),0) -> 0 | N394: =IFERROR(VLOOKUP($K394,Base_Atividades!$E$1:$N$2398,MATCH(BancoAjustado!N$1,Base_Atividades!$E$1:$N$1,0),FALSE),0) -> 0
A395: C | B395: 24 | C395: 243 | D395: 24393 | E395: 2439300 | F395: =VLOOKUP(A395,Base!$A:$F,6,FALSE) -> INDÚSTRIAS DE TRANSFORMAÇÃO | G395: =VLOOKUP(B395,Base!$B:$F,5,FALSE) -> METALURGIA | H395: =VLOOKUP(C395,Base!$C:$F,4,FALSE) -> Produção de tubos de aço, exceto tubos sem costura | I395: =VLOOKUP(D395,Base!$D:$F,3,FALSE) -> Produção de outros tubos de ferro e aço | J395: =VLOOKUP(E395,Base!$E:$F,2,FALSE) -> Produção de outros tubos de ferro e aço | K395: 2439300 | L395: =IFERROR(VLOOKUP($K395,Base_Atividades!$E$1:$N$2398,MATCH(BancoAjustado!L$1,Base_Atividades!$E$1:$N$1,0),FALSE),0) -> 0 | M395: =IFERROR(VLOOKUP($K395,Base_Atividades!$E$1:$N$2398,MATCH(BancoAjustado!M$1,Base_Atividades!$E$1:$N$1,0),FALSE),0) -> 0 | N395: =IFERROR(VLOOKUP($K395,Base_Atividades!$E$1:$N$2398,MATCH(BancoAjustado!N$1,Base_Atividades!$E$1:$N$1,0),FALSE),0) -> 0
A396: C | B396: 24 | C396: 244 | D396: 24415 | E396: 2441501 | F396: =VLOOKUP(A396,Base!$A:$F,6,FALSE) -> INDÚSTRIAS DE TRANSFORMAÇÃO | G396: =VLOOKUP(B396,Base!$B:$F,5,FALSE) -> METALURGIA | H396: =VLOOKUP(C396,Base!$C:$F,4,FALSE) -> Metalurgia dos metais não ferrosos | I396: =VLOOKUP(D396,Base!$D:$F,3,FALSE) -> Metalurgia do alumínio e suas ligas | J396: =VLOOKUP(E396,Base!$E:$F,2,FALSE) -> Produção de alumínio e suas ligas em formas primárias | K396: 2441501 | L396: =IFERROR(VLOOKUP($K396,Base_Atividades!$E$1:$N$2398,MATCH(BancoAjustado!L$1,Base_Atividades!$E$1:$N$1,0),FALSE),0) -> 0 | M396: =IFERROR(VLOOKUP($K396,Base_Atividades!$E$1:$N$2398,MATCH(BancoAjustado!M$1,Base_Atividades!$E$1:$N$1,0),FALSE),0) -> 0 | N396: =IFERROR(VLOOKUP($K396,Base_Atividades!$E$1:$N$2398,MATCH(BancoAjustado!N$1,Base_Atividades!$E$1:$N$1,0),FALSE),0) -> 0
... A549: C | B549: 32 | C549: 329 | D549: 32990 | E549: 3299099 | F549: =VLOOKUP(A549,Base!$A:$F,6,FALSE) -> INDÚSTRIAS DE TRANSFORMAÇÃO | G549: =VLOOKUP(B549,Base!$B:$F,5,FALSE) -> FABRICAÇÃO DE PRODUTOS DIVERSOS | H549: =VLOOKUP(C549,Base!$C:$F,4,FALSE) -> Fabricação de produtos diversos | I549: =VLOOKUP(D549,Base!$D:$F,3,FALSE) -> Fabricação de produtos diversos não especificados anteriormente | J549: =VLOOKUP(E549,Base!$E:$F,2,FALSE) -> Fabricação de produtos diversos não especificados anteriormente | K549: 3299099 | L549: =IFERROR(VLOOKUP($K549,Base_Atividades!$E$1:$N$2398,MATCH(BancoAjustado!L$1,Base_Atividades!$E$1:$N$1,0),FALSE),0) -> 1 | M549: =IFERROR(VLOOKUP($K549,Base_Atividades!$E$1:$N$2398,MATCH(BancoAjustado!M$1,Base_Atividades!$E$1:$N$1,0),FALSE),0) -> 0 | N549: =IFERROR(VLOOKUP($K549,Base_Atividades!$E$1:$N$2398,MATCH(BancoAjustado!N$1,Base_Atividades!$E$1:$N$1,0),FALSE),0) -> 0
A550: C | B550: 33 | C550: 331 | D550: 33112 | E550: 3311200 | F550: =VLOOKUP(A550,Base!$A:$F,6,FALSE) -> INDÚSTRIAS DE TRANSFORMAÇÃO | G550: =VLOOKUP(B550,Base!$B:$F,5,FALSE) -> MANUTENÇÃO, REPARAÇÃO E INSTALAÇÃO DE MÁQUINAS E EQUIPAMENTOS | H550: =VLOOKUP(C550,Base!$C:$F,4,FALSE) -> Manutenção e reparação de máquinas e equipamentos | I550: =VLOOKUP(D550,Base!$D:$F,3,FALSE) -> Manutenção e reparação de tanques, reservatórios metálicos e caldeiras, exceto para veículos | J550: =VLOOKUP(E550,Base!$E:$F,2,FALSE) -> Manutenção e reparação de tanques, reservatórios metálicos e caldeiras, exceto para veículos | K550: 3311200 | L550: =IFERROR(VLOOKUP($K550,Base_Atividades!$E$1:$N$2398,MATCH(BancoAjustado!L$1,Base_Atividades!$E$1:$N$1,0),FALSE),0) -> 1 | M550: =IFERROR(VLOOKUP($K550,Base_Atividades!$E$1:$N$2398,MATCH(BancoAjustado!M$1,Base_Atividades!$E$1:$N$1,0),FALSE),0) -> 0 | N550: =IFERROR(VLOOKUP($K550,Base_Atividades!$E$1:$N$2398,MATCH(BancoAjustado!N$1,Base_Atividades!$E$1:$N$1,0),FALSE),0) -> 0
A551: C | B551: 33 | C551: 331 | D551: 33121 | E551: 3312102 | F551: =VLOOKUP(A551,Base!$A:$F,6,FALSE) -> INDÚSTRIAS DE TRANSFORMAÇÃO | G551: =VLOOKUP(B551,Base!$B:$F,5,FALSE) -> MANUTENÇÃO, REPARAÇÃO E INSTALAÇÃO DE MÁQUINAS E EQUIPAMENTOS | H551: =VLOOKUP(C551,Base!$C:$F,4,FALSE) -> Manutenção e reparação de máquinas e equipamentos | I551: =VLOOKUP(D551,Base!$D:$F,3,FALSE) -> Manutenção e reparação de equipamentos eletrônicos e ópticos | J551: =VLOOKUP(E551,Base!$E:$F,2,FALSE) -> Manutenção e reparação de aparelhos e instrumentos de medida, teste e controle | K551: 3312102 | L551: =IFERROR(VLOOKUP($K551,Base_Atividades!$E$1:$N$2398,MATCH(BancoAjustado!L$1,Base_Atividades!$E$1:$N$1,0),FALSE),0) -> 1 | M551: =IFERROR(VLOOKUP($K551,Base_Atividades!$E$1:$N$2398,MATCH(BancoAjustado!M$1,Base_Atividades!$E$1:$N$1,0),FALSE),0) -> 0 | N551: =IFERROR(VLOOKUP($K551,Base_Atividades!$E$1:$N$2398,MATCH(BancoAjustado!N$1,Base_Atividades!$E$1:$N$1,0),FALSE),0) -> 0
A552: C | B552: 33 | C552: 331 | D552: 33121 | E552: 3312103 | F552: =VLOOKUP(A552,Base!$A:$F,6,FALSE) -> INDÚSTRIAS DE TRANSFORMAÇÃO | G552: =VLOOKUP(B552,Base!$B:$F,5,FALSE) -> MANUTENÇÃO, REPARAÇÃO E INSTALAÇÃO DE MÁQUINAS E EQUIPAMENTOS | H552: =VLOOKUP(C552,Base!$C:$F,4,FALSE) -> Manutenção e reparação de máquinas e equipamentos | I552: =VLOOKUP(D552,Base!$D:$F,3,FALSE) -> Manutenção e reparação de equipamentos eletrônicos e ópticos | J552: =VLOOKUP(E552,Base!$E:$F,2,FALSE) -> Manutenção e reparação de aparelhos eletromédicos e eletroterapêuticos e equipamentos de irradiação | K552: 3312103 | L552: =IFERROR(VLOOKUP($K552,Base_Atividades!$E$1:$N$2398,MATCH(BancoAjustado!L$1,Base_Atividades!$E$1:$N$1,0),FALSE),0) -> 1 | M552: =IFERROR(VLOOKUP($K552,Base_Atividades!$E$1:$N$2398,MATCH(BancoAjustado!M$1,Base_Atividades!$E$1:$N$1,0),FALSE),0) -> 0 | N552: =IFERROR(VLOOKUP($K552,Base_Atividades!$E$1:$N$2398,MATCH(BancoAjustado!N$1,Base_Atividades!$E$1:$N$1,0),FALSE),0) -> 0
A553: C | B553: 33 | C553: 331 | D553: 33121 | E553: 3312104 | F553: =VLOOKUP(A553,Base!$A:$F,6,FALSE) -> INDÚSTRIAS DE TRANSFORMAÇÃO | G553: =VLOOKUP(B553,Base!$B:$F,5,FALSE) -> MANUTENÇÃO, REPARAÇÃO E INSTALAÇÃO DE MÁQUINAS E EQUIPAMENTOS | H553: =VLOOKUP(C553,Base!$C:$F,4,FALSE) -> Manutenção e reparação de máquinas e equipamentos | I553: =VLOOKUP(D553,Base!$D:$F,3,FALSE) -> Manutenção e reparação de equipamentos eletrônicos e ópticos | J553: =VLOOKUP(E553,Base!$E:$F,2,FALSE) -> Manutenção e reparação de equipamentos e instrumentos ópticos | K553: 3312104 | L553: =IFERROR(VLOOKUP($K553,Base_Atividades!$E$1:$N$2398,MATCH(BancoAjustado!L$1,Base_Atividades!$E$1:$N$1,0),FALSE),0) -> 1 | M553: =IFERROR(VLOOKUP($K553,Base_Atividades!$E$1:$N$2398,MATCH(BancoAjustado!M$1,Base_Atividades!$E$1:$N$1,0),FALSE),0) -> 0 | N553: =IFERROR(VLOOKUP($K553,Base_Atividades!$E$1:$N$2398,MATCH(BancoAjustado!N$1,Base_Atividades!$E$1:$N$1,0),FALSE),0) -> 0
A554: C | B554: 33 | C554: 331 | D554: 33139 | E554: 3313901 | F554: =VLOOKUP(A554,Base!$A:$F,6,FALSE) -> INDÚSTRIAS DE TRANSFORMAÇÃO | G554: =VLOOKUP(B554,Base!$B:$F,5,FALSE) -> MANUTENÇÃO, REPARAÇÃO E INSTALAÇÃO DE MÁQUINAS E EQUIPAMENTOS | H554: =VLOOKUP(C554,Base!$C:$F,4,FALSE) -> Manutenção e reparação de máquinas e equipamentos | I554: =VLOOKUP(D554,Base!$D:$F,3,FALSE) -> Manutenção e reparação de máquinas e equipamentos elétricos | J554: =VLOOKUP(E554,Base!$E:$F,2,FALSE) -> Manutenção e reparação de geradores, transformadores e motores elétricos | K554: 3313901 | L554: =IFERROR(VLOOKUP($K554,Base_Atividades!$E$1:$N$2398,MATCH(BancoAjustado!L$1,Base_Atividades!$E$1:$N$1,0),FALSE),0) -> 1 | M554: =IFERROR(VLOOKUP($K554,Base_Atividades!$E$1:$N$2398,MATCH(BancoAjustado!M$1,Base_Atividades!$E$1:$N$1,0),FALSE),0) -> 0 | N554: =IFERROR(VLOOKUP($K554,Base_Atividades!$E$1:$N$2398,MATCH(BancoAjustado!N$1,Base_Atividades!$E$1:$N$1,0),FALSE),0) -> 0
A555: C | B555: 33 | C555: 331 | D555: 33139 | E555: 3313902 | F555: =VLOOKUP(A555,Base!$A:$F,6,FALSE) -> INDÚSTRIAS DE TRANSFORMAÇÃO | G555: =VLOOKUP(B555,Base!$B:$F,5,FALSE) -> MANUTENÇÃO, REPARAÇÃO E INSTALAÇÃO DE MÁQUINAS E EQUIPAMENTOS | H555: =VLOOKUP(C555,Base!$C:$F,4,FALSE) -> Manutenção e reparação de máquinas e equipamentos | I555: =VLOOKUP(D555,Base!$D:$F,3,FALSE) -> Manutenção e reparação de máquinas e equipamentos elétricos | J555: =VLOOKUP(E555,Base!$E:$F,2,FALSE) -> Manutenção e reparação de baterias e acumuladores elétricos, exceto para veículos | K555: 3313902 | L555: =IFERROR(VLOOKUP($K555,Base_Atividades!$E$1:$N$2398,MATCH(BancoAjustado!L$1,Base_Atividades!$E$1:$N$1,0),FALSE),0) -> 1 | M555: =IFERROR(VLOOKUP($K555,Base_Atividades!$E$1:$N$2398,MATCH(BancoAjustado!M$1,Base_Atividades!$E$1:$N$1,0),FALSE),0) -> 0 | N555: =IFERROR(VLOOKUP($K555,Base_Atividades!$E$1:$N$2398,MATCH(BancoAjustado!N$1,Base_Atividades!$E$1:$N$1,0),FALSE),0) -> 0
A556: C | B556: 33 | C556: 331 | D556: 33139 | E556: 3313999 | F556: =VLOOKUP(A556,Base!$A:$F,6,FALSE) -> INDÚSTRIAS DE TRANSFORMAÇÃO | G556: =VLOOKUP(B556,Base!$B:$F,5,FALSE) -> MANUTENÇÃO, REPARAÇÃO E INSTALAÇÃO DE MÁQUINAS E EQUIPAMENTOS | H556: =VLOOKUP(C556,Base!$C:$F,4,FALSE) -> Manutenção e reparação de máquinas e equipamentos | I556: =VLOOKUP(D556,Base!$D:$F,3,FALSE) -> Manutenção e reparação de máquinas e equipamentos elétricos | J556: =VLOOKUP(E556,Base!$E:$F,2,FALSE) -> Manutenção e reparação de máquinas, aparelhos e materiais elétricos não especificados anteriormente | K556: 3313999 | L556: =IFERROR(VLOOKUP($K556,Base_Atividades!$E$1:$N$2398,MATCH(BancoAjustado!L$1,Base_Atividades!$E$1:$N$1,0),FALSE),0) -> 1 | M556: =IFERROR(VLOOKUP($K556,Base_Atividades!$E$1:$N$2398,MATCH(BancoAjustado!M$1,Base_Atividades!$E$1:$N$1,0),FALSE),0) -> 0 | N556: =IFERROR(VLOOKUP($K556,Base_Atividades!$E$1:$N$2398,MATCH(BancoAjustado!N$1,Base_Atividades!$E$1:$N$1,0),FALSE),0) -> 0
A557: C | B557: 33 | C557: 331 | D557: 33147 | E557: 3314701 | F557: =VLOOKUP(A557,Base!$A:$F,6,FALSE) -> INDÚSTRIAS DE TRANSFORMAÇÃO | G557: =VLOOKUP(B557,Base!$B:$F,5,FALSE) -> MANUTENÇÃO, REPARAÇÃO E INSTALAÇÃO DE MÁQUINAS E EQUIPAMENTOS | H557: =VLOOKUP(C557,Base!$C:$F,4,FALSE) -> Manutenção e reparação de máquinas e equipamentos | I557: =VLOOKUP(D557,Base!$D:$F,3,FALSE) -> Manutenção e reparação de máquinas e equipamentos da indústria mecânica | J557: =VLOOKUP(E557,Base!$E:$F,2,FALSE) -> Manutenção e reparação de máquinas motrizes não elétricas | K557: 3314701 | L557: =IFERROR(VLOOKUP($K557,Base_Atividades!$E$1:$N$2398,MATCH(BancoAjustado!L$1,Base_Atividades!$E$1:$N$1,0),FALSE),0) -> 1 | M557: =IFERROR(VLOOKUP($K557,Base_Atividades!$E$1:$N$2398,MATCH(BancoAjustado!M$1,Base_Atividades!$E$1:$N$1,0),FALSE),0) -> 0 | N557: =IFERROR(VLOOKUP($K557,Base_Atividades!$E$1:$N$2398,MATCH(BancoAjustado!N$1,Base_Atividades!$E$1:$N$1,0),FALSE),0) -> 0
A558: C | B558: 33 | C558: 331 | D558: 33147 | E558: 3314702 | F558: =VLOOKUP(A558,Base!$A:$F,6,FALSE) -> INDÚSTRIAS DE TRANSFORMAÇÃO | G558: =VLOOKUP(B558,Base!$B:$F,5,FALSE) -> MANUTENÇÃO, REPARAÇÃO E INSTALAÇÃO DE MÁQUINAS E EQUIPAMENTOS | H558: =VLOOKUP(C558,Base!$C:$F,4,FALSE) -> Manutenção e reparação de máquinas e equipamentos | I558: =VLOOKUP(D558,Base!$D:$F,3,FALSE) -> Manutenção e reparação de máquinas e equipamentos da indústria mecânica | J558: =VLOOKUP(E558,Base!$E:$F,2,FALSE) -> Manutenção e reparação de equipamentos hidráulicos e pneumáticos, exceto válvulas | K558: 3314702 | L558: =IFERROR(VLOOKUP($K558,Base_Atividades!$E$1:$N$2398,MATCH(BancoAjustado!L$1,Base_Atividades!$E$1:$N$1,0),FALSE),0) -> 1 | M558: =IFERROR(VLOOKUP($K558,Base_Atividades!$E$1:$N$2398,MATCH(BancoAjustado!M$1,Base_Atividades!$E$1:$N$1,0),FALSE),0) -> 0 | N558: =IFERROR(VLOOKUP($K558,Base_Atividades!$E$1:$N$2398,MATCH(BancoAjustado!N$1,Base_Atividades!$E$1:$N$1,0),FALSE),0) -> 0
A559: C | B559: 33 | C559: 331 | D559: 33147 | E559: 3314703 | F559: =VLOOKUP(A559,Base!$A:$F,6,FALSE) -> INDÚSTRIAS DE TRANSFORMAÇÃO | G559: =VLOOKUP(B559,Base!$B:$F,5,FALSE) -> MANUTENÇÃO, REPARAÇÃO E INSTALAÇÃO DE MÁQUINAS E EQUIPAMENTOS | H559: =VLOOKUP(C559,Base!$C:$F,4,FALSE) -> Manutenção e reparação de máquinas e equipamentos | I559: =VLOOKUP(D559,Base!$D:$F,3,FALSE) -> Manutenção e reparação de máquinas e equipamentos da indústria mecânica | J559: =VLOOKUP(E559,Base!$E:$F,2,FALSE) -> Manutenção e reparação de válvulas industriais | K559: 3314703 | L559: =IFERROR(VLOOKUP($K559,Base_Atividades!$E$1:$N$2398,MATCH(BancoAjustado!L$1,Base_Atividades!$E$1:$N$1,0),FALSE),0) -> 1 | M559: =IFERROR(VLOOKUP($K559,Base_Atividades!$E$1:$N$2398,MATCH(BancoAjustado!M$1,Base_Atividades!$E$1:$N$1,0),FALSE),0) -> 0 | N559: =IFERROR(VLOOKUP($K559,Base_Atividades!$E$1:$N$2398,MATCH(BancoAjustado!N$1,Base_Atividades!$E$1:$N$1,0),FALSE),0) -> 0
A560: C | B560: 33 | C560: 331 | D560: 33147 | E560: 3314704 | F560: =VLOOKUP(A560,Base!$A:$F,6,FALSE) -> INDÚSTRIAS DE TRANSFORMAÇÃO | G560: =VLOOKUP(B560,Base!$B:$F,5,FALSE) -> MANUTENÇÃO, REPARAÇÃO E INSTALAÇÃO DE MÁQUINAS E EQUIPAMENTOS | H560: =VLOOKUP(C560,Base!$C:$F,4,FALSE) -> Manutenção e reparação de máquinas e equipamentos | I560: =VLOOKUP(D560,Base!$D:$F,3,FALSE) -> Manutenção e reparação de máquinas e equipamentos da indústria mecânica | J560: =VLOOKUP(E560,Base!$E:$F,2,FALSE) -> Manutenção e reparação de compressores | K560: 3314704 | L560: =IFERROR(VLOOKUP($K560,Base_Atividades!$E$1:$N$2398,MATCH(BancoAjustado!L$1,Base_Atividades!$E$1:$N$1,0),FALSE),0) -> 1 | M560: =IFERROR(VLOOKUP($K560,Base_Atividades!$E$1:$N$2398,MATCH(BancoAjustado!M$1,Base_Atividades!$E$1:$N$1,0),FALSE),0) -> 0 | N560: =IFERROR(VLOOKUP($K560,Base_Atividades!$E$1:$N$2398,MATCH(BancoAjustado!N$1,Base_Atividades!$E$1:$N$1,0),FALSE),0) -> 0
A561: C | B561: 33 | C561: 331 | D561: 33147 | E561: 3314705 | F561: =VLOOKUP(A561,Base!$A:$F,6,FALSE) -> INDÚSTRIAS DE TRANSFORMAÇÃO | G561: =VLOOKUP(B561,Base!$B:$F,5,FALSE) -> MANUTENÇÃO, REPARAÇÃO E INSTALAÇÃO DE MÁQUINAS E EQUIPAMENTOS | H561: =VLOOKUP(C561,Base!$C:$F,4,FALSE) -> Manutenção e reparação de máquinas e equipamentos | I561: =VLOOKUP(D561,Base!$D:$F,3,FALSE) -> Manutenção e reparação de máquinas e equipamentos da indústria mecânica | J561: =VLOOKUP(E561,Base!$E:$F,2,FALSE) -> Manutenção e reparação de equipamentos de transmissão para fins industriais | K561: 3314705 | L561: =IFERROR(VLOOKUP($K561,Base_Atividades!$E$1:$N$2398,MATCH(BancoAjustado!L$1,Base_Atividades!$E$1:$N$1,0),FALSE),0) -> 1 | M561: =IFERROR(VLOOKUP($K561,Base_Atividades!$E$1:$N$2398,MATCH(BancoAjustado!M$1,Base_Atividades!$E$1:$N$1,0),FALSE),0) -> 0 | N561: =IFERROR(VLOOKUP($K561,Base_Atividades!$E$1:$N$2398,MATCH(BancoAjustado!N$1,Base_Atividades!$E$1:$N$1,0),FALSE),0) -> 0
... A688: G | B688: 45 | C688: 454 | D688: 45439 | E688: 4543900 | F688: =VLOOKUP(A688,Base!$A:$F,6,FALSE) -> COMÉRCIO; REPARAÇÃO DE VEÍCULOS AUTOMOTORES E MOTOCICLETAS | G688: =VLOOKUP(B688,Base!$B:$F,5,FALSE) -> COMÉRCIO E REPARAÇÃO DE VEÍCULOS AUTOMOTORES E MOTOCICLETAS | H688: =VLOOKUP(C688,Base!$C:$F,4,FALSE) -> Comércio, manutenção e reparação de motocicletas, peças e acessórios | I688: =VLOOKUP(D688,Base!$D:$F,3,FALSE) -> Manutenção e reparação de motocicletas | J688: =VLOOKUP(E688,Base!$E:$F,2,FALSE) -> Manutenção e reparação de motocicletas e motonetas | K688: 4543900 | L688: =IFERROR(VLOOKUP($K688,Base_Atividades!$E$1:$N$2398,MATCH(BancoAjustado!L$1,Base_Atividades!$E$1:$N$1,0),FALSE),0) -> 1 | M688: =IFERROR(VLOOKUP($K688,Base_Atividades!$E$1:$N$2398,MATCH(BancoAjustado!M$1,Base_Atividades!$E$1:$N$1,0),FALSE),0) -> 0 | N688: =IFERROR(VLOOKUP($K688,Base_Atividades!$E$1:$N$2398,MATCH(BancoAjustado!N$1,Base_Atividades!$E$1:$N$1,0),FALSE),0) -> 0
A689: G | B689: 46 | C689: 461 | D689: 46117 | E689: 4611700 | F689: =VLOOKUP(A689,Base!$A:$F,6,FALSE) -> COMÉRCIO; REPARAÇÃO DE VEÍCULOS AUTOMOTORES E MOTOCICLETAS | G689: =VLOOKUP(B689,Base!$B:$F,5,FALSE) -> COMÉRCIO POR ATACADO, EXCETO VEÍCULOS AUTOMOTORES E MOTOCICLETAS | H689: =VLOOKUP(C689,Base!$C:$F,4,FALSE) -> Representantes comerciais e agentes do comércio, exceto de veículos automotores e motocicletas | I689: =VLOOKUP(D689,Base!$D:$F,3,FALSE) -> Representantes comerciais e agentes do comércio de matérias-primas agrícolas e animais vivos | J689: =VLOOKUP(E689,Base!$E:$F,2,FALSE) -> Representantes comerciais e agentes do comércio de matérias-primas agrícolas e animais vivos | K689: 4611700 | L689: =IFERROR(VLOOKUP($K689,Base_Atividades!$E$1:$N$2398,MATCH(BancoAjustado!L$1,Base_Atividades!$E$1:$N$1,0),FALSE),0) -> 0 | M689: =IFERROR(VLOOKUP($K689,Base_Atividades!$E$1:$N$2398,MATCH(BancoAjustado!M$1,Base_Atividades!$E$1:$N$1,0),FALSE),0) -> 0 | N689: =IFERROR(VLOOKUP($K689,Base_Atividades!$E$1:$N$2398,MATCH(BancoAjustado!N$1,Base_Atividades!$E$1:$N$1,0),FALSE),0) -> 0
A690: G | B690: 46 | C690: 461 | D690: 46125 | E690: 4612500 | F690: =VLOOKUP(A690,Base!$A:$F,6,FALSE) -> COMÉRCIO; REPARAÇÃO DE VEÍCULOS AUTOMOTORES E MOTOCICLETAS | G690: =VLOOKUP(B690,Base!$B:$F,5,FALSE) -> COMÉRCIO POR ATACADO, EXCETO VEÍCULOS AUTOMOTORES E MOTOCICLETAS | H690: =VLOOKUP(C690,Base!$C:$F,4,FALSE) -> Representantes comerciais e agentes do comércio, exceto de veículos automotores e motocicletas | I690: =VLOOKUP(D690,Base!$D:$F,3,FALSE) -> Representantes comerciais e agentes do comércio de combustíveis, minerais, produtos siderúrgicos e químicos | J690: =VLOOKUP(E690,Base!$E:$F,2,FALSE) -> Representantes comerciais e agentes do comércio de combustíveis, minerais, produtos siderúrgicos e químicos | K690: 4612500 | L690: =IFERROR(VLOOKUP($K690,Base_Atividades!$E$1:$N$2398,MATCH(BancoAjustado!L$1,Base_Atividades!$E$1:$N$1,0),FALSE),0) -> 0 | M690: =IFERROR(VLOOKUP($K690,Base_Atividades!$E$1:$N$2398,MATCH(BancoAjustado!M$1,Base_Atividades!$E$1:$N$1,0),FALSE),0) -> 0 | N690: =IFERROR(VLOOKUP($K690,Base_Atividades!$E$1:$N$2398,MATCH(BancoAjustado!N$1,Base_Atividades!$E$1:$N$1,0),FALSE),0) -> 0
A691: G | B691: 46 | C691: 461 | D691: 46133 | E691: 4613300 | F691: =VLOOKUP(A691,Base!$A:$F,6,FALSE) -> COMÉRCIO; REPARAÇÃO DE VEÍCULOS AUTOMOTORES E MOTOCICLETAS | G691: =VLOOKUP(B691,Base!$B:$F,5,FALSE) -> COMÉRCIO POR ATACADO, EXCETO VEÍCULOS AUTOMOTORES E MOTOCICLETAS | H691: =VLOOKUP(C691,Base!$C:$F,4,FALSE) -> Representantes comerciais e agentes do comércio, exceto de veículos automotores e motocicletas | I691: =VLOOKUP(D691,Base!$D:$F,3,FALSE) -> Representantes comerciais e agentes do comércio de madeira, material de construção e ferragens | J691: =VLOOKUP(E691,Base!$E:$F,2,FALSE) -> Representantes comerciais e agentes do comércio de madeira, material de construção e ferragens | K691: 4613300 | L691: =IFERROR(VLOOKUP($K691,Base_Atividades!$E$1:$N$2398,MATCH(BancoAjustado!L$1,Base_Atividades!$E$1:$N$1,0),FALSE),0) -> 0 | M691: =IFERROR(VLOOKUP($K691,Base_Atividades!$E$1:$N$2398,MATCH(BancoAjustado!M$1,Base_Atividades!$E$1:$N$1,0),FALSE),0) -> 0 | N691: =IFERROR(VLOOKUP($K691,Base_Atividades!$E$1:$N$2398,MATCH(BancoAjustado!N$1,Base_Atividades!$E$1:$N$1,0),FALSE),0) -> 0
A692: G | B692: 46 | C692: 461 | D692: 46141 | E692: 4614100 | F692: =VLOOKUP(A692,Base!$A:$F,6,FALSE) -> COMÉRCIO; REPARAÇÃO DE VEÍCULOS AUTOMOTORES E MOTOCICLETAS | G692: =VLOOKUP(B692,Base!$B:$F,5,FALSE) -> COMÉRCIO POR ATACADO, EXCETO VEÍCULOS AUTOMOTORES E MOTOCICLETAS | H692: =VLOOKUP(C692,Base!$C:$F,4,FALSE) -> Representantes comerciais e agentes do comércio, exceto de veículos automotores e motocicletas | I692: =VLOOKUP(D692,Base!$D:$F,3,FALSE) -> Representantes comerciais e agentes do comércio de máquinas, equipamentos, embarcações e aeronaves | J692: =VLOOKUP(E692,Base!$E:$F,2,FALSE) -> Representantes comerciais e agentes do comércio de máquinas, equipamentos, embarcações e aeronaves | K692: 4614100 | L692: =IFERROR(VLOOKUP($K692,Base_Atividades!$E$1:$N$2398,MATCH(BancoAjustado!L$1,Base_Atividades!$E$1:$N$1,0),FALSE),0) -> 0 | M692: =IFERROR(VLOOKUP($K692,Base_Atividades!$E$1:$N$2398,MATCH(BancoAjustado!M$1,Base_Atividades!$E$1:$N$1,0),FALSE),0) -> 0 | N692: =IFERROR(VLOOKUP($K692,Base_Atividades!$E$1:$N$2398,MATCH(BancoAjustado!N$1,Base_Atividades!$E$1:$N$1,0),FALSE),0) -> 0
A693: G | B693: 46 | C693: 461 | D693: 46150 | E693: 4615000 | F693: =VLOOKUP(A693,Base!$A:$F,6,FALSE) -> COMÉRCIO; REPARAÇÃO DE VEÍCULOS AUTOMOTORES E MOTOCICLETAS | G693: =VLOOKUP(B693,Base!$B:$F,5,FALSE) -> COMÉRCIO POR ATACADO, EXCETO VEÍCULOS AUTOMOTORES E MOTOCICLETAS | H693: =VLOOKUP(C693,Base!$C:$F,4,FALSE) -> Representantes comerciais e agentes do comércio, exceto de veículos automotores e motocicletas | I693: =VLOOKUP(D693,Base!$D:$F,3,FALSE) -> Representantes comerciais e agentes do comércio de eletrodomésticos, móveis e artigos de uso doméstico | J693: =VLOOKUP(E693,Base!$E:$F,2,FALSE) -> Representantes comerciais e agentes do comércio de eletrodomésticos, móveis e artigos de uso doméstico | K693: 4615000 | L693: =IFERROR(VLOOKUP($K693,Base_Atividades!$E$1:$N$2398,MATCH(BancoAjustado!L$1,Base_Atividades!$E$1:$N$1,0),FALSE),0) -> 0 | M693: =IFERROR(VLOOKUP($K693,Base_Atividades!$E$1:$N$2398,MATCH(BancoAjustado!M$1,Base_Atividades!$E$1:$N$1,0),FALSE),0) -> 0 | N693: =IFERROR(VLOOKUP($K693,Base_Atividades!$E$1:$N$2398,MATCH(BancoAjustado!N$1,Base_Atividades!$E$1:$N$1,0),FALSE),0) -> 0
A694: G | B694: 46 | C694: 461 | D694: 46168 | E694: 4616800 | F694: =VLOOKUP(A694,Base!$A:$F,6,FALSE) -> COMÉRCIO; REPARAÇÃO DE VEÍCULOS AUTOMOTORES E MOTOCICLETAS | G694: =VLOOKUP(B694,Base!$B:$F,5,FALSE) -> COMÉRCIO POR ATACADO, EXCETO VEÍCULOS AUTOMOTORES E MOTOCICLETAS | H694: =VLOOKUP(C694,Base!$C:$F,4,FALSE) -> Representantes comerciais e agentes do comércio, exceto de veículos automotores e motocicletas | I694: =VLOOKUP(D694,Base!$D:$F,3,FALSE) -> Representantes comerciais e agentes do comércio de têxteis, vestuário, calçados e artigos de viagem | J694: =VLOOKUP(E694,Base!$E:$F,2,FALSE) -> Representantes comerciais e agentes do comércio de têxteis, vestuário, calçados e artigos de viagem | K694: 4616800 | L694: =IFERROR(VLOOKUP($K694,Base_Atividades!$E$1:$N$2398,MATCH(BancoAjustado!L$1,Base_Atividades!$E$1:$N$1,0),FALSE),0) -> 0 | M694: =IFERROR(VLOOKUP($K694,Base_Atividades!$E$1:$N$2398,MATCH(BancoAjustado!M$1,Base_Atividades!$E$1:$N$1,0),FALSE),0) -> 0 | N694: =IFERROR(VLOOKUP($K694,Base_Atividades!$E$1:$N$2398,MATCH(BancoAjustado!N$1,Base_Atividades!$E$1:$N$1,0),FALSE),0) -> 0
A695: G | B695: 46 | C695: 461 | D695: 46176 | E695: 4617600 | F695: =VLOOKUP(A695,Base!$A:$F,6,FALSE) -> COMÉRCIO; REPARAÇÃO DE VEÍCULOS AUTOMOTORES E MOTOCICLETAS | G695: =VLOOKUP(B695,Base!$B:$F,5,FALSE) -> COMÉRCIO POR ATACADO, EXCETO VEÍCULOS AUTOMOTORES E MOTOCICLETAS | H695: =VLOOKUP(C695,Base!$C:$F,4,FALSE) -> Representantes comerciais e agentes do comércio, exceto de veículos automotores e motocicletas | I695: =VLOOKUP(D695,Base!$D:$F,3,FALSE) -> Representantes comerciais e agentes do comércio de produtos alimentícios, bebidas e fumo | J695: =VLOOKUP(E695,Base!$E:$F,2,FALSE) -> Representantes comerciais e agentes do comércio de produtos alimentícios, bebidas e fumo | K695: 4617600 | L695: =IFERROR(VLOOKUP($K695,Base_Atividades!$E$1:$N$2398,MATCH(BancoAjustado!L$1,Base_Atividades!$E$1:$N$1,0),FALSE),0) -> 0 | M695: =IFERROR(VLOOKUP($K695,Base_Atividades!$E$1:$N$2398,MATCH(BancoAjustado!M$1,Base_Atividades!$E$1:$N$1,0),FALSE),0) -> 0 | N695: =IFERROR(VLOOKUP($K695,Base_Atividades!$E$1:$N$2398,MATCH(BancoAjustado!N$1,Base_Atividades!$E$1:$N$1,0),FALSE),0) -> 0
A696: G | B696: 46 | C696: 461 | D696: 46184 | E696: 4618401 | F696: =VLOOKUP(A696,Base!$A:$F,6,FALSE) -> COMÉRCIO; REPARAÇÃO DE VEÍCULOS AUTOMOTORES E MOTOCICLETAS | G696: =VLOOKUP(B696,Base!$B:$F,5,FALSE) -> COMÉRCIO POR ATACADO, EXCETO VEÍCULOS AUTOMOTORES E MOTOCICLETAS | H696: =VLOOKUP(C696,Base!$C:$F,4,FALSE) -> Representantes comerciais e agentes do comércio, exceto de veículos automotores e motocicletas | I696: =VLOOKUP(D696,Base!$D:$F,3,FALSE) -> Representantes comerciais e agentes do comércio especializado em produtos não especificados anteriormente | J696: =VLOOKUP(E696,Base!$E:$F,2,FALSE) -> Representantes comerciais e agentes do comércio de medicamentos, cosméticos e produtos de perfumaria | K696: 4618401 | L696: =IFERROR(VLOOKUP($K696,Base_Atividades!$E$1:$N$2398,MATCH(BancoAjustado!L$1,Base_Atividades!$E$1:$N$1,0),FALSE),0) -> 0 | M696: =IFERROR(VLOOKUP($K696,Base_Atividades!$E$1:$N$2398,MATCH(BancoAjustado!M$1,Base_Atividades!$E$1:$N$1,0),FALSE),0) -> 0 | N696: =IFERROR(VLOOKUP($K696,Base_Atividades!$E$1:$N$2398,MATCH(BancoAjustado!N$1,Base_Atividades!$E$1:$N$1,0),FALSE),0) -> 0
A697: G | B697: 46 | C697: 461 | D697: 46184 | E697: 4618402 | F697: =VLOOKUP(A697,Base!$A:$F,6,FALSE) -> COMÉRCIO; REPARAÇÃO DE VEÍCULOS AUTOMOTORES E MOTOCICLETAS | G697: =VLOOKUP(B697,Base!$B:$F,5,FALSE) -> COMÉRCIO POR ATACADO, EXCETO VEÍCULOS AUTOMOTORES E MOTOCICLETAS | H697: =VLOOKUP(C697,Base!$C:$F,4,FALSE) -> Representantes comerciais e agentes do comércio, exceto de veículos automotores e motocicletas | I697: =VLOOKUP(D697,Base!$D:$F,3,FALSE) -> Representantes comerciais e agentes do comércio especializado em produtos não especificados anteriormente | J697: =VLOOKUP(E697,Base!$E:$F,2,FALSE) -> Representantes comerciais e agentes do comércio de instrumentos e materiais odonto-médico-hospitalares | K697: 4618402 | L697: =IFERROR(VLOOKUP($K697,Base_Atividades!$E$1:$N$2398,MATCH(BancoAjustado!L$1,Base_Atividades!$E$1:$N$1,0),FALSE),0) -> 0 | M697: =IFERROR(VLOOKUP($K697,Base_Atividades!$E$1:$N$2398,MATCH(BancoAjustado!M$1,Base_Atividades!$E$1:$N$1,0),FALSE),0) -> 0 | N697: =IFERROR(VLOOKUP($K697,Base_Atividades!$E$1:$N$2398,MATCH(BancoAjustado!N$1,Base_Atividades!$E$1:$N$1,0),FALSE),0) -> 0
A698: G | B698: 46 | C698: 461 | D698: 46184 | E698: 4618403 | F698: =VLOOKUP(A698,Base!$A:$F,6,FALSE) -> COMÉRCIO; REPARAÇÃO DE VEÍCULOS AUTOMOTORES E MOTOCICLETAS | G698: =VLOOKUP(B698,Base!$B:$F,5,FALSE) -> COMÉRCIO POR ATACADO, EXCETO VEÍCULOS AUTOMOTORES E MOTOCICLETAS | H698: =VLOOKUP(C698,Base!$C:$F,4,FALSE) -> Representantes comerciais e agentes do comércio, exceto de veículos automotores e motocicletas | I698: =VLOOKUP(D698,Base!$D:$F,3,FALSE) -> Representantes comerciais e agentes do comércio especializado em produtos não especificados anteriormente | J698: =VLOOKUP(E698,Base!$E:$F,2,FALSE) -> Representantes comerciais e agentes do comércio de jornais, revistas e outras publicações | K698: 4618403 | L698: =IFERROR(VLOOKUP($K698,Base_Atividades!$E$1:$N$2398,MATCH(BancoAjustado!L$1,Base_Atividades!$E$1:$N$1,0),FALSE),0) -> 0 | M698: =IFERROR(VLOOKUP($K698,Base_Atividades!$E$1:$N$2398,MATCH(BancoAjustado!M$1,Base_Atividades!$E$1:$N$1,0),FALSE),0) -> 0 | N698: =IFERROR(VLOOKUP($K698,Base_Atividades!$E$1:$N$2398,MATCH(BancoAjustado!N$1,Base_Atividades!$E$1:$N$1,0),FALSE),0) -> 0
A699: G | B699: 46 | C699: 461 | D699: 46184 | E699: 4618499 | F699: =VLOOKUP(A699,Base!$A:$F,6,FALSE) -> COMÉRCIO; REPARAÇÃO DE VEÍCULOS AUTOMOTORES E MOTOCICLETAS | G699: =VLOOKUP(B699,Base!$B:$F,5,FALSE) -> COMÉRCIO POR ATACADO, EXCETO VEÍCULOS AUTOMOTORES E MOTOCICLETAS | H699: =VLOOKUP(C699,Base!$C:$F,4,FALSE) -> Representantes comerciais e agentes do comércio, exceto de veículos automotores e motocicletas | I699: =VLOOKUP(D699,Base!$D:$F,3,FALSE) -> Representantes comerciais e agentes do comércio especializado em produtos não especificados anteriormente | J699: =VLOOKUP(E699,Base!$E:$F,2,FALSE) -> Outros representantes comerciais e agentes do comércio especializado em produtos não especificados anteriormente | K699: 4618499 | L699: =IFERROR(VLOOKUP($K699,Base_Atividades!$E$1:$N$2398,MATCH(BancoAjustado!L$1,Base_Atividades!$E$1:$N$1,0),FALSE),0) -> 0 | M699: =IFERROR(VLOOKUP($K699,Base_Atividades!$E$1:$N$2398,MATCH(BancoAjustado!M$1,Base_Atividades!$E$1:$N$1,0),FALSE),0) -> 0 | N699: =IFERROR(VLOOKUP($K699,Base_Atividades!$E$1:$N$2398,MATCH(BancoAjustado!N$1,Base_Atividades!$E$1:$N$1,0),FALSE),0) -> 0
A700: G | B700: 46 | C700: 461 | D700: 46192 | E700: 4619200 | F700: =VLOOKUP(A700,Base!$A:$F,6,FALSE) -> COMÉRCIO; REPARAÇÃO DE VEÍCULOS AUTOMOTORES E MOTOCICLETAS | G700: =VLOOKUP(B700,Base!$B:$F,5,FALSE) -> COMÉRCIO POR ATACADO, EXCETO VEÍCULOS AUTOMOTORES E MOTOCICLETAS | H700: =VLOOKUP(C700,Base!$C:$F,4,FALSE) -> Representantes comerciais e agentes do comércio, exceto de veículos automotores e motocicletas | I700: =VLOOKUP(D700,Base!$D:$F,3,FALSE) -> Representantes comerciais e agentes do comércio de mercadorias em geral não especializado | J700: =VLOOKUP(E700,Base!$E:$F,2,FALSE) -> Representantes comerciais e agentes do comércio de mercadorias em geral não especializado | K700: 4619200 | L700: =IFERROR(VLOOKUP($K700,Base_Atividades!$E$1:$N$2398,MATCH(BancoAjustado!L$1,Base_Atividades!$E$1:$N$1,0),FALSE),0) -> 0 | M700: =IFERROR(VLOOKUP($K700,Base_Atividades!$E$1:$N$2398,MATCH(BancoAjustado!M$1,Base_Atividades!$E$1:$N$1,0),FALSE),0) -> 0 | N700: =IFERROR(VLOOKUP($K700,Base_Atividades!$E$1:$N$2398,MATCH(BancoAjustado!N$1,Base_Atividades!$E$1:$N$1,0),FALSE),0) -> 0
... A1012: J | B1012: 62 | C1012: 620 | D1012: 62091 | E1012: 6209100 | F1012: =VLOOKUP(A1012,Base!$A:$F,6,FALSE) -> INFORMAÇÃO E COMUNICAÇÃO | G1012: =VLOOKUP(B1012,Base!$B:$F,5,FALSE) -> ATIVIDADES DOS SERVIÇOS DE TECNOLOGIA DA INFORMAÇÃO | H1012: =VLOOKUP(C1012,Base!$C:$F,4,FALSE) -> Atividades dos serviços de tecnologia da informação | I1012: =VLOOKUP(D1012,Base!$D:$F,3,FALSE) -> Suporte técnico, manutenção e outros serviços em tecnologia da informação | J1012: =VLOOKUP(E1012,Base!$E:$F,2,FALSE) -> Suporte técnico, manutenção e outros serviços em tecnologia da informação | K1012: 6209100 | L1012: =IFERROR(VLOOKUP($K1012,Base_Atividades!$E$1:$N$2398,MATCH(BancoAjustado!L$1,Base_Atividades!$E$1:$N$1,0),FALSE),0) -> 1 | M1012: =IFERROR(VLOOKUP($K1012,Base_Atividades!$E$1:$N$2398,MATCH(BancoAjustado!M$1,Base_Atividades!$E$1:$N$1,0),FALSE),0) -> 0 | N1012: =IFERROR(VLOOKUP($K1012,Base_Atividades!$E$1:$N$2398,MATCH(BancoAjustado!N$1,Base_Atividades!$E$1:$N$1,0),FALSE),0) -> 0
A1013: J | B1013: 63 | C1013: 631 | D1013: 63119 | E1013: 6311900 | F1013: =VLOOKUP(A1013,Base!$A:$F,6,FALSE) -> INFORMAÇÃO E COMUNICAÇÃO | G1013: =VLOOKUP(B1013,Base!$B:$F,5,FALSE) -> ATIVIDADES DE PRESTAÇÃO DE SERVIÇOS DE INFORMAÇÃO | H1013: =VLOOKUP(C1013,Base!$C:$F,4,FALSE) -> Tratamento de dados, hospedagem na Internet e outras atividades relacionadas | I1013: =VLOOKUP(D1013,Base!$D:$F,3,FALSE) -> Tratamento de dados, provedores de serviços de aplicação e serviços de hospedagem na Internet | J1013: =VLOOKUP(E1013,Base!$E:$F,2,FALSE) -> Tratamento de dados, provedores de serviços de aplicação e serviços de hospedagem na Internet | K1013: 6311900 | L1013: =IFERROR(VLOOKUP($K1013,Base_Atividades!$E$1:$N$2398,MATCH(BancoAjustado!L$1,Base_Atividades!$E$1:$N$1,0),FALSE),0) -> 1 | M1013: =IFERROR(VLOOKUP($K1013,Base_Atividades!$E$1:$N$2398,MATCH(BancoAjustado!M$1,Base_Atividades!$E$1:$N$1,0),FALSE),0) -> 0 | N1013: =IFERROR(VLOOKUP($K1013,Base_Atividades!$E$1:$N$2398,MATCH(BancoAjustado!N$1,Base_Atividades!$E$1:$N$1,0),FALSE),0) -> 0
A1014: J | B1014: 63 | C1014: 631 | D1014: 63194 | E1014: 6319400 | F1014: =VLOOKUP(A1014,Base!$A:$F,6,FALSE) -> INFORMAÇÃO E COMUNICAÇÃO | G1014: =VLOOKUP(B1014,Base!$B:$F,5,FALSE) -> ATIVIDADES DE PRESTAÇÃO DE SERVIÇOS DE INFORMAÇÃO | H1014: =VLOOKUP(C1014,Base!$C:$F,4,FALSE) -> Tratamento de dados, hospedagem na Internet e outras atividades relacionadas | I1014: =VLOOKUP(D1014,Base!$D:$F,3,FALSE) -> Portais, provedores de conteúdo e outros serviços de informação na Internet | J1014: =VLOOKUP(E1014,Base!$E:$F,2,FALSE) -> Portais, provedores de conteúdo e outros serviços de informação na Internet | K1014: 6319400 | L1014: =IFERROR(VLOOKUP($K1014,Base_Atividades!$E$1:$N$2398,MATCH(BancoAjustado!L$1,Base_Atividades!$E$1:$N$1,0),FALSE),0) -> 1 | M1014: =IFERROR(VLOOKUP($K1014,Base_Atividades!$E$1:$N$2398,MATCH(BancoAjustado!M$1,Base_Atividades!$E$1:$N$1,0),FALSE),0) -> 0 | N1014: =IFERROR(VLOOKUP($K1014,Base_Atividades!$E$1:$N$2398,MATCH(BancoAjustado!N$1,Base_Atividades!$E$1:$N$1,0),FALSE),0) -> 0
A1015: J | B1015: 63 | C1015: 639 | D1015: 63917 | E1015: 6391700 | F1015: =VLOOKUP(A1015,Base!$A:$F,6,FALSE) -> INFORMAÇÃO E COMUNICAÇÃO | G1015: =VLOOKUP(B1015,Base!$B:$F,5,FALSE) -> ATIVIDADES DE PRESTAÇÃO DE SERVIÇOS DE INFORMAÇÃO | H1015: =VLOOKUP(C1015,Base!$C:$F,4,FALSE) -> Outras atividades de prestação de serviços de informação | I1015: =VLOOKUP(D1015,Base!$D:$F,3,FALSE) -> Agências de notícias | J1015: =VLOOKUP(E1015,Base!$E:$F,2,FALSE) -> Agências de notícias | K1015: 6391700 | L1015: =IFERROR(VLOOKUP($K1015,Base_Atividades!$E$1:$N$2398,MATCH(BancoAjustado!L$1,Base_Atividades!$E$1:$N$1,0),FALSE),0) -> 1 | M1015: =IFERROR(VLOOKUP($K1015,Base_Atividades!$E$1:$N$2398,MATCH(BancoAjustado!M$1,Base_Atividades!$E$1:$N$1,0),FALSE),0) -> 0 | N1015: =IFERROR(VLOOKUP($K1015,Base_Atividades!$E$1:$N$2398,MATCH(BancoAjustado!N$1,Base_Atividades!$E$1:$N$1,0),FALSE),0) -> 0
A1016: J | B1016: 63 | C1016: 639 | D1016: 63992 | E1016: 6399200 | F1016: =VLOOKUP(A1016,Base!$A:$F,6,FALSE) -> INFORMAÇÃO E COMUNICAÇÃO | G1016: =VLOOKUP(B1016,Base!$B:$F,5,FALSE) -> ATIVIDADES DE PRESTAÇÃO DE SERVIÇOS DE INFORMAÇÃO | H1016: =VLOOKUP(C1016,Base!$C:$F,4,FALSE) -> Outras atividades de prestação de serviços de informação | I1016: =VLOOKUP(D1016,Base!$D:$F,3,FALSE) -> Outras atividades de prestação de serviços de informação não especificadas anteriormente | J1016: =VLOOKUP(E1016,Base!$E:$F,2,FALSE) -> Outras atividades de prestação de serviços de informação não especificadas anteriormente | K1016: 6399200 | L1016: =IFERROR(VLOOKUP($K1016,Base_Atividades!$E$1:$N$2398,MATCH(BancoAjustado!L$1,Base_Atividades!$E$1:$N$1,0),FALSE),0) -> 1 | M1016: =IFERROR(VLOOKUP($K1016,Base_Atividades!$E$1:$N$2398,MATCH(BancoAjustado!M$1,Base_Atividades!$E$1:$N$1,0),FALSE),0) -> 0 | N1016: =IFERROR(VLOOKUP($K1016,Base_Atividades!$E$1:$N$2398,MATCH(BancoAjustado!N$1,Base_Atividades!$E$1:$N$1,0),FALSE),0) -> 0
A1017: K | B1017: 64 | C1017: 641 | D1017: 64107 | E1017: 6410700 | F1017: =VLOOKUP(A1017,Base!$A:$F,6,FALSE) -> ATIVIDADES FINANCEIRAS, DE SEGUROS E SERVIÇOS RELACIONADOS | G1017: =VLOOKUP(B1017,Base!$B:$F,5,FALSE) -> ATIVIDADES DE SERVIÇOS FINANCEIROS | H1017: =VLOOKUP(C1017,Base!$C:$F,4,FALSE) -> Banco Central | I1017: =VLOOKUP(D1017,Base!$D:$F,3,FALSE) -> Banco Central | J1017: =VLOOKUP(E1017,Base!$E:$F,2,FALSE) -> Banco Central | K1017: 6410700 | L1017: =IFERROR(VLOOKUP($K1017,Base_Atividades!$E$1:$N$2398,MATCH(BancoAjustado!L$1,Base_Atividades!$E$1:$N$1,0),FALSE),0) -> 0 | M1017: =IFERROR(VLOOKUP($K1017,Base_Atividades!$E$1:$N$2398,MATCH(BancoAjustado!M$1,Base_Atividades!$E$1:$N$1,0),FALSE),0) -> 0 | N1017: =IFERROR(VLOOKUP($K1017,Base_Atividades!$E$1:$N$2398,MATCH(BancoAjustado!N$1,Base_Atividades!$E$1:$N$1,0),FALSE),0) -> 0
A1018: K | B1018: 64 | C1018: 642 | D1018: 64212 | E1018: 6421200 | F1018: =VLOOKUP(A1018,Base!$A:$F,6,FALSE) -> ATIVIDADES FINANCEIRAS, DE SEGUROS E SERVIÇOS RELACIONADOS | G1018: =VLOOKUP(B1018,Base!$B:$F,5,FALSE) -> ATIVIDADES DE SERVIÇOS FINANCEIROS | H1018: =VLOOKUP(C1018,Base!$C:$F,4,FALSE) -> Intermediação monetária - depósitos à vista | I1018: =VLOOKUP(D1018,Base!$D:$F,3,FALSE) -> Bancos comerciais | J1018: =VLOOKUP(E1018,Base!$E:$F,2,FALSE) -> Bancos comerciais | K1018: 6421200 | L1018: =IFERROR(VLOOKUP($K1018,Base_Atividades!$E$1:$N$2398,MATCH(BancoAjustado!L$1,Base_Atividades!$E$1:$N$1,0),FALSE),0) -> 0 | M1018: =IFERROR(VLOOKUP($K1018,Base_Atividades!$E$1:$N$2398,MATCH(BancoAjustado!M$1,Base_Atividades!$E$1:$N$1,0),FALSE),0) -> 0 | N1018: =IFERROR(VLOOKUP($K1018,Base_Atividades!$E$1:$N$2398,MATCH(BancoAjustado!N$1,Base_Atividades!$E$1:$N$1,0),FALSE),0) -> 0
A1019: K | B1019: 64 | C1019: 642 | D1019: 64221 | E1019: 6422100 | F1019: =VLOOKUP(A1019,Base!$A:$F,6,FALSE) -> ATIVIDADES FINANCEIRAS, DE SEGUROS E SERVIÇOS RELACIONADOS | G1019: =VLOOKUP(B1019,Base!$B:$F,5,FALSE) -> ATIVIDADES DE SERVIÇOS FINANCEIROS | H1019: =VLOOKUP(C1019,Base!$C:$F,4,FALSE) -> Intermediação monetária - depósitos à vista | I1019: =VLOOKUP(D1019,Base!$D:$F,3,FALSE) -> Bancos múltiplos, com carteira comercial | J1019: =VLOOKUP(E1019,Base!$E:$F,2,FALSE) -> Bancos múltiplos, com carteira comercial | K1019: 6422100 | L1019: =IFERROR(VLOOKUP($K1019,Base_Atividades!$E$1:$N$2398,MATCH(BancoAjustado!L$1,Base_Atividades!$E$1:$N$1,0),FALSE),0) -> 0 | M1019: =IFERROR(VLOOKUP($K1019,Base_Atividades!$E$1:$N$2398,MATCH(BancoAjustado!M$1,Base_Atividades!$E$1:$N$1,0),FALSE),0) -> 0 | N1019: =IFERROR(VLOOKUP($K1019,Base_Atividades!$E$1:$N$2398,MATCH(BancoAjustado!N$1,Base_Atividades!$E$1:$N$1,0),FALSE),0) -> 0
A1020: K | B1020: 64 | C1020: 642 | D1020: 64239 | E1020: 6423900 | F1020: =VLOOKUP(A1020,Base!$A:$F,6,FALSE) -> ATIVIDADES FINANCEIRAS, DE SEGUROS E SERVIÇOS RELACIONADOS | G1020: =VLOOKUP(B1020,Base!$B:$F,5,FALSE) -> ATIVIDADES DE SERVIÇOS FINANCEIROS | H1020: =VLOOKUP(C1020,Base!$C:$F,4,FALSE) -> Intermediação monetária - depósitos à vista | I1020: =VLOOKUP(D1020,Base!$D:$F,3,FALSE) -> Caixas econômicas | J1020: =VLOOKUP(E1020,Base!$E:$F,2,FALSE) -> Caixas econômicas | K1020: 6423900 | L1020: =IFERROR(VLOOKUP($K1020,Base_Atividades!$E$1:$N$2398,MATCH(BancoAjustado!L$1,Base_Atividades!$E$1:$N$1,0),FALSE),0) -> 0 | M1020: =IFERROR(VLOOKUP($K1020,Base_Atividades!$E$1:$N$2398,MATCH(BancoAjustado!M$1,Base_Atividades!$E$1:$N$1,0),FALSE),0) -> 0 | N1020: =IFERROR(VLOOKUP($K1020,Base_Atividades!$E$1:$N$2398,MATCH(BancoAjustado!N$1,Base_Atividades!$E$1:$N$1,0),FALSE),0) -> 0
A1021: K | B1021: 64 | C1021: 642 | D1021: 64247 | E1021: 6424701 | F1021: =VLOOKUP(A1021,Base!$A:$F,6,FALSE) -> ATIVIDADES FINANCEIRAS, DE SEGUROS E SERVIÇOS RELACIONADOS | G1021: =VLOOKUP(B1021,Base!$B:$F,5,FALSE) -> ATIVIDADES DE SERVIÇOS FINANCEIROS | H1021: =VLOOKUP(C1021,Base!$C:$F,4,FALSE) -> Intermediação monetária - depósitos à vista | I1021: =VLOOKUP(D1021,Base!$D:$F,3,FALSE) -> Crédito cooperativo | J1021: =VLOOKUP(E1021,Base!$E:$F,2,FALSE) -> Bancos cooperativos | K1021: 6424701 | L1021: =IFERROR(VLOOKUP($K1021,Base_Atividades!$E$1:$N$2398,MATCH(BancoAjustado!L$1,Base_Atividades!$E$1:$N$1,0),FALSE),0) -> 0 | M1021: =IFERROR(VLOOKUP($K1021,Base_Atividades!$E$1:$N$2398,MATCH(BancoAjustado!M$1,Base_Atividades!$E$1:$N$1,0),FALSE),0) -> 0 | N1021: =IFERROR(VLOOKUP($K1021,Base_Atividades!$E$1:$N$2398,MATCH(BancoAjustado!N$1,Base_Atividades!$E$1:$N$1,0),FALSE),0) -> 0
A1022: K | B1022: 64 | C1022: 642 | D1022: 64247 | E1022: 6424702 | F1022: =VLOOKUP(A1022,Base!$A:$F,6,FALSE) -> ATIVIDADES FINANCEIRAS, DE SEGUROS E SERVIÇOS RELACIONADOS | G1022: =VLOOKUP(B1022,Base!$B:$F,5,FALSE) -> ATIVIDADES DE SERVIÇOS FINANCEIROS | H1022: =VLOOKUP(C1022,Base!$C:$F,4,FALSE) -> Intermediação monetária - depósitos à vista | I1022: =VLOOKUP(D1022,Base!$D:$F,3,FALSE) -> Crédito cooperativo | J1022: =VLOOKUP(E1022,Base!$E:$F,2,FALSE) -> Cooperativas centrais de crédito | K1022: 6424702 | L1022: =IFERROR(VLOOKUP($K1022,Base_Atividades!$E$1:$N$2398,MATCH(BancoAjustado!L$1,Base_Atividades!$E$1:$N$1,0),FALSE),0) -> 0 | M1022: =IFERROR(VLOOKUP($K1022,Base_Atividades!$E$1:$N$2398,MATCH(BancoAjustado!M$1,Base_Atividades!$E$1:$N$1,0),FALSE),0) -> 0 | N1022: =IFERROR(VLOOKUP($K1022,Base_Atividades!$E$1:$N$2398,MATCH(BancoAjustado!N$1,Base_Atividades!$E$1:$N$1,0),FALSE),0) -> 0
A1023: K | B1023: 64 | C1023: 642 | D1023: 64247 | E1023: 6424703 | F1023: =VLOOKUP(A1023,Base!$A:$F,6,FALSE) -> ATIVIDADES FINANCEIRAS, DE SEGUROS E SERVIÇOS RELACIONADOS | G1023: =VLOOKUP(B1023,Base!$B:$F,5,FALSE) -> ATIVIDADES DE SERVIÇOS FINANCEIROS | H1023: =VLOOKUP(C1023,Base!$C:$F,4,FALSE) -> Intermediação monetária - depósitos à vista | I1023: =VLOOKUP(D1023,Base!$D:$F,3,FALSE) -> Crédito cooperativo | J1023: =VLOOKUP(E1023,Base!$E:$F,2,FALSE) -> Cooperativas de crédito mútuo | K1023: 6424703 | L1023: =IFERROR(VLOOKUP($K1023,Base_Atividades!$E$1:$N$2398,MATCH(BancoAjustado!L$1,Base_Atividades!$E$1:$N$1,0),FALSE),0) -> 0 | M1023: =IFERROR(VLOOKUP($K1023,Base_Atividades!$E$1:$N$2398,MATCH(BancoAjustado!M$1,Base_Atividades!$E$1:$N$1,0),FALSE),0) -> 0 | N1023: =IFERROR(VLOOKUP($K1023,Base_Atividades!$E$1:$N$2398,MATCH(BancoAjustado!N$1,Base_Atividades!$E$1:$N$1,0),FALSE),0) -> 0
A1024: K | B1024: 64 | C1024: 642 | D1024: 64247 | E1024: 6424704 | F1024: =VLOOKUP(A1024,Base!$A:$F,6,FALSE) -> ATIVIDADES FINANCEIRAS, DE SEGUROS E SERVIÇOS RELACIONADOS | G1024: =VLOOKUP(B1024,Base!$B:$F,5,FALSE) -> ATIVIDADES DE SERVIÇOS FINANCEIROS | H1024: =VLOOKUP(C1024,Base!$C:$F,4,FALSE) -> Intermediação monetária - depósitos à vista | I1024: =VLOOKUP(D1024,Base!$D:$F,3,FALSE) -> Crédito cooperativo | J1024: =VLOOKUP(E1024,Base!$E:$F,2,FALSE) -> Cooperativas de crédito rural | K1024: 6424704 | L1024: =IFERROR(VLOOKUP($K1024,Base_Atividades!$E$1:$N$2398,MATCH(BancoAjustado!L$1,Base_Atividades!$E$1:$N$1,0),FALSE),0) -> 0 | M1024: =IFERROR(VLOOKUP($K1024,Base_Atividades!$E$1:$N$2398,MATCH(BancoAjustado!M$1,Base_Atividades!$E$1:$N$1,0),FALSE),0) -> 0 | N1024: =IFERROR(VLOOKUP($K1024,Base_Atividades!$E$1:$N$2398,MATCH(BancoAjustado!N$1,Base_Atividades!$E$1:$N$1,0),FALSE),0) -> 0
A1025: K | B1025: 64 | C1025: 643 | D1025: 64310 | E1025: 6431000 | F1025: =VLOOKUP(A1025,Base!$A:$F,6,FALSE) -> ATIVIDADES FINANCEIRAS, DE SEGUROS E SERVIÇOS RELACIONADOS | G1025: =VLOOKUP(B1025,Base!$B:$F,5,FALSE) -> ATIVIDADES DE SERVIÇOS FINANCEIROS | H1025: =VLOOKUP(C1025,Base!$C:$F,4,FALSE) -> Intermediação não monetária - outros instrumentos de captação | I1025: =VLOOKUP(D1025,Base!$D:$F,3,FALSE) -> Bancos múltiplos, sem carteira comercial | J1025: =VLOOKUP(E1025,Base!$E:$F,2,FALSE) -> Bancos múltiplos, sem carteira comercial | K1025: 6431000 | L1025: =IFERROR(VLOOKUP($K1025,Base_Atividades!$E$1:$N$2398,MATCH(BancoAjustado!L$1,Base_Atividades!$E$1:$N$1,0),FALSE),0) -> 0 | M1025: =IFERROR(VLOOKUP($K1025,Base_Atividades!$E$1:$N$2398,MATCH(BancoAjustado!M$1,Base_Atividades!$E$1:$N$1,0),FALSE),0) -> 0 | N1025: =IFERROR(VLOOKUP($K1025,Base_Atividades!$E$1:$N$2398,MATCH(BancoAjustado!N$1,Base_Atividades!$E$1:$N$1,0),FALSE),0) -> 0
A1026: K | B1026: 64 | C1026: 643 | D1026: 64328 | E1026: 6432800 | F1026: =VLOOKUP(A1026,Base!$A:$F,6,FALSE) -> ATIVIDADES FINANCEIRAS, DE SEGUROS E SERVIÇOS RELACIONADOS | G1026: =VLOOKUP(B1026,Base!$B:$F,5,FALSE) -> ATIVIDADES DE SERVIÇOS FINANCEIROS | H1026: =VLOOKUP(C1026,Base!$C:$F,4,FALSE) -> Intermediação não monetária - outros instrumentos de captação | I1026: =VLOOKUP(D1026,Base!$D:$F,3,FALSE) -> Bancos de investimento | J1026: =VLOOKUP(E1026,Base!$E:$F,2,FALSE) -> Bancos de investimento | K1026: 6432800 | L1026: =IFERROR(VLOOKUP($K1026,Base_Atividades!$E$1:$N$2398,MATCH(BancoAjustado!L$1,Base_Atividades!$E$1:$N$1,0),FALSE),0) -> 0 | M1026: =IFERROR(VLOOKUP($K1026,Base_Atividades!$E$1:$N$2398,MATCH(BancoAjustado!M$1,Base_Atividades!$E$1:$N$1,0),FALSE),0) -> 0 | N1026: =IFERROR(VLOOKUP($K1026,Base_Atividades!$E$1:$N$2398,MATCH(BancoAjustado!N$1,Base_Atividades!$E$1:$N$1,0),FALSE),0) -> 0
A1027: K | B1027: 64 | C1027: 643 | D1027: 64336 | E1027: 6433600 | F1027: =VLOOKUP(A1027,Base!$A:$F,6,FALSE) -> ATIVIDADES FINANCEIRAS, DE SEGUROS E SERVIÇOS RELACIONADOS | G1027: =VLOOKUP(B1027,Base!$B:$F,5,FALSE) -> ATIVIDADES DE SERVIÇOS FINANCEIROS | H1027: =VLOOKUP(C1027,Base!$C:$F,4,FALSE) -> Intermediação não monetária - outros instrumentos de captação | I1027: =VLOOKUP(D1027,Base!$D:$F,3,FALSE) -> Bancos de desenvolvimento | J1027: =VLOOKUP(E1027,Base!$E:$F,2,FALSE) -> Bancos de desenvolvimento | K1027: 6433600 | L1027: =IFERROR(VLOOKUP($K1027,Base_Atividades!$E$1:$N$2398,MATCH(BancoAjustado!L$1,Base_Atividades!$E$1:$N$1,0),FALSE),0) -> 0 | M1027: =IFERROR(VLOOKUP($K1027,Base_Atividades!$E$1:$N$2398,MATCH(BancoAjustado!M$1,Base_Atividades!$E$1:$N$1,0),FALSE),0) -> 0 | N1027: =IFERROR(VLOOKUP($K1027,Base_Atividades!$E$1:$N$2398,MATCH(BancoAjustado!N$1,Base_Atividades!$E$1:$N$1,0),FALSE),0) -> 0
A1028: K | B1028: 64 | C1028: 643 | D1028: 64344 | E1028: 6434400 | F1028: =VLOOKUP(A1028,Base!$A:$F,6,FALSE) -> ATIVIDADES FINANCEIRAS, DE SEGUROS E SERVIÇOS RELACIONADOS | G1028: =VLOOKUP(B1028,Base!$B:$F,5,FALSE) -> ATIVIDADES DE SERVIÇOS FINANCEIROS | H1028: =VLOOKUP(C1028,Base!$C:$F,4,FALSE) -> Intermediação não monetária - outros instrumentos de captação | I1028: =VLOOKUP(D1028,Base!$D:$F,3,FALSE) -> Agências de fomento | J1028: =VLOOKUP(E1028,Base!$E:$F,2,FALSE) -> Agências de fomento | K1028: 6434400 | L1028: =IFERROR(VLOOKUP($K1028,Base_Atividades!$E$1:$N$2398,MATCH(BancoAjustado!L$1,Base_Atividades!$E$1:$N$1,0),FALSE),0) -> 0 | M1028: =IFERROR(VLOOKUP($K1028,Base_Atividades!$E$1:$N$2398,MATCH(BancoAjustado!M$1,Base_Atividades!$E$1:$N$1,0),FALSE),0) -> 0 | N1028: =IFERROR(VLOOKUP($K1028,Base_Atividades!$E$1:$N$2398,MATCH(BancoAjustado!N$1,Base_Atividades!$E$1:$N$1,0),FALSE),0) -> 0
... A1294: R | B1294: 93 | C1294: 932 | D1294: 93298 | E1294: 9329899 | F1294: =VLOOKUP(A1294,Base!$A:$F,6,FALSE) -> ARTES, CULTURA, ESPORTE E RECREAÇÃO | G1294: =VLOOKUP(B1294,Base!$B:$F,5,FALSE) -> ATIVIDADES ESPORTIVAS E DE RECREAÇÃO E LAZER | H1294: =VLOOKUP(C1294,Base!$C:$F,4,FALSE) -> Atividades de recreação e lazer | I1294: =VLOOKUP(D1294,Base!$D:$F,3,FALSE) -> Atividades de recreação e lazer não especificadas anteriormente | J1294: =VLOOKUP(E1294,Base!$E:$F,2,FALSE) -> Outras atividades de recreação e lazer não especificadas anteriormente | K1294: 9329899 | L1294: =IFERROR(VLOOKUP($K1294,Base_Atividades!$E$1:$N$2398,MATCH(BancoAjustado!L$1,Base_Atividades!$E$1:$N$1,0),FALSE),0) -> 0 | M1294: =IFERROR(VLOOKUP($K1294,Base_Atividades!$E$1:$N$2398,MATCH(BancoAjustado!M$1,Base_Atividades!$E$1:$N$1,0),FALSE),0) -> 0 | N1294: =IFERROR(VLOOKUP($K1294,Base_Atividades!$E$1:$N$2398,MATCH(BancoAjustado!N$1,Base_Atividades!$E$1:$N$1,0),FALSE),0) -> 0
A1295: S | B1295: 94 | C1295: 941 | D1295: 94111 | E1295: 9411100 | F1295: =VLOOKUP(A1295,Base!$A:$F,6,FALSE) -> OUTRAS ATIVIDADES DE SERVIÇOS | G1295: =VLOOKUP(B1295,Base!$B:$F,5,FALSE) -> ATIVIDADES DE ORGANIZAÇÕES ASSOCIATIVAS | H1295: =VLOOKUP(C1295,Base!$C:$F,4,FALSE) -> Atividades de organizações associativas patronais, empresariais e profissionais | I1295: =VLOOKUP(D1295,Base!$D:$F,3,FALSE) -> Atividades de organizações associativas patronais e empresariais | J1295: =VLOOKUP(E1295,Base!$E:$F,2,FALSE) -> Atividades de organizações associativas patronais e empresariais | K1295: 9411100 | L1295: =IFERROR(VLOOKUP($K1295,Base_Atividades!$E$1:$N$2398,MATCH(BancoAjustado!L$1,Base_Atividades!$E$1:$N$1,0),FALSE),0) -> 0 | M1295: =IFERROR(VLOOKUP($K1295,Base_Atividades!$E$1:$N$2398,MATCH(BancoAjustado!M$1,Base_Atividades!$E$1:$N$1,0),FALSE),0) -> 0 | N1295: =IFERROR(VLOOKUP($K1295,Base_Atividades!$E$1:$N$2398,MATCH(BancoAjustado!N$1,Base_Atividades!$E$1:$N$1,0),FALSE),0) -> 0
...

Sheet Base
A1: Seção | B1: Divisão | C1: Grupo | D1: Classe | E1: Subclasse | F1: Denominação
A2: A | F2: AGRICULTURA, PECUÁRIA, PRODUÇÃO FLORESTAL, PESCA E AQUICULTURA
B3: 01 | F3: AGRICULTURA, PECUÁRIA E SERVIÇOS RELACIONADOS
C4: 011 | F4: Produção de lavouras temporárias
D5: 01113 | F5: Cultivo de cereais
E6: 0111301 | F6: Cultivo de arroz | G6: =A2 -> A | H6: =B3 -> 01 | I6: =C4 -> 011 | J6: =D5 -> 01113 | K6: =E6 -> 0111301
E7: 0111302 | F7: Cultivo de milho | G7: =IF(A7="",G6,A7) -> A | H7: =IF(B7="",H6,B7) -> 01 | I7: =IF(C7="",I6,C7) -> 011 | J7: =IF(D7="",J6,D7) -> 01113 | K7: =E7 -> 0111302
E8: 0111303 | F8: Cultivo de trigo | G8: =IF(A8="",G7,A8) -> A | H8: =IF(B8="",H7,B8) -> 01 | I8: =IF(C8="",I7,C8) -> 011 | J8: =IF(D8="",J7,D8) -> 01113 | K8: =E8 -> 0111303
E9: 0111399 | F9: Cultivo de outros cereais não especificados anteriormente | G9: =IF(A9="",G8,A9) -> A | H9: =IF(B9="",H8,B9) -> 01 | I9: =IF(C9="",I8,C9) -> 011 | J9: =IF(D9="",J8,D9) -> 01113 | K9: =E9 -> 0111399
D10: 01121 | F10: Cultivo de algodão herbáceo e de outras fibras de lavoura temporária | G10: =IF(A10="",G9,A10) -> A | H10: =IF(B10="",H9,B10) -> 01 | I10: =IF(C10="",I9,C10) -> 011 | J10: =IF(D10="",J9,D10) -> 01121 | K10: =E10
E11: 0112101 | F11: Cultivo de algodão herbáceo | G11: =IF(A11="",G10,A11) -> A | H11: =IF(B11="",H10,B11) -> 01 | I11: =IF(C11="",I10,C11) -> 011 | J11: =IF(D11="",J10,D11) -> 01121 | K11: =E11 -> 0112101
E12: 0112102 | F12: Cultivo de juta | G12: =IF(A12="",G11,A12) -> A | H12: =IF(B12="",H11,B12) -> 01 | I12: =IF(C12="",I11,C12) -> 011 | J12: =IF(D12="",J11,D12) -> 01121 | K12: =E12 -> 0112102
E13: 0112199 | F13: Cultivo de outras fibras de lavoura temporária não especificadas anteriormente | G13: =IF(A13="",G12,A13) -> A | H13: =IF(B13="",H12,B13) -> 01 | I13: =IF(C13="",I12,C13) -> 011 | J13: =IF(D13="",J12,D13) -> 01121 | K13: =E13 -> 0112199
D14: 01130 | F14: Cultivo de cana-de-açúcar | G14: =IF(A14="",G13,A14) -> A | H14: =IF(B14="",H13,B14) -> 01 | I14: =IF(C14="",I13,C14) -> 011 | J14: =IF(D14="",J13,D14) -> 01130 | K14: =E14
E15: 0113000 | F15: Cultivo de cana-de-açúcar | G15: =IF(A15="",G14,A15) -> A | H15: =IF(B15="",H14,B15) -> 01 | I15: =IF(C15="",I14,C15) -> 011 | J15: =IF(D15="",J14,D15) -> 01130 | K15: =E15 -> 0113000
D16: 01148 | F16: Cultivo de fumo | G16: =IF(A16="",G15,A16) -> A | H16: =IF(B16="",H15,B16) -> 01 | I16: =IF(C16="",I15,C16) -> 011 | J16: =IF(D16="",J15,D16) -> 01148 | K16: =E16
E17: 0114800 | F17: Cultivo de fumo | G17: =IF(A17="",G16,A17) -> A | H17: =IF(B17="",H16,B17) -> 01 | I17: =IF(C17="",I16,C17) -> 011 | J17: =IF(D17="",J16,D17) -> 01148 | K17: =E17 -> 0114800
D18: 01156 | F18: Cultivo de soja | G18: =IF(A18="",G17,A18) -> A | H18: =IF(B18="",H17,B18) -> 01 | I18: =IF(C18="",I17,C18) -> 011 | J18: =IF(D18="",J17,D18) -> 01156 | K18: =E18
E19: 0115600 | F19: Cultivo de soja | G19: =IF(A19="",G18,A19) -> A | H19: =IF(B19="",H18,B19) -> 01 | I19: =IF(C19="",I18,C19) -> 011 | J19: =IF(D19="",J18,D19) -> 01156 | K19: =E19 -> 0115600
D20: 01164 | F20: Cultivo de oleaginosas de lavoura temporária, exceto soja | G20: =IF(A20="",G19,A20) -> A | H20: =IF(B20="",H19,B20) -> 01 | I20: =IF(C20="",I19,C20) -> 011 | J20: =IF(D20="",J19,D20) -> 01164 | K20: =E20
E21: 0116401 | F21: Cultivo de amendoim | G21: =IF(A21="",G20,A21) -> A | H21: =IF(B21="",H20,B21) -> 01 | I21: =IF(C21="",I20,C21) -> 011 | J21: =IF(D21="",J20,D21) -> 01164 | K21: =E21 -> 0116401
E22: 0116402 | F22: Cultivo de girassol | G22: =IF(A22="",G21,A22) -> A | H22: =IF(B22="",H21,B22) -> 01 | I22: =IF(C22="",I21,C22) -> 011 | J22: =IF(D22="",J21,D22) -> 01164 | K22: =E22 -> 0116402
E23: 0116403 | F23: Cultivo de mamona | G23: =IF(A23="",G22,A23) -> A | H23: =IF(B23="",H22,B23) -> 01 | I23: =IF(C23="",I22,C23) -> 011 | J23: =IF(D23="",J22,D23) -> 01164 | K23: =E23 -> 0116403
E24: 0116499 | F24: Cultivo de outras oleaginosas de lavoura temporária não especificadas anteriormente | G24: =IF(A24="",G23,A24) -> A | H24: =IF(B24="",H23,B24) -> 01 | I24: =IF(C24="",I23,C24) -> 011 | J24: =IF(D24="",J23,D24) -> 01164 | K24: =E24 -> 0116499
D25: 01199 | F25: Cultivo de plantas de lavoura temporária não especificadas anteriormente | G25: =IF(A25="",G24,A25) -> A | H25: =IF(B25="",H24,B25) -> 01 | I25: =IF(C25="",I24,C25) -> 011 | J25: =IF(D25="",J24,D25) -> 01199 | K25: =E25
E26: 0119901 | F26: Cultivo de abacaxi | G26: =IF(A26="",G25,A26) -> A | H26: =IF(B26="",H25,B26) -> 01 | I26: =IF(C26="",I25,C26) -> 011 | J26: =IF(D26="",J25,D26) -> 01199 | K26: =E26 -> 0119901
E27: 0119902 | F27: Cultivo de alho | G27: =IF(A27="",G26,A27) -> A | H27: =IF(B27="",H26,B27) -> 01 | I27: =IF(C27="",I26,C27) -> 011 | J27: =IF(D27="",J26,D27) -> 01199 | K27: =E27 -> 0119902
E28: 0119903 | F28: Cultivo de batata-inglesa | G28: =IF(A28="",G27,A28) -> A | H28: =IF(B28="",H27,B28) -> 01 | I28: =IF(C28="",I27,C28) -> 011 | J28: =IF(D28="",J27,D28) -> 01199 | K28: =E28 -> 0119903
E29: 0119904 | F29: Cultivo de cebola | G29: =IF(A29="",G28,A29) -> A | H29: =IF(B29="",H28,B29) -> 01 | I29: =IF(C29="",I28,C29) -> 011 | J29: =IF(D29="",J28,D29) -> 01199 | K29: =E29 -> 0119904
E30: 0119905 | F30: Cultivo de feijão | G30: =IF(A30="",G29,A30) -> A | H30: =IF(B30="",H29,B30) -> 01 | I30: =IF(C30="",I29,C30) -> 011 | J30: =IF(D30="",J29,D30) -> 01199 | K30: =E30 -> 0119905
E31: 0119906 | F31: Cultivo de mandioca | G31: =IF(A31="",G30,A31) -> A | H31: =IF(B31="",H30,B31) -> 01 | I31: =IF(C31="",I30,C31) -> 011 | J31: =IF(D31="",J30,D31) -> 01199 | K31: =E31 -> 0119906
E32: 0119907 | F32: Cultivo de melão | G32: =IF(A32="",G31,A32) -> A | H32: =IF(B32="",H31,B32) -> 01 | I32: =IF(C32="",I31,C32) -> 011 | J32: =IF(D32="",J31,D32) -> 01199 | K32: =E32 -> 0119907
E33: 0119908 | F33: Cultivo de melancia | G33: =IF(A33="",G32,A33) -> A | H33: =IF(B33="",H32,B33) -> 01 | I33: =IF(C33="",I32,C33) -> 011 | J33: =IF(D33="",J32,D33) -> 01199 | K33: =E33 -> 0119908
E34: 0119909 | F34: Cultivo de tomate rasteiro | G34: =IF(A34="",G33,A34) -> A | H34: =IF(B34="",H33,B34) -> 01 | I34: =IF(C34="",I33,C34) -> 011 | J34: =IF(D34="",J33,D34) -> 01199 | K34: =E34 -> 0119909
E35: 0119999 | F35: Cultivo de outras plantas de lavoura temporária não especificadas anteriormente | G35: =IF(A35="",G34,A35) -> A | H35: =IF(B35="",H34,B35) -> 01 | I35: =IF(C35="",I34,C35) -> 011 | J35: =IF(D35="",J34,D35) -> 01199 | K35: =E35 -> 0119999
C36: 012 | F36: Horticultura e floricultura | G36: =IF(A36="",G35,A36) -> A | H36: =IF(B36="",H35,B36) -> 01 | I36: =IF(C36="",I35,C36) -> 012 | J36: =IF(D36="",J35,D36) -> 01199 | K36: =E36
D37: 01211 | F37: Horticultura | G37: =IF(A37="",G36,A37) -> A | H37: =IF(B37="",H36,B37) -> 01 | I37: =IF(C37="",I36,C37) -> 012 | J37: =IF(D37="",J36,D37) -> 01211 | K37: =E37
E38: 0121101 | F38: Horticultura, exceto morango | G38: =IF(A38="",G37,A38) -> A | H38: =IF(B38="",H37,B38) -> 01 | I38: =IF(C38="",I37,C38) -> 012 | J38: =IF(D38="",J37,D38) -> 01211 | K38: =E38 -> 0121101
E39: 0121102 | F39: Cultivo de morango | G39: =IF(A39="",G38,A39) -> A | H39: =IF(B39="",H38,B39) -> 01 | I39: =IF(C39="",I38,C39) -> 012 | J39: =IF(D39="",J38,D39) -> 01211 | K39: =E39 -> 0121102
D40: 01229 | F40: Cultivo de flores e plantas ornamentais | G40: =IF(A40="",G39,A40) -> A | H40: =IF(B40="",H39,B40) -> 01 | I40: =IF(C40="",I39,C40) -> 012 | J40: =IF(D40="",J39,D40) -> 01229 | K40: =E40
E41: 0122900 | F41: Cultivo de flores e plantas ornamentais | G41: =IF(A41="",G40,A41) -> A | H41: =IF(B41="",H40,B41) -> 01 | I41: =IF(C41="",I40,C41) -> 012 | J41: =IF(D41="",J40,D41) -> 01229 | K41: =E41 -> 0122900
C42: 013 | F42: Produção de lavouras permanentes | G42: =IF(A42="",G41,A42) -> A | H42: =IF(B42="",H41,B42) -> 01 | I42: =IF(C42="",I41,C42) -> 013 | J42: =IF(D42="",J41,D42) -> 01229 | K42: =E42
D43: 01318 | F43: Cultivo de laranja | G43: =IF(A43="",G42,A43) -> A | H43: =IF(B43="",H42,B43) -> 01 | I43: =IF(C43="",I42,C43) -> 013 | J43: =IF(D43="",J42,D43) -> 01318 | K43: =E43
E44: 0131800 | F44: Cultivo de laranja | G44: =IF(A44="",G43,A44) -> A | H44: =IF(B44="",H43,B44) -> 01 | I44: =IF(C44="",I43,C44) -> 013 | J44: =IF(D44="",J43,D44) -> 01318 | K44: =E44 -> 0131800
D45: 01326 | F45: Cultivo de uva | G45: =IF(A45="",G44,A45) -> A | H45: =IF(B45="",H44,B45) -> 01 | I45: =IF(C45="",I44,C45) -> 013 | J45: =IF(D45="",J44,D45) -> 01326 | K45: =E45
E46: 0132600 | F46: Cultivo de uva | G46: =IF(A46="",G45,A46) -> A | H46: =IF(B46="",H45,B46) -> 01 | I46: =IF(C46="",I45,C46) -> 013 | J46: =IF(D46="",J45,D46) -> 01326 | K46: =E46 -> 0132600
D47: 01334 | F47: Cultivo de frutas de lavoura permanente, exceto laranja e uva | G47: =IF(A47="",G46,A47) -> A | H47: =IF(B47="",H46,B47) -> 01 | I47: =IF(C47="",I46,C47) -> 013 | J47: =IF(D47="",J46,D47) -> 01334 | K47: =E47
E48: 0133401 | F48: Cultivo de açaí | G48: =IF(A48="",G47,A48) -> A | H48: =IF(B48="",H47,B48) -> 01 | I48: =IF(C48="",I47,C48) -> 013 | J48: =IF(D48="",J47,D48) -> 01334 | K48: =E48 -> 0133401
E49: 0133402 | F49: Cultivo de banana | G49: =IF(A49="",G48,A49) -> A | H49: =IF(B49="",H48,B49) -> 01 | I49: =IF(C49="",I48,C49) -> 013 | J49: =IF(D49="",J48,D49) -> 01334 | K49: =E49 -> 0133402
E50: 0133403 | F50: Cultivo de caju | G50: =IF(A50="",G49,A50) -> A | H50: =IF(B50="",H49,B50) -> 01 | I50: =IF(C50="",I49,C50) -> 013 | J50: =IF(D50="",J49,D50) -> 01334 | K50: =E50 -> 0133403
E51: 0133404 | F51: Cultivo de cítricos, exceto laranja | G51: =IF(A51="",G50,A51) -> A | H51: =IF(B51="",H50,B51) -> 01 | I51: =IF(C51="",I50,C51) -> 013 | J51: =IF(D51="",J50,D51) -> 01334 | K51: =E51 -> 0133404
E52: 0133405 | F52: Cultivo de coco-da-baía | G52: =IF(A52="",G51,A52) -> A | H52: =IF(B52="",H51,B52) -> 01 | I52: =IF(C52="",I51,C52) -> 013 | J52: =IF(D52="",J51,D52) -> 01334 | K52: =E52 -> 0133405
E53: 0133406 | F53: Cultivo de guaraná | G53: =IF(A53="",G52,A53) -> A | H53: =IF(B53="",H52,B53) -> 01 | I53: =IF(C53="",I52,C53) -> 013 | J53: =IF(D53="",J52,D53) -> 01334 | K53: =E53 -> 0133406
E54: 0133407 | F54: Cultivo de maçã | G54: =IF(A54="",G53,A54) -> A | H54: =IF(B54="",H53,B54) -> 01 | I54: =IF(C54="",I53,C54) -> 013 | J54: =IF(D54="",J53,D54) -> 01334 | K54: =E54 -> 0133407
E55: 0133408 | F55: Cultivo de mamão | G55: =IF(A55="",G54,A55) -> A | H55: =IF(B55="",H54,B55) -> 01 | I55: =IF(C55="",I54,C55) -> 013 | J55: =IF(D55="",J54,D55) -> 01334 | K55: =E55 -> 0133408
E56: 0133409 | F56: Cultivo de maracujá | G56: =IF(A56="",G55,A56) -> A | H56: =IF(B56="",H55,B56) -> 01 | I56: =IF(C56="",I55,C56) -> 013 | J56: =IF(D56="",J55,D56) -> 01334 | K56: =E56 -> 0133409
E57: 0133410 | F57: Cultivo de manga | G57: =IF(A57="",G56,A57) -> A | H57: =IF(B57="",H56,B57) -> 01 | I57: =IF(C57="",I56,C57) -> 013 | J57: =IF(D57="",J56,D57) -> 01334 | K57: =E57 -> 0133410
E58: 0133411 | F58: Cultivo de pêssego | G58: =IF(A58="",G57,A58) -> A | H58: =IF(B58="",H57,B58) -> 01 | I58: =IF(C58="",I57,C58) -> 013 | J58: =IF(D58="",J57,D58) -> 01334 | K58: =E58 -> 0133411
E59: 0133499 | F59: Cultivo de frutas de lavoura permanente não especificadas anteriormente | G59: =IF(A59="",G58,A59) -> A | H59: =IF(B59="",H58,B59) -> 01 | I59: =IF(C59="",I58,C59) -> 013 | J59: =IF(D59="",J58,D59) -> 01334 | K59: =E59 -> 0133499
D60: 01342 | F60: Cultivo de café | G60: =IF(A60="",G59,A60) -> A | H60: =IF(B60="",H59,B60) -> 01 | I60: =IF(C60="",I59,C60) -> 013 | J60: =IF(D60="",J59,D60) -> 01342 | K60: =E60
E61: 0134200 | F61: Cultivo de café | G61: =IF(A61="",G60,A61) -> A | H61: =IF(B61="",H60,B61) -> 01 | I61: =IF(C61="",I60,C61) -> 013 | J61: =IF(D61="",J60,D61) -> 01342 | K61: =E61 -> 0134200
D62: 01351 | F62: Cultivo de cacau | G62: =IF(A62="",G61,A62) -> A | H62: =IF(B62="",H61,B62) -> 01 | I62: =IF(C62="",I61,C62) -> 013 | J62: =IF(D62="",J61,D62) -> 01351 | K62: =E62
E63: 0135100 | F63: Cultivo de cacau | G63: =IF(A63="",G62,A63) -> A | H63: =IF(B63="",H62,B63) -> 01 | I63: =IF(C63="",I62,C63) -> 013 | J63: =IF(D63="",J62,D63) -> 01351 | K63: =E63 -> 0135100
D64: 01393 | F64: Cultivo de plantas de lavoura permanente não especificadas anteriormente | G64: =IF(A64="",G63,A64) -> A | H64: =IF(B64="",H63,B64) -> 01 | I64: =IF(C64="",I63,C64) -> 013 | J64: =IF(D64="",J63,D64) -> 01393 | K64: =E64
E65: 0139301 | F65: Cultivo de chá-da-índia | G65: =IF(A65="",G64,A65) -> A | H65: =IF(B65="",H64,B65) -> 01 | I65: =IF(C65="",I64,C65) -> 013 | J65: =IF(D65="",J64,D65) -> 01393 | K65: =E65 -> 0139301
E66: 0139302 | F66: Cultivo de erva-mate | G66: =IF(A66="",G65,A66) -> A | H66: =IF(B66="",H65,B66) -> 01 | I66: =IF(C66="",I65,C66) -> 013 | J66: =IF(D66="",J65,D66) -> 01393 | K66: =E66 -> 0139302
E67: 0139303 | F67: Cultivo de pimenta-do-reino | G67: =IF(A67="",G66,A67) -> A | H67: =IF(B67="",H66,B67) -> 01 | I67: =IF(C67="",I66,C67) -> 013 | J67: =IF(D67="",J66,D67) -> 01393 | K67: =E67 -> 0139303
E68: 0139304 | F68: Cultivo de plantas para condimento, exceto pimenta-do-reino | G68: =IF(A68="",G67,A68) -> A | H68: =IF(B68="",H67,B68) -> 01 | I68: =IF(C68="",I67,C68) -> 013 | J68: =IF(D68="",J67,D68) -> 01393 | K68: =E68 -> 0139304
E69: 0139305 | F69: Cultivo de dendê | G69: =IF(A69="",G68,A69) -> A | H69: =IF(B69="",H68,B69) -> 01 | I69: =IF(C69="",I68,C69) -> 013 | J69: =IF(D69="",J68,D69) -> 01393 | K69: =E69 -> 0139305
E70: 0139306 | F70: Cultivo de seringueira | G70: =IF(A70="",G69,A70) -> A | H70: =IF(B70="",H69,B70) -> 01 | I70: =IF(C70="",I69,C70) -> 013 | J70: =IF(D70="",J69,D70) -> 01393 | K70: =E70 -> 0139306
E71: 0139399 | F71: Cultivo de outras plantas de lavoura permanente não especificadas anteriormente | G71: =IF(A71="",G70,A71) -> A | H71: =IF(B71="",H70,B71) -> 01 | I71: =IF(C71="",I70,C71) -> 013 | J71: =IF(D71="",J70,D71) -> 01393 | K71: =E71 -> 0139399
C72: 014 | F72: Produção de sementes e mudas certificadas | G72: =IF(A72="",G71,A72) -> A | H72: =IF(B72="",H71,B72) -> 01 | I72: =IF(C72="",I71,C72) -> 014 | J72: =IF(D72="",J71,D72) -> 01393 | K72: =E72
D73: 01415 | F73: Produção de sementes certificadas | G73: =IF(A73="",G72,A73) -> A | H73: =IF(B73="",H72,B73) -> 01 | I73: =IF(C73="",I72,C73) -> 014 | J73: =IF(D73="",J72,D73) -> 01415 | K73: =E73
E74: 0141501 | F74: Produção de sementes certificadas, exceto de forrageiras para pasto | G74: =IF(A74="",G73,A74) -> A | H74: =IF(B74="",H73,B74) -> 01 | I74: =IF(C74="",I73,C74) -> 014 | J74: =IF(D74="",J73,D74) -> 01415 | K74: =E74 -> 0141501
E75: 0141502 | F75: Produção de sementes certificadas de forrageiras para formação de pasto | G75: =IF(A75="",G74,A75) -> A | H75: =IF(B75="",H74,B75) -> 01 | I75: =IF(C75="",I74,C75) -> 014 | J75: =IF(D75="",J74,D75) -> 01415 | K75: =E75 -> 0141502
D76: 01423 | F76: Produção de mudas e outras formas de propagação vegetal, certificadas | G76: =IF(A76="",G75,A76) -> A | H76: =IF(B76="",H75,B76) -> 01 | I76: =IF(C76="",I75,C76) -> 014 | J76: =IF(D76="",J75,D76) -> 01423 | K76: =E76
E77: 0142300 | F77: Produção de mudas e outras formas de propagação vegetal, certificadas | G77: =IF(A77="",G76,A77) -> A | H77: =IF(B77="",H76,B77) -> 01 | I77: =IF(C77="",I76,C77) -> 014 | J77: =IF(D77="",J76,D77) -> 01423 | K77: =E77 -> 0142300
C78: 015 | F78: Pecuária | G78: =IF(A78="",G77,A78) -> A | H78: =IF(B78="",H77,B78) -> 01 | I78: =IF(C78="",I77,C78) -> 015 | J78: =IF(D78="",J77,D78) -> 01423 | K78: =E78
D79: 01512 | F79: Criação de bovinos | G79: =IF(A79="",G78,A79) -> A | H79: =IF(B79="",H78,B79) -> 01 | I79: =IF(C79="",I78,C79) -> 015 | J79: =IF(D79="",J78,D79) -> 01512 | K79: =E79
E80: 0151201 | F80: Criação de bovinos para corte | G80: =IF(A80="",G79,A80) -> A | H80: =IF(B80="",H79,B80) -> 01 | I80: =IF(C80="",I79,C80) -> 015 | J80: =IF(D80="",J79,D80) -> 01512 | K80: =E80 -> 0151201
E81: 0151202 | F81: Criação de bovinos para leite | G81: =IF(A81="",G80,A81) -> A | H81: =IF(B81="",H80,B81) -> 01 | I81: =IF(C81="",I80,C81) -> 015 | J81: =IF(D81="",J80,D81) -> 01512 | K81: =E81 -> 0151202
E82: 0151203 | F82: Criação de bovinos, exceto para corte e leite | G82: =IF(A82="",G81,A82) -> A | H82: =IF(B82="",H81,B82) -> 01 | I82: =IF(C82="",I81,C82) -> 015 | J82: =IF(D82="",J81,D82) -> 01512 | K82: =E82 -> 0151203
D83: 01521 | F83: Criação de outros animais de grande porte | G83: =IF(A83="",G82,A83) -> A | H83: =IF(B83="",H82,B83) -> 01 | I83: =IF(C83="",I82,C83) -> 015 | J83: =IF(D83="",J82,D83) -> 01521 | K83: =E83
E84: 0152101 | F84: Criação de bufalinos | G84: =IF(A84="",G83,A84) -> A | H84: =IF(B84="",H83,B84) -> 01 | I84: =IF(C84="",I83,C84) -> 015 | J84: =IF(D84="",J83,D84) -> 01521 | K84: =E84 -> 0152101
E85: 0152102 | F85: Criação de equinos | G85: =IF(A85="",G84,A85) -> A | H85: =IF(B85="",H84,B85) -> 01 | I85: =IF(C85="",I84,C85) -> 015 | J85: =IF(D85="",J84,D85) -> 01521 | K85: =E85 -> 0152102
E86: 0152103 | F86: Criação de asininos e muares | G86: =IF(A86="",G85,A86) -> A | H86: =IF(B86="",H85,B86) -> 01 | I86: =IF(C86="",I85,C86) -> 015 | J86: =IF(D86="",J85,D86) -> 01521 | K86: =E86 -> 0152103
D87: 01539 | F87: Criação de caprinos e ovinos | G87: =IF(A87="",G86,A87) -> A | H87: =IF(B87="",H86,B87) -> 01 | I87: =IF(C87="",I86,C87) -> 015 | J87: =IF(D87="",J86,D87) -> 01539 | K87: =E87
E88: 0153901 | F88: Criação de caprinos | G88: =IF(A88="",G87,A88) -> A | H88: =IF(B88="",H87,B88) -> 01 | I88: =IF(C88="",I87,C88) -> 015 | J88: =IF(D88="",J87,D88) -> 01539 | K88: =E88 -> 0153901
E89: 0153902 | F89: Criação de ovinos, inclusive para produção de lã | G89: =IF(A89="",G88,A89) -> A | H89: =IF(B89="",H88,B89) -> 01 | I89: =IF(C89="",I88,C89) -> 015 | J89: =IF(D89="",J88,D89) -> 01539 | K89: =E89 -> 0153902
D90: 01547 | F90: Criação de suínos | G90: =IF(A90="",G89,A90) -> A | H90: =IF(B90="",H89,B90) -> 01 | I90: =IF(C90="",I89,C90) -> 015 | J90: =IF(D90="",J89,D90) -> 01547 | K90: =E90
E91: 0154700 | F91: Criação de suínos | G91: =IF(A91="",G90,A91) -> A | H91: =IF(B91="",H90,B91) -> 01 | I91: =IF(C91="",I90,C91) -> 015 | J91: =IF(D91="",J90,D91) -> 01547 | K91: =E91 -> 0154700
D92: 01555 | F92: Criação de aves | G92: =IF(A92="",G91,A92) -> A | H92: =IF(B92="",H91,B92) -> 01 | I92: =IF(C92="",I91,C92) -> 015 | J92: =IF(D92="",J91,D92) -> 01555 | K92: =E92
E93: 0155501 | F93: Criação de frangos para corte | G93: =IF(A93="",G92,A93) -> A | H93: =IF(B93="",H92,B93) -> 01 | I93: =IF(C93="",I92,C93) -> 015 | J93: =IF(D93="",J92,D93) -> 01555 | K93: =E93 -> 0155501
E94: 0155502 | F94: Produção de pintos de um dia | G94: =IF(A94="",G93,A94) -> A | H94: =IF(B94="",H93,B94) -> 01 | I94: =IF(C94="",I93,C94) -> 015 | J94: =IF(D94="",J93,D94) -> 01555 | K94: =E94 -> 0155502
E95: 0155503 | F95: Criação de outros galináceos, exceto para corte | G95: =IF(A95="",G94,A95) -> A | H95: =IF(B95="",H94,B95) -> 01 | I95: =IF(C95="",I94,C95) -> 015 | J95: =IF(D95="",J94,D95) -> 01555 | K95: =E95 -> 0155503
E96: 0155504 | F96: Criação de aves, exceto galináceos | G96: =IF(A96="",G95,A96) -> A | H96: =IF(B96="",H95,B96) -> 01 | I96: =IF(C96="",I95,C96) -> 015 | J96: =IF(D96="",J95,D96) -> 01555 | K96: =E96 -> 0155504
E97: 0155505 | F97: Produção de ovos | G97: =IF(A97="",G96,A97) -> A | H97: =IF(B97="",H96,B97) -> 01 | I97: =IF(C97="",I96,C97) -> 015 | J97: =IF(D97="",J96,D97) -> 01555 | K97: =E97 -> 0155505
D98: 01598 | F98: Criação de animais não especificados anteriormente | G98: =IF(A98="",G97,A98) -> A | H98: =IF(B98="",H97,B98) -> 01 | I98: =IF(C98="",I97,C98) -> 015 | J98: =IF(D98="",J97,D98) -> 01598 | K98: =E98
E99: 0159801 | F99: Apicultura | G99: =IF(A99="",G98,A99) -> A | H99: =IF(B99="",H98,B99) -> 01 | I99: =IF(C99="",I98,C99) -> 015 | J99: =IF(D99="",J98,D99) -> 01598 | K99: =E99 -> 0159801
E100: 0159802 | F100: Criação de animais de estimação | G100: =IF(A100="",G99,A100) -> A | H100: =IF(B100="",H99,B100) -> 01 | I100: =IF(C100="",I99,C100) -> 015 | J100: =IF(D100="",J99,D100) -> 01598 | K100: =E100 -> 0159802
...

Sheet Base_Atividades
A1: Seção | B1: Divisão | C1: Grupo | D1: Classe | E1: Subclasse | F1: Denominação | L1: e_obj4 | M1: com_agr | N1: com_min
A2: A | F2: AGRICULTURA, PECUÁRIA, PRODUÇÃO FLORESTAL, PESCA E AQUICULTURA
B3: 01 | F3: AGRICULTURA, PECUÁRIA E SERVIÇOS RELACIONADOS
C4: 011 | F4: Produção de lavouras temporárias
D5: 01113 | F5: Cultivo de cereais
E6: 0111301 | F6: Cultivo de arroz | G6: =A2 -> A | H6: =B3 -> 01 | I6: =C4 -> 011 | J6: =D5 -> 01113 | K6: =E6 -> 0111301 | L6: 1
E7: 0111302 | F7: Cultivo de milho | G7: =IF(A7="",G6,A7) -> A | H7: =IF(B7="",H6,B7) -> 01 | I7: =IF(C7="",I6,C7) -> 011 | J7: =IF(D7="",J6,D7) -> 01113 | K7: =E7 -> 0111302 | L7: 0 | M7: 1
E8: 0111303 | F8: Cultivo de trigo | G8: =IF(A8="",G7,A8) -> A | H8: =IF(B8="",H7,B8) -> 01 | I8: =IF(C8="",I7,C8) -> 011 | J8: =IF(D8="",J7,D8) -> 01113 | K8: =E8 -> 0111303 | L8: 0 | M8: 1
E9: 0111399 | F9: Cultivo de outros cereais não especificados anteriormente | G9: =IF(A9="",G8,A9) -> A | H9: =IF(B9="",H8,B9) -> 01 | I9: =IF(C9="",I8,C9) -> 011 | J9: =IF(D9="",J8,D9) -> 01113 | K9: =E9 -> 0111399 | L9: 1
D10: 01121 | F10: Cultivo de algodão herbáceo e de outras fibras de lavoura temporária | G10: =IF(A10="",G9,A10) -> A | H10: =IF(B10="",H9,B10) -> 01 | I10: =IF(C10="",I9,C10) -> 011 | J10: =IF(D10="",J9,D10) -> 01121 | K10: =E10
E11: 0112101 | F11: Cultivo de algodão herbáceo | G11: =IF(A11="",G10,A11) -> A | H11: =IF(B11="",H10,B11) -> 01 | I11: =IF(C11="",I10,C11) -> 011 | J11: =IF(D11="",J10,D11) -> 01121 | K11: =E11 -> 0112101 | L11: 0 | M11: 1
E12: 0112102 | F12: Cultivo de juta | G12: =IF(A12="",G11,A12) -> A | H12: =IF(B12="",H11,B12) -> 01 | I12: =IF(C12="",I11,C12) -> 011 | J12: =IF(D12="",J11,D12) -> 01121 | K12: =E12 -> 0112102 | L12: 1
E13: 0112199 | F13: Cultivo de outras fibras de lavoura temporária não especificadas anteriormente | G13: =IF(A13="",G12,A13) -> A | H13: =IF(B13="",H12,B13) -> 01 | I13: =IF(C13="",I12,C13) -> 011 | J13: =IF(D13="",J12,D13) -> 01121 | K13: =E13 -> 0112199 | L13: 1
D14: 01130 | F14: Cultivo de cana-de-açúcar | G14: =IF(A14="",G13,A14) -> A | H14: =IF(B14="",H13,B14) -> 01 | I14: =IF(C14="",I13,C14) -> 011 | J14: =IF(D14="",J13,D14) -> 01130 | K14: =E14
E15: 0113000 | F15: Cultivo de cana-de-açúcar | G15: =IF(A15="",G14,A15) -> A | H15: =IF(B15="",H14,B15) -> 01 | I15: =IF(C15="",I14,C15) -> 011 | J15: =IF(D15="",J14,D15) -> 01130 | K15: =E15 -> 0113000 | L15: 0 | M15: 1
D16: 01148 | F16: Cultivo de fumo | G16: =IF(A16="",G15,A16) -> A | H16: =IF(B16="",H15,B16) -> 01 | I16: =IF(C16="",I15,C16) -> 011 | J16: =IF(D16="",J15,D16) -> 01148 | K16: =E16
E17: 0114800 | F17: Cultivo de fumo | G17: =IF(A17="",G16,A17) -> A | H17: =IF(B17="",H16,B17) -> 01 | I17: =IF(C17="",I16,C17) -> 011 | J17: =IF(D17="",J16,D17) -> 01148 | K17: =E17 -> 0114800 | L17: 0
D18: 01156 | F18: Cultivo de soja | G18: =IF(A18="",G17,A18) -> A | H18: =IF(B18="",H17,B18) -> 01 | I18: =IF(C18="",I17,C18) -> 011 | J18: =IF(D18="",J17,D18) -> 01156 | K18: =E18
E19: 0115600 | F19: Cultivo de soja | G19: =IF(A19="",G18,A19) -> A | H19: =IF(B19="",H18,B19) -> 01 | I19: =IF(C19="",I18,C19) -> 011 | J19: =IF(D19="",J18,D19) -> 01156 | K19: =E19 -> 0115600 | L19: 0 | M19: 1
D20: 01164 | F20: Cultivo de oleaginosas de lavoura temporária, exceto soja | G20: =IF(A20="",G19,A20) -> A | H20: =IF(B20="",H19,B20) -> 01 | I20: =IF(C20="",I19,C20) -> 011 | J20: =IF(D20="",J19,D20) -> 01164 | K20: =E20
E21: 0116401 | F21: Cultivo de amendoim | G21: =IF(A21="",G20,A21) -> A | H21: =IF(B21="",H20,B21) -> 01 | I21: =IF(C21="",I20,C21) -> 011 | J21: =IF(D21="",J20,D21) -> 01164 | K21: =E21 -> 0116401 | L21: 1
E22: 0116402 | F22: Cultivo de girassol | G22: =IF(A22="",G21,A22) -> A | H22: =IF(B22="",H21,B22) -> 01 | I22: =IF(C22="",I21,C22) -> 011 | J22: =IF(D22="",J21,D22) -> 01164 | K22: =E22 -> 0116402 | L22: 1
E23: 0116403 | F23: Cultivo de mamona | G23: =IF(A23="",G22,A23) -> A | H23: =IF(B23="",H22,B23) -> 01 | I23: =IF(C23="",I22,C23) -> 011 | J23: =IF(D23="",J22,D23) -> 01164 | K23: =E23 -> 0116403 | L23: 1
E24: 0116499 | F24: Cultivo de outras oleaginosas de lavoura temporária não especificadas anteriormente | G24: =IF(A24="",G23,A24) -> A | H24: =IF(B24="",H23,B24) -> 01 | I24: =IF(C24="",I23,C24) -> 011 | J24: =IF(D24="",J23,D24) -> 01164 | K24: =E24 -> 0116499 | L24: 1
D25: 01199 | F25: Cultivo de plantas de lavoura temporária não especificadas anteriormente | G25: =IF(A25="",G24,A25) -> A | H25: =IF(B25="",H24,B25) -> 01 | I25: =IF(C25="",I24,C25) -> 011 | J25: =IF(D25="",J24,D25) -> 01199 | K25: =E25
E26: 0119901 | F26: Cultivo de abacaxi | G26: =IF(A26="",G25,A26) -> A | H26: =IF(B26="",H25,B26) -> 01 | I26: =IF(C26="",I25,C26) -> 011 | J26: =IF(D26="",J25,D26) -> 01199 | K26: =E26 -> 0119901 | L26: 1
E27: 0119902 | F27: Cultivo de alho | G27: =IF(A27="",G26,A27) -> A | H27: =IF(B27="",H26,B27) -> 01 | I27: =IF(C27="",I26,C27) -> 011 | J27: =IF(D27="",J26,D27) -> 01199 | K27: =E27 -> 0119902 | L27: 1
E28: 0119903 | F28: Cultivo de batata-inglesa | G28: =IF(A28="",G27,A28) -> A | H28: =IF(B28="",H27,B28) -> 01 | I28: =IF(C28="",I27,C28) -> 011 | J28: =IF(D28="",J27,D28) -> 01199 | K28: =E28 -> 0119903 | L28: 1
E29: 0119904 | F29: Cultivo de cebola | G29: =IF(A29="",G28,A29) -> A | H29: =IF(B29="",H28,B29) -> 01 | I29: =IF(C29="",I28,C29) -> 011 | J29: =IF(D29="",J28,D29) -> 01199 | K29: =E29 -> 0119904 | L29: 1
E30: 0119905 | F30: Cultivo de feijão | G30: =IF(A30="",G29,A30) -> A | H30: =IF(B30="",H29,B30) -> 01 | I30: =IF(C30="",I29,C30) -> 011 | J30: =IF(D30="",J29,D30) -> 01199 | K30: =E30 -> 0119905 | L30: 1
E31: 0119906 | F31: Cultivo de mandioca | G31: =IF(A31="",G30,A31) -> A | H31: =IF(B31="",H30,B31) -> 01 | I31: =IF(C31="",I30,C31) -> 011 | J31: =IF(D31="",J30,D31) -> 01199 | K31: =E31 -> 0119906 | L31: 1
E32: 0119907 | F32: Cultivo de melão | G32: =IF(A32="",G31,A32) -> A | H32: =IF(B32="",H31,B32) -> 01 | I32: =IF(C32="",I31,C32) -> 011 | J32: =IF(D32="",J31,D32) -> 01199 | K32: =E32 -> 0119907 | L32: 1
E33: 0119908 | F33: Cultivo de melancia | G33: =IF(A33="",G32,A33) -> A | H33: =IF(B33="",H32,B33) -> 01 | I33: =IF(C33="",I32,C33) -> 011 | J33: =IF(D33="",J32,D33) -> 01199 | K33: =E33 -> 0119908 | L33: 1
E34: 0119909 | F34: Cultivo de tomate rasteiro | G34: =IF(A34="",G33,A34) -> A | H34: =IF(B34="",H33,B34) -> 01 | I34: =IF(C34="",I33,C34) -> 011 | J34: =IF(D34="",J33,D34) -> 01199 | K34: =E34 -> 0119909 | L34: 1
E35: 0119999 | F35: Cultivo de outras plantas de lavoura temporária não especificadas anteriormente | G35: =IF(A35="",G34,A35) -> A | H35: =IF(B35="",H34,B35) -> 01 | I35: =IF(C35="",I34,C35) -> 011 | J35: =IF(D35="",J34,D35) -> 01199 | K35: =E35 -> 0119999 | L35: 1
C36: 012 | F36: Horticultura e floricultura | G36: =IF(A36="",G35,A36) -> A | H36: =IF(B36="",H35,B36) -> 01 | I36: =IF(C36="",I35,C36) -> 012 | J36: =IF(D36="",J35,D36) -> 01199 | K36: =E36
D37: 01211 | F37: Horticultura | G37: =IF(A37="",G36,A37) -> A | H37: =IF(B37="",H36,B37) -> 01 | I37: =IF(C37="",I36,C37) -> 012 | J37: =IF(D37="",J36,D37) -> 01211 | K37: =E37
E38: 0121101 | F38: Horticultura, exceto morango | G38: =IF(A38="",G37,A38) -> A | H38: =IF(B38="",H37,B38) -> 01 | I38: =IF(C38="",I37,C38) -> 012 | J38: =IF(D38="",J37,D38) -> 01211 | K38: =E38 -> 0121101 | L38: 1
E39: 0121102 | F39: Cultivo de morango | G39: =IF(A39="",G38,A39) -> A | H39: =IF(B39="",H38,B39) -> 01 | I39: =IF(C39="",I38,C39) -> 012 | J39: =IF(D39="",J38,D39) -> 01211 | K39: =E39 -> 0121102 | L39: 1
D40: 01229 | F40: Cultivo de flores e plantas ornamentais | G40: =IF(A40="",G39,A40) -> A | H40: =IF(B40="",H39,B40) -> 01 | I40: =IF(C40="",I39,C40) -> 012 | J40: =IF(D40="",J39,D40) -> 01229 | K40: =E40
E41: 0122900 | F41: Cultivo de flores e plantas ornamentais | G41: =IF(A41="",G40,A41) -> A | H41: =IF(B41="",H40,B41) -> 01 | I41: =IF(C41="",I40,C41) -> 012 | J41: =IF(D41="",J40,D41) -> 01229 | K41: =E41 -> 0122900 | L41: 1
C42: 013 | F42: Produção de lavouras permanentes | G42: =IF(A42="",G41,A42) -> A | H42: =IF(B42="",H41,B42) -> 01 | I42: =IF(C42="",I41,C42) -> 013 | J42: =IF(D42="",J41,D42) -> 01229 | K42: =E42
D43: 01318 | F43: Cultivo de laranja | G43: =IF(A43="",G42,A43) -> A | H43: =IF(B43="",H42,B43) -> 01 | I43: =IF(C43="",I42,C43) -> 013 | J43: =IF(D43="",J42,D43) -> 01318 | K43: =E43
E44: 0131800 | F44: Cultivo de laranja | G44: =IF(A44="",G43,A44) -> A | H44: =IF(B44="",H43,B44) -> 01 | I44: =IF(C44="",I43,C44) -> 013 | J44: =IF(D44="",J43,D44) -> 01318 | K44: =E44 -> 0131800 | L44: 1
D45: 01326 | F45: Cultivo de uva | G45: =IF(A45="",G44,A45) -> A | H45: =IF(B45="",H44,B45) -> 01 | I45: =IF(C45="",I44,C45) -> 013 | J45: =IF(D45="",J44,D45) -> 01326 | K45: =E45
E46: 0132600 | F46: Cultivo de uva | G46: =IF(A46="",G45,A46) -> A | H46: =IF(B46="",H45,B46) -> 01 | I46: =IF(C46="",I45,C46) -> 013 | J46: =IF(D46="",J45,D46) -> 01326 | K46: =E46 -> 0132600 | L46: 1
D47: 01334 | F47: Cultivo de frutas de lavoura permanente, exceto laranja e uva | G47: =IF(A47="",G46,A47) -> A | H47: =IF(B47="",H46,B47) -> 01 | I47: =IF(C47="",I46,C47) -> 013 | J47: =IF(D47="",J46,D47) -> 01334 | K47: =E47
E48: 0133401 | F48: Cultivo de açaí | G48: =IF(A48="",G47,A48) -> A | H48: =IF(B48="",H47,B48) -> 01 | I48: =IF(C48="",I47,C48) -> 013 | J48: =IF(D48="",J47,D48) -> 01334 | K48: =E48 -> 0133401 | L48: 1
E49: 0133402 | F49: Cultivo de banana | G49: =IF(A49="",G48,A49) -> A | H49: =IF(B49="",H48,B49) -> 01 | I49: =IF(C49="",I48,C49) -> 013 | J49: =IF(D49="",J48,D49) -> 01334 | K49: =E49 -> 0133402 | L49: 1
E50: 0133403 | F50: Cultivo de caju | G50: =IF(A50="",G49,A50) -> A | H50: =IF(B50="",H49,B50) -> 01 | I50: =IF(C50="",I49,C50) -> 013 | J50: =IF(D50="",J49,D50) -> 01334 | K50: =E50 -> 0133403 | L50: 1
E51: 0133404 | F51: Cultivo de cítricos, exceto laranja | G51: =IF(A51="",G50,A51) -> A | H51: =IF(B51="",H50,B51) -> 01 | I51: =IF(C51="",I50,C51) -> 013 | J51: =IF(D51="",J50,D51) -> 01334 | K51: =E51 -> 0133404 | L51: 1
E52: 0133405 | F52: Cultivo de coco-da-baía | G52: =IF(A52="",G51,A52) -> A | H52: =IF(B52="",H51,B52) -> 01 | I52: =IF(C52="",I51,C52) -> 013 | J52: =IF(D52="",J51,D52) -> 01334 | K52: =E52 -> 0133405 | L52: 1
E53: 0133406 | F53: Cultivo de guaraná | G53: =IF(A53="",G52,A53) -> A | H53: =IF(B53="",H52,B53) -> 01 | I53: =IF(C53="",I52,C53) -> 013 | J53: =IF(D53="",J52,D53) -> 01334 | K53: =E53 -> 0133406 | L53: 1
E54: 0133407 | F54: Cultivo de maçã | G54: =IF(A54="",G53,A54) -> A | H54: =IF(B54="",H53,B54) -> 01 | I54: =IF(C54="",I53,C54) -> 013 | J54: =IF(D54="",J53,D54) -> 01334 | K54: =E54 -> 0133407 | L54: 1
E55: 0133408 | F55: Cultivo de mamão | G55: =IF(A55="",G54,A55) -> A | H55: =IF(B55="",H54,B55) -> 01 | I55: =IF(C55="",I54,C55) -> 013 | J55: =IF(D55="",J54,D55) -> 01334 | K55: =E55 -> 0133408 | L55: 1
E56: 0133409 | F56: Cultivo de maracujá | G56: =IF(A56="",G55,A56) -> A | H56: =IF(B56="",H55,B56) -> 01 | I56: =IF(C56="",I55,C56) -> 013 | J56: =IF(D56="",J55,D56) -> 01334 | K56: =E56 -> 0133409 | L56: 1
E57: 0133410 | F57: Cultivo de manga | G57: =IF(A57="",G56,A57) -> A | H57: =IF(B57="",H56,B57) -> 01 | I57: =IF(C57="",I56,C57) -> 013 | J57: =IF(D57="",J56,D57) -> 01334 | K57: =E57 -> 0133410 | L57: 1
E58: 0133411 | F58: Cultivo de pêssego | G58: =IF(A58="",G57,A58) -> A | H58: =IF(B58="",H57,B58) -> 01 | I58: =IF(C58="",I57,C58) -> 013 | J58: =IF(D58="",J57,D58) -> 01334 | K58: =E58 -> 0133411 | L58: 1
E59: 0133499 | F59: Cultivo de frutas de lavoura permanente não especificadas anteriormente | G59: =IF(A59="",G58,A59) -> A | H59: =IF(B59="",H58,B59) -> 01 | I59: =IF(C59="",I58,C59) -> 013 | J59: =IF(D59="",J58,D59) -> 01334 | K59: =E59 -> 0133499 | L59: 1
D60: 01342 | F60: Cultivo de café | G60: =IF(A60="",G59,A60) -> A | H60: =IF(B60="",H59,B60) -> 01 | I60: =IF(C60="",I59,C60) -> 013 | J60: =IF(D60="",J59,D60) -> 01342 | K60: =E60
E61: 0134200 | F61: Cultivo de café | G61: =IF(A61="",G60,A61) -> A | H61: =IF(B61="",H60,B61) -> 01 | I61: =IF(C61="",I60,C61) -> 013 | J61: =IF(D61="",J60,D61) -> 01342 | K61: =E61 -> 0134200 | L61: 1
D62: 01351 | F62: Cultivo de cacau | G62: =IF(A62="",G61,A62) -> A | H62: =IF(B62="",H61,B62) -> 01 | I62: =IF(C62="",I61,C62) -> 013 | J62: =IF(D62="",J61,D62) -> 01351 | K62: =E62
E63: 0135100 | F63: Cultivo de cacau | G63: =IF(A63="",G62,A63) -> A | H63: =IF(B63="",H62,B63) -> 01 | I63: =IF(C63="",I62,C63) -> 013 | J63: =IF(D63="",J62,D63) -> 01351 | K63: =E63 -> 0135100 | L63: 1
D64: 01393 | F64: Cultivo de plantas de lavoura permanente não especificadas anteriormente | G64: =IF(A64="",G63,A64) -> A | H64: =IF(B64="",H63,B64) -> 01 | I64: =IF(C64="",I63,C64) -> 013 | J64: =IF(D64="",J63,D64) -> 01393 | K64: =E64
E65: 0139301 | F65: Cultivo de chá-da-índia | G65: =IF(A65="",G64,A65) -> A | H65: =IF(B65="",H64,B65) -> 01 | I65: =IF(C65="",I64,C65) -> 013 | J65: =IF(D65="",J64,D65) -> 01393 | K65: =E65 -> 0139301 | L65: 1
E66: 0139302 | F66: Cultivo de erva-mate | G66: =IF(A66="",G65,A66) -> A | H66: =IF(B66="",H65,B66) -> 01 | I66: =IF(C66="",I65,C66) -> 013 | J66: =IF(D66="",J65,D66) -> 01393 | K66: =E66 -> 0139302 | L66: 1
E67: 0139303 | F67: Cultivo de pimenta-do-reino | G67: =IF(A67="",G66,A67) -> A | H67: =IF(B67="",H66,B67) -> 01 | I67: =IF(C67="",I66,C67) -> 013 | J67: =IF(D67="",J66,D67) -> 01393 | K67: =E67 -> 0139303 | L67: 1
E68: 0139304 | F68: Cultivo de plantas para condimento, exceto pimenta-do-reino | G68: =IF(A68="",G67,A68) -> A | H68: =IF(B68="",H67,B68) -> 01 | I68: =IF(C68="",I67,C68) -> 013 | J68: =IF(D68="",J67,D68) -> 01393 | K68: =E68 -> 0139304 | L68: 1
E69: 0139305 | F69: Cultivo de dendê | G69: =IF(A69="",G68,A69) -> A | H69: =IF(B69="",H68,B69) -> 01 | I69: =IF(C69="",I68,C69) -> 013 | J69: =IF(D69="",J68,D69) -> 01393 | K69: =E69 -> 0139305 | L69: 1
E70: 0139306 | F70: Cultivo de seringueira | G70: =IF(A70="",G69,A70) -> A | H70: =IF(B70="",H69,B70) -> 01 | I70: =IF(C70="",I69,C70) -> 013 | J70: =IF(D70="",J69,D70) -> 01393 | K70: =E70 -> 0139306 | L70: 0
E71: 0139399 | F71: Cultivo de outras plantas de lavoura permanente não especificadas anteriormente | G71: =IF(A71="",G70,A71) -> A | H71: =IF(B71="",H70,B71) -> 01 | I71: =IF(C71="",I70,C71) -> 013 | J71: =IF(D71="",J70,D71) -> 01393 | K71: =E71 -> 0139399 | L71: 1
C72: 014 | F72: Produção de sementes e mudas certificadas | G72: =IF(A72="",G71,A72) -> A | H72: =IF(B72="",H71,B72) -> 01 | I72: =IF(C72="",I71,C72) -> 014 | J72: =IF(D72="",J71,D72) -> 01393 | K72: =E72
D73: 01415 | F73: Produção de sementes certificadas | G73: =IF(A73="",G72,A73) -> A | H73: =IF(B73="",H72,B73) -> 01 | I73: =IF(C73="",I72,C73) -> 014 | J73: =IF(D73="",J72,D73) -> 01415 | K73: =E73
E74: 0141501 | F74: Produção de sementes certificadas, exceto de forrageiras para pasto | G74: =IF(A74="",G73,A74) -> A | H74: =IF(B74="",H73,B74) -> 01 | I74: =IF(C74="",I73,C74) -> 014 | J74: =IF(D74="",J73,D74) -> 01415 | K74: =E74 -> 0141501 | L74: 1
E75: 0141502 | F75: Produção de sementes certificadas de forrageiras para formação de pasto | G75: =IF(A75="",G74,A75) -> A | H75: =IF(B75="",H74,B75) -> 01 | I75: =IF(C75="",I74,C75) -> 014 | J75: =IF(D75="",J74,D75) -> 01415 | K75: =E75 -> 0141502 | L75: 1
D76: 01423 | F76: Produção de mudas e outras formas de propagação vegetal, certificadas | G76: =IF(A76="",G75,A76) -> A | H76: =IF(B76="",H75,B76) -> 01 | I76: =IF(C76="",I75,C76) -> 014 | J76: =IF(D76="",J75,D76) -> 01423 | K76: =E76
E77: 0142300 | F77: Produção de mudas e outras formas de propagação vegetal, certificadas | G77: =IF(A77="",G76,A77) -> A | H77: =IF(B77="",H76,B77) -> 01 | I77: =IF(C77="",I76,C77) -> 014 | J77: =IF(D77="",J76,D77) -> 01423 | K77: =E77 -> 0142300 | L77: 1
C78: 015 | F78: Pecuária | G78: =IF(A78="",G77,A78) -> A | H78: =IF(B78="",H77,B78) -> 01 | I78: =IF(C78="",I77,C78) -> 015 | J78: =IF(D78="",J77,D78) -> 01423 | K78: =E78
D79: 01512 | F79: Criação de bovinos | G79: =IF(A79="",G78,A79) -> A | H79: =IF(B79="",H78,B79) -> 01 | I79: =IF(C79="",I78,C79) -> 015 | J79: =IF(D79="",J78,D79) -> 01512 | K79: =E79
E80: 0151201 | F80: Criação de bovinos para corte | G80: =IF(A80="",G79,A80) -> A | H80: =IF(B80="",H79,B80) -> 01 | I80: =IF(C80="",I79,C80) -> 015 | J80: =IF(D80="",J79,D80) -> 01512 | K80: =E80 -> 0151201 | L80: 0 | M80: 1
E81: 0151202 | F81: Criação de bovinos para leite | G81: =IF(A81="",G80,A81) -> A | H81: =IF(B81="",H80,B81) -> 01 | I81: =IF(C81="",I80,C81) -> 015 | J81: =IF(D81="",J80,D81) -> 01512 | K81: =E81 -> 0151202 | L81: 1
E82: 0151203 | F82: Criação de bovinos, exceto para corte e leite | G82: =IF(A82="",G81,A82) -> A | H82: =IF(B82="",H81,B82) -> 01 | I82: =IF(C82="",I81,C82) -> 015 | J82: =IF(D82="",J81,D82) -> 01512 | K82: =E82 -> 0151203 | L82: 0 | M82: 1
D83: 01521 | F83: Criação de outros animais de grande porte | G83: =IF(A83="",G82,A83) -> A | H83: =IF(B83="",H82,B83) -> 01 | I83: =IF(C83="",I82,C83) -> 015 | J83: =IF(D83="",J82,D83) -> 01521 | K83: =E83
E84: 0152101 | F84: Criação de bufalinos | G84: =IF(A84="",G83,A84) -> A | H84: =IF(B84="",H83,B84) -> 01 | I84: =IF(C84="",I83,C84) -> 015 | J84: =IF(D84="",J83,D84) -> 01521 | K84: =E84 -> 0152101 | L84: 0
E85: 0152102 | F85: Criação de equinos | G85: =IF(A85="",G84,A85) -> A | H85: =IF(B85="",H84,B85) -> 01 | I85: =IF(C85="",I84,C85) -> 015 | J85: =IF(D85="",J84,D85) -> 01521 | K85: =E85 -> 0152102 | L85: 0
E86: 0152103 | F86: Criação de asininos e muares | G86: =IF(A86="",G85,A86) -> A | H86: =IF(B86="",H85,B86) -> 01 | I86: =IF(C86="",I85,C86) -> 015 | J86: =IF(D86="",J85,D86) -> 01521 | K86: =E86 -> 0152103 | L86: 0
D87: 01539 | F87: Criação de caprinos e ovinos | G87: =IF(A87="",G86,A87) -> A | H87: =IF(B87="",H86,B87) -> 01 | I87: =IF(C87="",I86,C87) -> 015 | J87: =IF(D87="",J86,D87) -> 01539 | K87: =E87
E88: 0153901 | F88: Criação de caprinos | G88: =IF(A88="",G87,A88) -> A | H88: =IF(B88="",H87,B88) -> 01 | I88: =IF(C88="",I87,C88) -> 015 | J88: =IF(D88="",J87,D88) -> 01539 | K88: =E88 -> 0153901 | L88: 1
E89: 0153902 | F89: Criação de ovinos, inclusive para produção de lã | G89: =IF(A89="",G88,A89) -> A | H89: =IF(B89="",H88,B89) -> 01 | I89: =IF(C89="",I88,C89) -> 015 | J89: =IF(D89="",J88,D89) -> 01539 | K89: =E89 -> 0153902 | L89: 1
D90: 01547 | F90: Criação de suínos | G90: =IF(A90="",G89,A90) -> A | H90: =IF(B90="",H89,B90) -> 01 | I90: =IF(C90="",I89,C90) -> 015 | J90: =IF(D90="",J89,D90) -> 01547 | K90: =E90
E91: 0154700 | F91: Criação de suínos | G91: =IF(A91="",G90,A91) -> A | H91: =IF(B91="",H90,B91) -> 01 | I91: =IF(C91="",I90,C91) -> 015 | J91: =IF(D91="",J90,D91) -> 01547 | K91: =E91 -> 0154700 | L91: 1
D92: 01555 | F92: Criação de aves | G92: =IF(A92="",G91,A92) -> A | H92: =IF(B92="",H91,B92) -> 01 | I92: =IF(C92="",I91,C92) -> 015 | J92: =IF(D92="",J91,D92) -> 01555 | K92: =E92
E93: 0155501 | F93: Criação de frangos para corte | G93: =IF(A93="",G92,A93) -> A | H93: =IF(B93="",H92,B93) -> 01 | I93: =IF(C93="",I92,C93) -> 015 | J93: =IF(D93="",J92,D93) -> 01555 | K93: =E93 -> 0155501 | L93: 1
E94: 0155502 | F94: Produção de pintos de um dia | G94: =IF(A94="",G93,A94) -> A | H94: =IF(B94="",H93,B94) -> 01 | I94: =IF(C94="",I93,C94) -> 015 | J94: =IF(D94="",J93,D94) -> 01555 | K94: =E94 -> 0155502 | L94: 1
E95: 0155503 | F95: Criação de outros galináceos, exceto para corte | G95: =IF(A95="",G94,A95) -> A | H95: =IF(B95="",H94,B95) -> 01 | I95: =IF(C95="",I94,C95) -> 015 | J95: =IF(D95="",J94,D95) -> 01555 | K95: =E95 -> 0155503 | L95: 1
E96: 0155504 | F96: Criação de aves, exceto galináceos | G96: =IF(A96="",G95,A96) -> A | H96: =IF(B96="",H95,B96) -> 01 | I96: =IF(C96="",I95,C96) -> 015 | J96: =IF(D96="",J95,D96) -> 01555 | K96: =E96 -> 0155504 | L96: 1
E97: 0155505 | F97: Produção de ovos | G97: =IF(A97="",G96,A97) -> A | H97: =IF(B97="",H96,B97) -> 01 | I97: =IF(C97="",I96,C97) -> 015 | J97: =IF(D97="",J96,D97) -> 01555 | K97: =E97 -> 0155505 | L97: 1
D98: 01598 | F98: Criação de animais não especificados anteriormente | G98: =IF(A98="",G97,A98) -> A | H98: =IF(B98="",H97,B98) -> 01 | I98: =IF(C98="",I97,C98) -> 015 | J98: =IF(D98="",J97,D98) -> 01598 | K98: =E98
E99: 0159801 | F99: Apicultura | G99: =IF(A99="",G98,A99) -> A | H99: =IF(B99="",H98,B99) -> 01 | I99: =IF(C99="",I98,C99) -> 015 | J99: =IF(D99="",J98,D99) -> 01598 | K99: =E99 -> 0159801 | L99: 1
E100: 0159802 | F100: Criação de animais de estimação | G100: =IF(A100="",G99,A100) -> A | H100: =IF(B100="",H99,B100) -> 01 | I100: =IF(C100="",I99,C100) -> 015 | J100: =IF(D100="",J99,D100) -> 01598 | K100: =E100 -> 0159802 | L100: 1
...
